Workbook

Sheet README
B2: Buy or Build
B3: Consolidation in Indian consumer brands: evidence workbook
B4: Consumer Brands Research · Prepared by Priyanshi Paul · October 2026
B6: Headline results (live, linked to the model)
B7: Price paid at completion, 90.5% of Minimalist | C7: =Sensitivity!B14 -> 2706.45 | D7: HUL completion filing, 2025-04-21 (see Conflicts #1)
B8: Risk-adjusted build-equivalent cost (base) | C8: =Sensitivity!B10 -> 3723.1639 | D8: PV of burn ÷ P(success) + cost of delay
B9: Buy all-in cost, 100% (base) | C9: =Sensitivity!B11 -> 3233.45 | D9: Price + last 9.5% + transaction + integration − cash acquired
B10: Breakeven price for 90.5% (base) | C10: =Sensitivity!B12 -> 3196.1639 | D10: Above this, buying stops making sense
B11: Headroom vs price paid (base) | C11: =Sensitivity!B13 -> 489.71389 | D11: Positive = buying was cheaper
B12: P(success) of an in-house build (base) | C12: =Sensitivity!B7 -> 0.11 | D12: Laplace estimate from 0 of 7 FMCG digital-first builds (Base_Rates c)
B13: Years from decision to ₹347 Cr (base) | C13: =Sensitivity!B5 -> 7 | D13: Bull 5 · Bear 9
B15: Dataset at a glance
B16: Acquisitions (Tab A) | C16: =COUNTA(Tab_A_Buy!A2:A1000) -> 31 | D16: Listed parents, 2020 onward
B17: In-house builds (Tab B) | C17: =COUNTA(Tab_B_Build!A2:A1000) -> 29 | D17: Core (2020+) and calibration (pre-2020) rows
B18: Sources logged | C18: =COUNTA(Source_Log!A2:A1000) -> 216 | D18: Exchange filings and annual reports first
B19: AI claims checked | C19: =COUNTA(Claims_Log!A2:A1000) -> 72 | D19: Every figure recalled from model memory, verified against a source
B20: Annual-report brand mentions tracked | C20: =COUNTA(AR_Mentions!A2:A1000) -> 203 | D20: Brand × parent × FY rows, FY20–FY26
B22: Tabs (click to open)
B24: Source tiers
B26: Confidence rules
B27: High | C27: A T1 source with a verbatim quote.
B28: Medium | C28: A T2 source, or two independent T3 sources that agree.
B29: Low | C29: A single T3 source, or a derived or inferred value.
B30: UNCONFIRMED | C30: Value left blank with the reason in notes; never estimated silently.
B32: Conventions
B33: 1,000 | C33: Blue font = hard-coded input (edit these on Assumptions)
B34: formula output | C34: Yellow fill = live formula output
B35: ₹ Cr · ISO dates | C35: All money in ₹ crore; FY24 = Apr 2023 to Mar 2024; revenue basis recorded per row
B36: Conflicts | C36: Resolved in favour of the most authoritative source; every figure and what it measures is kept

Sheet Tab_A_Buy
A1: route | B1: row_type | C1: parent | D1: brand | E1: category | F1: year_start | G1: consideration_inr_cr | H1: stake_pct | I1: deal_structure | J1: revenue_inr_cr | K1: revenue_fy | L1: revenue_basis | M1: revenue_multiple | N1: what_was_acquired | O1: vocab_rationale | P1: status_today | Q1: status_evidence | R1: source_url | S1: source_ids | T1: date_accessed | U1: confidence | V1: notes
A2: Buy | B2: core | C2: Hindustan Unilever Ltd | D2: Minimalist (Uprising Science Pvt Ltd) | E2: BPC-Skincare | F2: 2025 | G2: 2706.45 | H2: 90.5 | I2: outright_majority | J2: 347 | K2: FY24 | L2: turnover as stated in Reg 30 annexure ("turnover of the Business"); not labelled ops vs total income | M2: =IF(AND(ISNUMBER(G2),ISNUMBER(H2),ISNUMBER(J2),N(J2)>0),G2/(H2/100)/J2,"") -> 8.6183069 | N2: COHORT_EQUITY | O2: HUL already sold skincare (Pond's, Lakme, Glow & Lovely); Minimalist brought the actives-led, digital-first premium cohort HUL lacked ('higher growth demand spaces'). | P2: Subsidiary since 2025-04-21; founders Mohit & Rahul Yadav continue to run it; balance 9.5% to be acquired | Q2: S002: 'Uprising and its subsidiaries have become subsidiaries of the Company'; S006: 'The current Minimalist team led by Mohit and Rahul will continue to operate the business' | R2: https://www.bseindia.com/xml-data/corpfiling/AttachHis/7ecb9005-13d6-4ea3-8cad-7fe05bffd54e.pdf | S2: S007;S002;S006 | T2: 2026-10-10 | U2: High | V2: Announced 2025-01-22 (S007 p.1: 'secondary buyout for a cash consideration of INR 2670 crores at a pre-money Enterprise Valuation of INR 2955 crores (subject to adjustments as set out in the SPSA) and a primary infusion of INR 45 crores'); CCI approval 2025-03-17; completed 2025-04-21 for total cash consideration 'INR 2,706,44,95,728' incl. primary (S002 p.1) = INR 2,706.45 Cr (press rounds down to 2,706.44). consideration_inr_cr uses the completion figure. Turnover S007 p.3: 'FY 2021-22: INR 103 Crores / FY 2022-23: INR 184 Crores / FY 2023-24: INR 347 Crores'; ARR >INR 500 Cr (Dec-24 quarter, unaudited). D5 check: '~347 Cr turnover' CONFIRMED against the filing; filing calls it 'turnover', Entrackr calls it 'revenue' (same number). Remaining 9.5% 'with eventual acquisition'; press release: 'path to acquire the balance stake in two years'. Multiple on EV basis = 2955/347 = 8.5x. See conflicts.md (2,670 vs 2,706.44 vs 2,955).
A3: Buy | B3: core | C3: Hindustan Unilever Ltd | D3: OZiva (Zywie Ventures Pvt Ltd) | E3: Wellness-Nutrition&Supplements | F3: 2023 | G3: 264.28 | H3: 51 | I3: outright_majority | J3: 124.17 | K3: FY22 | L3: revenue_from_operations ('turnover from operations') | M3: =IF(AND(ISNUMBER(G3),ISNUMBER(H3),ISNUMBER(J3),N(J3)>0),G3/(H3/100)/J3,"") -> 4.1732792 | N3: CATEGORY_ENTRY | O3: Filing calls it entry into Health & Wellbeing (VMS/plant protein), a category where HUL had no supplements business (Horlicks/Boost are health food drinks). | P3: Wholly owned since 2026-02-13; balance 49% bought for INR 824 Cr; FY25 turnover INR 257.67 Cr (2.1x FY22) | Q3: S003: 'completed the acquisition' of 'the balance stake of 49%... for a total consideration of INR 824 Crores'; S009: 'turnover from operations of INR 257.67 Crores for the financial year 2024-2025' | R3: https://www.bseindia.com/xml-data/corpfiling/AttachHis/a9bee337-d3ac-428e-b3eb-9fe3bf141942.pdf | S3: S008;S005;S009;S003;S001 | T3: 2026-10-10 | U3: High | V3: Announced 2022-12-08 (S008): agreement to acquire 100% in 2 tranches; 'Total consideration for acquisition of the first tranche: INR 264.28 Crores'; 51% first tranche, 'Balance 49.00%... after the expiry of a period of 3 years'. Completed first tranche 2023-01-11 (S005), so year_start=2023 (announced 2022). Turnover S008 p.2: 'turnover from operations of INR 124.17 Crores for the financial year 2021-2022'. Second tranche approved 2026-02-12 (S009) and completed 2026-02-13 (S003) at INR 824 Cr for 49%: implied 100% value ~INR 1,682 Cr vs ~INR 518 Cr at first tranche (264.28/0.51, post-money incl. primary). deal_structure = outright_majority (51% at first completion; contracted top-up noted, not reclassified per D6).
A4: Buy | B4: core | C4: Hindustan Unilever Ltd | D4: Wellbeing Nutrition (Nutritionalab Pvt Ltd) | E4: Wellness-Nutrition&Supplements | F4: 2023 | G4: 70 | H4: 19.8 | I4: minority_no_path | J4: 19.4 | K4: FY22 | L4: turnover as stated in Reg 30 annexure; not labelled ops vs total income | M4: =IF(AND(ISNUMBER(G4),ISNUMBER(H4),ISNUMBER(J4),N(J4)>0),G4/(H4/100)/J4,"") -> 18.223472 | N4: CATEGORY_ENTRY | O4: Same filing language as OZiva: 'Strategic investment to enter the Health & Wellbeing category'. | P4: EXITED: HUL sold entire 19.8% to USV Pvt Ltd for ~INR 307 Cr (completed 2026-03-04); FY25 revenue from ops INR 118.48 Cr | Q4: S011: 'completed the sale of its entire shareholding in Nutritionalab, for a total consideration of approx. INR 307 Crores'; S009 Annexure 2: 'revenue from operations of Nutritionalab... for the financial year 2024-25 is INR 118.48 crores' | R4: https://bseindia.com/xml-data/corpfiling/AttachHis/52af87d5-25a4-45c8-aad3-78626bd1a474.pdf | S4: S001;S012;S009;S011 | T4: 2026-10-10 | U4: High | V4: Announced 2022-12-08 (S001 p.3: 'INR 70.00 Crores for the acquisition of proposed stake'; 'agreed to acquire 19.8% shareholding'); completed 2023-01-04 (S012). Turnover S001 p.3: FY22 19.40 / FY21 5.33 / FY20 2.14 (INR Cr). Accounted as a joint venture under the equity method (S009). deal_structure = minority_no_path (added in D12): a 19.8% stake with no disclosed option or schedule to increase; minority_with_path needs rights to increase, and none were found. Arguably an investment, not an acquisition; kept as a core row because it shows the exit route (bought 70, sold ~307 = ~4.4x in ~3 years).
A5: Buy | B5: core | C5: ITC Ltd | D5: Yoga Bar (Sproutlife Foods Pvt Ltd) | E5: Food-Snacks&Bars | F5: 2023 | G5: 175 | H5: 39.42 | I5: staged_to_control | J5: 68 | K5: FY22 | L5: turnover as stated in Reg 30 enclosure; not labelled ops vs total income | M5: =IF(AND(ISNUMBER(G5),ISNUMBER(H5),ISNUMBER(J5),N(J5)>0),G5/(H5/100)/J5,"") -> 6.5284866 | N5: COHORT_EQUITY | O5: ITC already sold packaged snacks/biscuits; filing says the deal adds 'innovative food products for health conscious consumers' via a digital-first brand, a cohort ITC lacked. | P5: Wholly owned since 2026-09-28; subsidiary (board control) from 2026-04-01; turnover FY26 INR 452 Cr (6.6x FY22) | Q5: S031: 'the Company now holds 100% of the entire share capital of Sproutlife'; 'Cost of acquisition... ~ ₹ 645 crores'; 'turnover (based on audited accounts) 2025-26 INR 452 crores 2024-25 INR 200 crores 2023-24 INR 108 crores' | R5: https://www.bseindia.com/xml-data/corpfiling/AttachHis/2919b815-f54c-41e2-894d-65994e51f770.pdf | S5: S013;S014;S015;S016;S017;S030;S031 | T5: 2026-10-10 | U5: High | V5: Term sheet 2023-01-17 (S013); SSPA executed 2023-04-19 (S014); first tranche completed 2023-05-04: 'aggregate consideration of Rs. 175 crores... aggregates 39.42%' (S015). Plan (S013 Annexure): 175 Cr for 39.4% + 80 Cr primary by Mar-2025 to reach 47.5%, balance to 100% on pre-agreed valuation criteria. Path - all stakes are stated 'on a fully diluted basis'; no undiluted figure is disclosed. 44.74% and 47.50% are NOT separate deals: they are the two primary-infusion steps of the ~Rs 80 Cr agreed up-front in the term sheet (S013 Annexure: 'Acquisition of 47.5%... Initial Investment of Rs 175 crores... for acquisition of 39.4%... Further infusion of Rs 80 crores will be made through primary subscription, in one or more tranches, by 31st March, 2025... based on pre-agreed pre-money valuation'). Step 1, 2024-03-11 (S016): 2,356 CCPS for '~ Rs. 50 crores' -> 'aggregates 44.74%... (on a fully diluted basis) at a total investment of ~ Rs. 225 crores'. Step 2, 2024-09-25 (S017): 1,413 CCPS for '~ Rs. 30 crores' -> 'aggregates ~ 47.50%... at a total investment of ~ Rs. 255 crores'. CONTROL AT SUB-50% (the study's note): on 2026-04-01, still at ~47.50%, ITC 'acquired the right to nominate majority of the Directors on the Board of Sproutlife' under the 2023 SHA, so Sproutlife became a subsidiary under Section 2(87)(i) (S030). The 52.5% = 100% - 47.50%: bought 2026-09-28 from the remaining holders by secondary purchase for '~ ₹ 645 crores', taking ITC 'from ~ 47.50% to 100%' (S031). Total cost of 100% ~INR 900 Cr. Implied 100% value at first tranche ~444 Cr (post-money) vs ~1,358 Cr at the final tranche (645/0.525). Turnover S013 p.4: '2021-22 Rs 68 crores 2020-21 Rs 39 crores 2019-20 Rs 32 crores'.
A6: Buy | B6: core | C6: ITC Ltd | D6: Mother Sparsh (Mother Sparsh Baby Care Pvt Ltd) | E6: BPC-Baby&Mother | F6: 2025 | G6: 50.6 | H6: 12.97 | I6: staged_to_control | J6: 58.7 | K6: FY24 | L6: turnover as stated in Reg 30 enclosure; not labelled ops vs total income | M6: =IF(AND(ISNUMBER(G6),ISNUMBER(H6),ISNUMBER(J6),N(J6)>0),G6/(H6/100)/J6,"") -> 6.6461852 | N6: CATEGORY_ENTRY | O6: Filings frame it as access to baby care / D2C ayurvedic personal care; no ITC baby-care brand is named in any filing (INFERRED: ITC's personal care brands are adult soaps, fragrances, skincare). | P6: Associate at 49.32% (2026-05-19); FY26 turnover INR 138.5 Cr; balance to 100% by Q1 FY2027-28 (extendable to Q1 FY2028-29) | Q6: S032: 'shareholding in Mother Sparsh has increased from 39.47% to 49.32%'; 'turnover 2025-26 INR 138.5 crores 2024-25 INR 80.9 crores *' | R6: https://www.bseindia.com/xml-data/corpfiling/AttachHis/eb24ba27-a9eb-42ca-b4dd-29312337bdcf.pdf | S6: S020;S021;S032;S025;S026;S027;S028;S029;S018;S019 | T6: 2026-10-10 | U6: High | V6: Row = the CONTROL deal: SSPA executed 2025-04-17 to acquire the balance 73.5% (S020); first tranche completed 2025-05-21: 'aggregate consideration of approx. Rs 50.6 crores', stake 26.50% -> 39.47% (S021), so stake_pct = 12.97 incremental. Plan (S020 p.16): ~Rs 81 Cr in two tranches to reach up to 49.3% (total investment ~Rs 126 Cr), then balance to 100% by Q1 FY2027-28 on pre-agreed criteria. Second tranche ~Rs 30 Cr -> 49.32% on 2026-05-19 (S032). PRIOR MINORITY ENTRY (not counted in this row): 16% agreed 2021-11-26 for '~ Rs 20 crores' (S025), completed in two tranches 2021-12 (8.70%, S026) and 2022-03-15 (16%, S027); to 22% for ~Rs 13.50 Cr (2022-10-27, S028/S029); to 26.50% for ~Rs 11.54 Cr (2023-06-27, S018/S019). Multiple caveat: 50.6 Cr includes primary subscription, so implied value is post-money. Turnover restated: FY25 Rs 99.6 Cr (S021) vs Rs 80.9 Cr restated (S032). See conflicts.md.
A7: Buy | B7: core | C7: ITC Ltd | D7: 24 Mantra Organic (Sresta Natural Bioproducts Pvt Ltd) | E7: Food-Staples&Organic | F7: 2025 | G7: 472.5 | H7: 100 | I7: full_100 | J7: 306.1 | K7: FY24 | L7: consolidated turnover as stated in Reg 30 annexure; not labelled ops vs total income | M7: =IF(AND(ISNUMBER(G7),ISNUMBER(H7),ISNUMBER(J7),N(J7)>0),G7/(H7/100)/J7,"") -> 1.5436132 | N7: COHORT_EQUITY | O7: ITC was already in staples (filing: deal will 'fortify ITC's presence'); 24 Mantra brought the organic shopper and US Indian-diaspora franchise (~50% revenue international). Tie-break over CAPABILITY (27,500-farmer organic sourcing base). | P7: Wholly owned from 2025-06-13; amalgamated into ITC Ltd (NCLT-sanctioned, appointed date 2025-06-13), so no longer a separate entity | Q7: S022: 'SNBPL has become a wholly owned subsidiary of the Company'; S033: 'Scheme of Amalgamation of Sresta Natural Bioproducts Private Limited... with the Company... has been sanctioned' | R7: https://www.bseindia.com/xml-data/corpfiling/AttachHis/eb24ba27-a9eb-42ca-b4dd-29312337bdcf.pdf | S7: S020;S022;S033 | T7: 2026-10-10 | U7: High | V7: Announced 2025-04-17 (S020): 'Consideration of up to Rs 472.50 crores on a cash-free debt-free basis... comprising Rs 400 crores payable upfront at Closing and up to Rs 72.50 crores payable in the next 24 months'. Presentation: 'Additional Founders Consideration of up to Rs. 72.5 cr... basis pre-agreed criteria'; founder Raj Seelam stays 2 years. Completed 2025-06-13 (S022). consideration_inr_cr = the maximum 472.5 (upfront 400 + earn-out); upfront-only multiple = 400/306.1 = 1.31x. Turnover S020 p.4 (consolidated): '2023-24 Rs 306.1 crores 2022-23 Rs 327.3 crores 2021-22 Rs 326.7 crores' - flat-to-declining before the deal. Earn-out not counted as FOUNDER_TEAM: price is 1.5x revenue, so people are not the primary asset (D6).
A8: Buy | B8: core | C8: ITC Ltd | D8: Prasuma (Ample Foods Pvt Ltd) | E8: Food-Frozen&ReadyToCook | F8: 2025 | G8: 131 | H8: 43.75 | I8: staged_to_control | J8: 116 | K8: FY24 | L8: revenue_from_operations (AFPL consolidated, sales to third parties incl. sales to MSPL) | M8: =IF(AND(ISNUMBER(G8),ISNUMBER(H8),ISNUMBER(J8),N(J8)>0),G8/(H8/100)/J8,"") -> 2.5812808 | N8: CAPABILITY | O8: ITC already had frozen foods (Master Chef, 2019); release cites 'Prasuma's strength in manufacturing and innovation' and first-to-market products (momos, baos) to build a 'full stack' portfolio. Judgement call vs REVENUE_SCALE. | P8: Associate at 43.75%; next secondary (~Rs 56 Cr to 62.5%) due by Apr 2027; 100% by 2028-06-30 | Q8: S024: 'shareholding in AFPL aggregates 43.75% of its share capital'; no later Reg 30 update found on BSE to 2026-10-10 | R8: https://www.bseindia.com/xml-data/corpfiling/AttachHis/a8097585-aeec-49ae-9525-cebf604d1aaf.pdf | S8: S023;S024 | T8: 2026-10-10 | U8: High | V8: Announced 2025-02-06 (S023); first tranche completed 2025-04-04: 'aggregate consideration of approx. Rs 131 crores... aggregates 43.75%' (S024). Plan (S023 Annexure): ~Rs 131 Cr for 43.8%; ~Rs 56 Cr secondary to 62.5% by Apr-2027; balance 37.5% of AFPL plus 100% of Meat and Spice Pvt Ltd (MSPL, owns ~43% of AFPL) by 2028-06-30 on pre-agreed criteria. Revenue: AFPL FY24 Rs 116 Cr used (stake is in AFPL); 'Target Business' (AFPL+MSPL+Chao Chao) FY24 Rs 131 Cr -> multiple 2.29x on that basis. ARR ~Rs 200 Cr (trailing 3 months, Feb-2025 release). Category 'Food-Frozen&ReadyToCook' added to the taxonomy: no existing bucket fits frozen/chilled meats and momos.
A9: Buy | B9: core | C9: Tata Consumer Products Ltd | D9: Soulfull (Kottaram Agro Foods Pvt Ltd) | E9: Food-Snacks&Bars | F9: 2021 | G9: 155.8 | H9: 100 | I9: full_100 | J9: 39.38 | K9: FY20 | L9: turnover as stated in Reg 30 annexure; not labelled ops vs total income | M9: =IF(AND(ISNUMBER(G9),ISNUMBER(H9),ISNUMBER(J9),N(J9)>0),G9/(H9/100)/J9,"") -> 3.956323 | N9: CATEGORY_ENTRY | O9: Filing: deal is in line with TCPL's 'strategic intent of entering into new adjacent categories'; TCPL had no breakfast cereals or millet snacks. | P9: Renamed Tata Consumer Soulfull, then amalgamated into Tata Consumer Products Ltd (scheme effective 2024-09-01); brand continues as Tata Soulfull | Q9: S044: 'has now been re-named to Tata Consumer Soulfull'; S042 headline: 'Scheme Of Amalgamation Of Nourishco Beverages Limited (NCBL), Tata Smartfoodz Limited (TSFL) And Tata Consumer Soulfull...'; 'the Effective Date of the Scheme is September 1, 2024' | R9: https://www.bseindia.com/xml-data/corpfiling/AttachHis/6b5c78ca-543a-4181-8f13-c0b10991f345.pdf | S9: S034;S035;S042;S044 | T9: 2026-10-10 | U9: High | V9: Announced 2021-02-02 (S034): 'Consideration of INR 155.8 cr. In addition, the promoters are entitled to a contingent consideration, which is payable upon the business achieving certain operational and financial milestones over a period of 5 years.' Completed 2021-02-20 (S035). Turnover S034 p.3: 2019-20 INR 39.38 Cr; 2018-19 INR 21.58 Cr (OCR reads '2L58'); 2017-18 INR 11.08 Cr; net worth 31-Mar-2020 INR -6.26 Cr. Contingent consideration amount UNCONFIRMED: not disclosed. Post-deal Soulfull revenue UNCONFIRMED: not separately disclosed after amalgamation.
A10: Buy | B10: core | C10: Tata Consumer Products Ltd | D10: Ching's Secret / Smith & Jones (Capital Foods Pvt Ltd) | E10: Food-Ethnic&Condiments | F10: 2024 | G10: 3825 | H10: 75 | I10: outright_majority | J10: 705.5 | K10: FY23 | L10: revenue_from_operations | M10: =IF(AND(ISNUMBER(G10),ISNUMBER(H10),ISNUMBER(J10),N(J10)>0),G10/(H10/100)/J10,"") -> 7.2289157 | N10: CATEGORY_ENTRY | O10: Filing: 'entering into new adjacent high growth/ attractive margin categories'; TCPL (tea, coffee, salt, pulses) had no sauces, chutneys or Desi-Chinese condiments. | P10: Subsidiary; stake 80% after buying 5% from Wildflower Private Trust on 2026-09-01; 20% still to be acquired (3-year window from 2024-02-01) | Q10: S038: 'the Company now holds 27,95,533 equity shares... (representing 80% of the paid-up equity share capital of Capital Foods)' | R10: https://www.bseindia.com/xml-data/corpfiling/AttachHis/4c77fffc-daff-4dad-8633-13be1e459dfe.pdf | S10: S036;S037;S038;S043 | T10: 2026-10-10 | U10: Low | V10: Announced 2024-01-12 (S036): 'Enterprise value on no cash/no debt basis for 100% of the Target Company is INR 5,100 crores'; 75% upfront, balance 25% within 3 years. Completed 75% on 2024-02-01 (S037). consideration_inr_cr 3,825 is DERIVED (75% x INR 5,100 Cr EV): the equity cash paid for 75% is not in the Reg 30 filing, hence Low confidence under the rules; EV, stake and revenue are all T1. Multiple = EV/FY23 revenue = 7.2x. Revenue S036 p.4: 'Revenue from operations: FY 2022-23 Rs. 705.5 crores FY 2021-22 Rs. 574.2 crores FY 2020-21 Rs. 666.7 crores'; FY24 estimated 'approximately Rs. 750 to 770 crores' (S036 p.2). UNCONFIRMED: equity consideration paid for 75% (try TCPL FY24 annual report business-combination note); price of the 2026 5% top-up (BW Retail World S043: 'did not disclose the value').
A11: Buy | B11: core | C11: Tata Consumer Products Ltd | D11: Organic India (Organic India Pvt Ltd) | E11: Wellness-Nutrition&Supplements | F11: 2024 | G11: 1900 | H11: 99.99 | I11: full_100 | J11: 324.4 | K11: FY23 | L11: revenue_from_operations (consolidated) | M11: =IF(AND(ISNUMBER(G11),ISNUMBER(H11),ISNUMBER(J11),N(J11)>0),G11/(H11/100)/J11,"") -> 5.8575525 | N11: CATEGORY_ENTRY | O11: Filing: 'entering into new adjacent... categories' and 'will enable creation of health and wellness platform'; TCPL sold tea but not herbal supplements. Herbal infusions overlap TCPL tea, so COHORT_EQUITY is the runner-up. | P11: Wholly owned subsidiary since 2024-12-13 (99.99% from 2024-04-16) | Q11: S041: 'completed the acquisition of the remaining 8,750 equity shares... thereby making Organic India a wholly owned subsidiary of the Company' | R11: https://www.bseindia.com/xml-data/corpfiling/AttachHis/28441e71-335d-47a6-a86e-2bff25286d57.pdf | S11: S039;S040;S041 | T11: 2026-10-10 | U11: High | V11: Announced 2024-01-12 (S039): 'Enterprise value on no cash/no debt basis for 100% of the Target Company is Rs. 1,900 crores along with an additional earnout for the shareholders linked to FY2025-26 audited financials'. Seller: Fabindia Ltd. Completed 99.99% on 2024-04-16 (S040); remaining 8,750 shares 2024-12-13 (S041). consideration_inr_cr = disclosed EV (equity value not disclosed); earn-out amount UNCONFIRMED. Revenue S039 p.4: 'Revenue from operations (consolidated) FY22-23 Rs. 324.4 crores FY21-22 Rs. 361.8 crores FY20-21 Rs. 394.8 crores' - declining before the deal; FY24 estimated 'approximately Rs. 360 to 370 crores'. deal_structure full_100: 99.99% at first completion.
A12: Buy | B12: core | C12: Marico Ltd | D12: Beardo (Zed Lifestyle Pvt Ltd) | E12: BPC-MensGrooming | F12: 2020 | H12: 55 | I12: full_100 | J12: 78.5 | K12: FY20 | L12: turnover as stated in Reg 30 annexure (INR 78,49,85,170); not labelled ops vs total income | M12: =IF(AND(ISNUMBER(G12),ISNUMBER(H12),ISNUMBER(J12),N(J12)>0),G12/(H12/100)/J12,"") | N12: COHORT_EQUITY | O12: Marico already sold men's styling (Set Wet, Parachute Advansed Men - INFERRED, not in filing); Beardo brought the young, online beard-grooming cohort. The 2020 step-up itself is about 'complete control'. | P12: Wholly owned since 2020-06-30; FY25 turnover INR 214.17 Cr (2.7x FY20); business being moved into Marico Ltd via voluntary liquidation of Zed Lifestyle (announced 2026-01-27) | Q12: S064: 'Zed's financial details... Turnover 214.17 1.98%' (contribution to consolidated); 'Distribution of business undertaking of Zed on a going concern basis' | R12: https://www.bseindia.com/xml-data/corpfiling/AttachHis/9bdee60f-06e1-4486-a933-6c890b79602a.pdf | S12: S045;S064;S063 | T12: 2026-10-10 | U12: High | V12: Row = the 2020 control step: 'The Company has now acquired the balance equity stake of 55%' on 2020-06-30, holding 45% since March 2017 (S045). The 2017 entry is pre-2020; it could be a calibration row in Tab A. consideration_inr_cr UNCONFIRMED: 'pre-money enterprise valuation has not been disclosed herein due to reasons of confidentiality' (S045); press also reports 'undisclosed sum'. Turnover S045 p.3: FY20 INR 78.50 Cr; FY19 INR 48.24 Cr; FY18 INR 22.66 Cr. deal_structure full_100 because holding reached 100% at this completion (55% bought on top of 45%).
A13: Buy | B13: core | C13: Marico Ltd | D13: Just Herbs (Apcos Naturals Pvt Ltd) | E13: BPC-Skincare | F13: 2021 | H13: 52.38 | I13: outright_majority | J13: 17.25 | K13: FY21 | L13: turnover as stated in later Reg 30 annexure (FY21 INR 17.25 Cr; 'approx. revenue' INR 17.5 Cr unaudited at signing) | M13: =IF(AND(ISNUMBER(G13),ISNUMBER(H13),ISNUMBER(J13),N(J13)>0),G13/(H13/100)/J13,"") | N13: COHORT_EQUITY | O13: Marico had personal care; filing says the deal lets it participate 'in the premium, natural and ayurvedic beauty segment' and the D2C channel, a cohort its mass brands lacked. | P13: Wholly owned since 2024-09-17 (balance 40% for up to INR 70 Cr); FY24 turnover INR 96.03 Cr (5.6x FY21) | Q13: S049: 'Aggregate consideration of upto Rs. 70 Crores towards acquisition of balance 40% equity stake'; 'FY 2023 - 24 96.03'; S050: 'the transaction has been completed today' | R13: https://www.bseindia.com/xml-data/corpfiling/AttachHis/b14ca7a2-bf6b-4ee2-be75-9db8bae2c8f4.pdf | S13: S046;S047;S048;S049;S050 | T13: 2026-10-10 | U13: High | V13: Signed 2021-07-14 (S046): 60% via equity + CCPS; 52.4% by 2021-07-31 (subsidiary), balance 7.6% by 2023-03-31. Path: 52.38% -> 56.52% (2022-07-04, S047) -> 60% (2022-11-11, 'Rs. 9.99 crores for... additional equity stake of 3.48%', S048) -> 100% (2024-09-17, up to Rs 70 Cr for 40%, S049/S050). consideration_inr_cr UNCONFIRMED: first-tranche price not disclosed ('pre-money enterprise valuation has not been disclosed herein due to reasons of confidentiality'). DERIVED, not used: 9.99/0.0348 implies ~INR 287 Cr for 100% at the 2021 agreed pre-money valuation (~16x FY21 turnover) - treat with caution, tranche may include a different primary/secondary mix. Final 40% at up to 70 Cr implies ~175 Cr for 100% in 2024 (1.8x FY24 turnover) - lower than the 2021-agreed valuation. year_start=2021 (first completion by 2021-07-31).
A14: Buy | B14: core | C14: Marico Ltd | D14: True Elements (HW Wellness Solutions Pvt Ltd) | E14: Food-Snacks&Bars | F14: 2022 | H14: 53.98 | I14: outright_majority | J14: 54.3 | K14: FY22 | L14: turnover as stated in Reg 30 annexure (unaudited at the time) | M14: =IF(AND(ISNUMBER(G14),ISNUMBER(H14),ISNUMBER(J14),N(J14)>0),G14/(H14/100)/J14,"") | N14: COHORT_EQUITY | O14: Marico already sold breakfast (Saffola Oats - INFERRED, not in filing); filing says the deal expands its 'presence in the healthy foods segment' with a digital-first brand, i.e. the online health-food cohort. | P14: Wholly owned since 2025-10-17 (balance 46.02% for up to INR 138 Cr); FY25 turnover INR 164.38 Cr (3.0x FY22) | Q14: S052: 'Aggregate consideration of upto Rs. 138 Crores towards acquisition of balance 46.02%'; 'FY 2024 - 25 164.38'; S053: 'completed the aforesaid acquisition on October 17, 2025... True Elements has become a wholly owned subsidiary' | R14: https://www.bseindia.com/xml-data/corpfiling/AttachHis/27472172-f501-43b4-bfea-2d22eda5b637.pdf | S14: S051;S052;S053 | T14: 2026-10-10 | U14: High | V14: Completed 2022-05-23 (S051): 'acquired 53.98% of the paid-up share capital of HW Wellness and it has accordingly become a subsidiary'. consideration_inr_cr UNCONFIRMED: 'mutually agreed pre-money enterprise valuation... has not been disclosed herein due to reasons of confidentiality'. Turnover S051: FY22 54.3 (unaudited), FY21 36.3, FY20 16.5 (INR Cr). Balance 46.02% at up to 138 Cr implies ~300 Cr for 100% in 2025 (1.8x FY25 turnover). Storyboard18 headline 'Marico acquires 100% stake in True Elements for Rs 138 crore' (T3, seen via search, NOT saved; not relied on) misstates it: 138 Cr bought the remaining 46.02%, not 100%.
A15: Buy | B15: core | C15: Marico Ltd | D15: Plix (Satiya Nutraceuticals Pvt Ltd) | E15: Wellness-Nutrition&Supplements | F15: 2023 | G15: 369.01 | H15: 58 | I15: staged_to_control | J15: 106.43 | K15: FY23 | L15: turnover as stated in Reg 30 annexure; later filings call it consolidated turnover | M15: =IF(AND(ISNUMBER(G15),ISNUMBER(H15),ISNUMBER(J15),N(J15)>0),G15/(H15/100)/J15,"") -> 5.9778647 | N15: CATEGORY_ENTRY | O15: Filing: deal expands 'presence in the rapidly growing Health & Wellness category' (plant-based supplements/ACV gummies), where Marico had no material revenue (INFERRED: Saffola's wellness extensions were small). | P15: Subsidiary at 84.09% (2026-10-05, INR 1,012.03 Cr for 24.09%); FY26 consolidated turnover INR 864.31 Cr (8.1x FY23); last 14.09% due July 2027 | Q15: S058: 'Consideration of INR 1,012.03 Crores towards current tranche of acquisition of 24.09% stake'; 'FY 2025 - 26 864.31'; 'aggregate consideration for acquisition of 84.09% stake... stands at INR 1,392.07 Crores' | R15: https://www.bseindia.com/xml-data/corpfiling/AttachHis/32224d77-4090-4b97-9c64-a9b3319a3b5e.pdf | S15: S054;S055;S056;S057;S058 | T15: 2026-10-10 | U15: High | V15: Signed and first tranche completed 2023-07-26 (S054): 32.75% 'and requisite majority control over the Board composition/total voting rights', i.e. subsidiary from day one; 'Aggregate Consideration of upto Rs. 369.01 Crores towards acquisition of 58%'. consideration/stake = the contracted 58% package (first-tranche price alone not disclosed). Path: 51.20% (2023-11-30; +2% from founders for Rs 11.03 Cr, package now 60% for Rs 380.04 Cr, S055/S056); 60% (2025-05-31, S056); agreement amended 2025-12-17 to change timing of the 40% (S057); 84.09% (2026-10-05, S058); remaining 14.09% 'will be acquired in July 2027' for 'up to INR 592 Crores and additional consideration subject to milestones' (S058). Implied 100% value: ~636 Cr (2023) vs ~4,201 Cr (2026 tranche, 1012.03/0.2409). Turnover: FY21 10.92, FY22 41.58, FY23 106.43, FY24 155.32, FY25 432.84, FY26 864.31 (INR Cr). deal_structure staged_to_control: first tranche 32.75% (<=50%) with contracted tranches to majority, even though board control came at once.
A16: Buy | B16: core | C16: Marico Ltd | D16: Cosmix (Cosmix Wellness Pvt Ltd) | E16: Wellness-Nutrition&Supplements | F16: 2026 | G16: 225.67 | H16: 60 | I16: outright_majority | J16: 50.93 | K16: FY25 | L16: turnover 'Calculated as per Indian GAAP' (Reg 30 annexure) | M16: =IF(AND(ISNUMBER(G16),ISNUMBER(H16),ISNUMBER(J16),N(J16)>0),G16/(H16/100)/J16,"") -> 7.3849728 | N16: COHORT_EQUITY | O16: Marico was already in wellness via Plix; filing cites 'a digital-first functional wellness brand with a distinct and compelling proposition', i.e. another consumer cohort, not a new category. | P16: Subsidiary at 60% since 2026-02-05; Marico has a right to buy the rest after FY29 | Q16: S060: 'transaction has been completed on February 5, 2026 and consequently Cosmix Wellness has become a subsidiary' | R16: https://www.bseindia.com/xml-data/corpfiling/AttachHis/01fbc9b3-3e17-4de2-8d46-4228c8de2550.pdf | S16: S059;S060 | T16: 2026-10-10 | U16: High | V16: Signed 2026-02-04 (S059): 'Aggregate consideration of Rs. 225.67 crores towards acquisition of 60%' via secondary buy-out from founders; 'right to acquire the remaining stake in Cosmix Wellness after completion of FY29'. Completed 2026-02-05 (S060). Turnover: FY25 50.93, FY24 24.32, FY23 5.39 (INR Cr, Indian GAAP); 'Last 6 months ARR as per IndAS (Aug 2025 to Jan 2026): ~Rs. 100 crores'. Memory said 2025 completion (C014): actual is 2026. Remaining-stake right is an option, not a committed schedule; noted, not reclassified.
A17: Buy | B17: core | C17: Marico Ltd | D17: 4700BC (Zea Maize Pvt Ltd) | E17: Food-Snacks&Bars | F17: 2026 | G17: 226.83 | H17: 93.27 | I17: outright_majority | J17: 98.66 | K17: FY25 | L17: turnover as stated in Reg 30 annexure; not labelled ops vs total income | M17: =IF(AND(ISNUMBER(G17),ISNUMBER(H17),ISNUMBER(J17),N(J17)>0),G17/(H17/100)/J17,"") -> 2.4650027 | N17: COHORT_EQUITY | O17: Marico already sold healthy snacks (True Elements); filing cites 'a gourmet snacking brand with a differentiated premium positioning', i.e. the premium/gourmet snacking cohort. | P17: Subsidiary at 93.27% since 2026-01-29; founder retains a stake; Marico can buy it after 3 years | Q17: S062: 'the aforesaid transaction has been completed on January 29, 2026 and consequently Zea Maize has become a subsidiary' | R17: https://www.bseindia.com/xml-data/corpfiling/AttachHis/1e497d48-0c27-4c5b-811c-7658d2bfbf12.pdf | S17: S061;S062;S063 | T17: 2026-10-10 | U17: High | V17: NEW (not in the lead list). Signed 2026-01-26 (S061): 'Aggregate consideration of up to Rs. 226.83 Crores towards acquisition of 93.27%' bought from PVR INOX Ltd, the listed former parent, so this is listed-to-listed and the brand was itself a corporate buy-and-build. Completed 2026-01-29 (S062). Turnover: FY25 98.66, FY24 75.29, FY23 48.47 (INR Cr); 'Last 3 months ARR (Oct to Dec 2025): ~Rs. 140 crores'. Seller-side view: PVR INOX's exit is a data point for the cinema-snacks-to-retail brand route.
A18: Buy | B18: core | C18: Dabur India Ltd | D18: Badshah Masala (Badshah Masala Pvt Ltd) | E18: Food-Ethnic&Condiments | F18: 2023 | G18: 587.52 | H18: 51 | I18: outright_majority | J18: 189.1 | K18: FY22 | L18: turnover as stated in Reg 30 annexure; not labelled ops vs total income | M18: =IF(AND(ISNUMBER(G18),ISNUMBER(H18),ISNUMBER(J18),N(J18)>0),G18/(H18/100)/J18,"") -> 6.0920148 | N18: CATEGORY_ENTRY | O18: Dabur had no branded spices business; Badshah (ground and blended spices) gave it entry into the masala category (INFERRED: filing gives no rationale beyond the business description). | P18: Subsidiary at 51% since 2023-01-02; balance 49% due after 5 years (~2028); Badshah portfolio +12% in Q4 FY26 | Q18: S066: 'Badshah Masala Private Limited has become a subsidiary of Dabur India Limited w.e.f. today i.e. 2nd January 2023'; S076 (T3): 'The Badshah portfolio increased 12% during the quarter' (Q4 FY26) | R18: https://www.bseindia.com/xml-data/corpfiling/AttachHis/479e8327-282f-4bb6-9a41-a7d3ffb13143.pdf | S18: S065;S066;S076 | T18: 2026-10-10 | U18: High | V18: Announced 2022-10-26 (S065): 'Cost of Acquisition of 51% equity shareholding has been agreed at INR 587.52 crore less proportionate debt as on the closing date (100% enterprise valuation being INR 1152 crore which translates to Revenue multiple of around 4.5x and EBIDTA multiple of around 19.6x of FY2022-23 estimated financials)'; balance 49% 'after a period of five years'. Completed 2023-01-02 (S066), so year_start=2023 (announced 2022). Turnover: 'Turnover for FY 21-22 - INR 189.1 crore'. Multiple here = 6.1x on FY22 actuals vs Dabur's own '4.5x' on FY23 estimates (see conflicts.md). The 587.52 is before deducting proportionate debt, so the actual cash paid may be lower: UNCONFIRMED.
A19: Buy | B19: core | C19: Dabur India Ltd | D19: Sesa (Sesa Care Pvt Ltd) | E19: BPC-Haircare | F19: 2026 | G19: 320 | H19: 100 | I19: full_100 | J19: 133.3 | K19: FY24 | L19: consolidated turnover as stated in Reg 30 annexure | M19: =IF(AND(ISNUMBER(G19),ISNUMBER(H19),ISNUMBER(J19),N(J19)>0),G19/(H19/100)/J19,"") -> 2.4006002 | N19: REVENUE_SCALE | O19: Dabur is 'a market leader in the hair oils category' (its own release); Sesa is #3 in ayurvedic hair oil, so the deal mainly adds share in a category and cohort Dabur already owns. | P19: Merger into Dabur sanctioned by NCLT on 2026-09-24; Sesa Care to be dissolved; Dabur shares issued to Sesa shareholders (True North) | Q19: S075/S074: NCLT 'pronounced the order sanctioning the Scheme of Amalgamation between Sesa Care Private Limited... and Dabur India Limited' (2026-09-24); 'There is no cash consideration involved in the Scheme' | R19: https://www.bseindia.com/xml-data/corpfiling/AttachHis/cadeef7a-138a-4e88-abf5-2285a34d9383.pdf | S19: S067;S074;S075 | T19: 2026-10-10 | U19: Low | V19: NEW (not in the lead list). Implementation agreement 2024-10-30 (S067): Dabur buys 51% of Sesa's cumulative redeemable preference shares for Rs 12.59 Cr at face value and guarantees Rs 289 Cr of Sesa debt; equity and remaining CRPS then swapped into Dabur shares on merger. 'Enterprise value of the Target Company (including debt of INR 289 crs.) is estimated to be in the range of INR 315-325 crs'; presentation: 'EV/ Sales: 2.4x and EV/ EBITDA: 19-20x'. consideration_inr_cr 320 = DERIVED midpoint of the disclosed EV range (hence Low); it is EV, mostly assumed debt, not cash. Share-swap ratios set 2025-05-26 (S074). year_start=2026: equity changes hands only when the merger becomes effective (NCLT sanction 2026-09-24; effective date UNCONFIRMED). Turnover: FY24 133.3, FY23 130.3, FY22 111.9 (INR Cr), i.e. near-flat. Seller: True North (PE), which bought the business from Ban Labs in 2018.
A20: Buy | B20: core | C20: Godrej Consumer Products Ltd | D20: Park Avenue (FMCG) & KamaSutra (Raymond Consumer Care FMCG business) | E20: BPC-MensGrooming | F20: 2023 | G20: 2825 | H20: 100 | I20: full_100 | J20: 622 | K20: FY23 | L20: 'historical reported sales' as stated in Reg 30 annexure | M20: =IF(AND(ISNUMBER(G20),ISNUMBER(H20),ISNUMBER(J20),N(J20)>0),G20/(H20/100)/J20,"") -> 4.5418006 | N20: CATEGORY_ENTRY | O20: GCPL calls deodorants and sexual wellness 'under-penetrated categories' that 'complement our business portfolio'; it had no sexual-wellness brand and only a small deo presence (INFERRED: Cinthol deo). | P20: Integrated into GCPL (slump sale, completed 2023-05-08); post-deal brand sales not separately disclosed | Q20: S069: 'the Company has now completed this acquisition'. Post-deal performance UNCONFIRMED. | R20: https://www.bseindia.com/xml-data/corpfiling/AttachHis/09aaabc3-d276-44a4-b240-f217c79c7333.pdf | S20: S068;S069 | T20: 2026-10-10 | U20: Medium | V20: VERIFICATION 2026-10-10: stake_pct 100 is inferred from the deal type (slump sale of the whole business); the Reg 30 field 'Percentage of shareholding / control acquired' reads 'NA' (S068), so the row is downgraded from High to Medium. Consideration and revenue are verbatim T1. Announced 2023-04-27 (S068): 'Cost of acquisition Rs. 2825 Crore / Rs. 2725 Crore (ex cash acquisition from RCCL)'; slump sale of the FMCG business with the Park Avenue (FMCG category), KS, KamaSutra and Premium trademarks. Completed 2023-05-08 (S069). Sales: 'FY21- Rs. 411 crore FY22- Rs. 522 crore FY23- Rs. 622 crore'. Multiple 4.5x (4.4x ex cash). Seller Raymond Ltd is itself listed, so this is a listed-to-listed carve-out. Category judgement: Park Avenue deodorants are the bigger part; if GCPL's Cinthol deo is judged 'meaningful', the label becomes REVENUE_SCALE (deos) + CATEGORY_ENTRY (sexual wellness).
A21: Buy | B21: core | C21: Godrej Consumer Products Ltd | D21: Muuchstac (Triology Solutions Pvt Ltd FMCG business) | E21: BPC-MensGrooming | F21: 2025 | G21: 449 | H21: 100 | I21: full_100 | J21: 87 | K21: FY25 | L21: 'Audited turnover as per IGAAP' (Ind AS TTM FY25 = INR 60 Cr; see notes) | M21: =IF(AND(ISNUMBER(G21),ISNUMBER(H21),ISNUMBER(J21),N(J21)>0),G21/(H21/100)/J21,"") -> 5.1609195 | N21: COHORT_EQUITY | O21: GCPL already sold men's grooming (Park Avenue, Cinthol); Muuchstac brought the young, online men's face-wash cohort. | P21: Integrated into GCPL (slump sale completed 2025-11-10); second-tranche payment (~INR 160 Cr) due ~12 months after signing, i.e. late 2026 | Q21: S072: 'the said acquisition has been completed today' (2025-11-10) | R21: https://www.bseindia.com/xml-data/corpfiling/AttachHis/d84288eb-224d-4315-8ca8-0327ab543ee2.pdf | S21: S071;S072 | T21: 2026-10-10 | U21: Low | V21: NEW (not in the lead list). Signed 2025-10-31 (S071): '100% of Business acquired via slump sale. Tranche 1 cash payment (signing date): Rs 289 crore (EV @ ~Rs 380 Crore); Tranche 2 cash payment (post 12 months): Approx. Rs 160 crore (EV @ ~Rs 400-500 Crore)'. Completed 2025-11-10 (S072). consideration_inr_cr 449 = 289 + ~160 (approximate, valuation-linked second tranche), hence Low; tranche-1-only multiple = 3.3x on 87. Turnover: 'Audited turnover as per IGAAP FY 2022-23 19 Crore FY 2023-24 12 Crore FY 2024-25 87 Crore'; 'TTM turnover as per IND AS FY 2024-25 60 Crore; TTM September 2025 80 Crore'. IGAAP vs Ind AS gap (87 vs 60) logged in conflicts.md; on Ind AS the multiple is 7.5x.
A22: Buy | B22: core | C22: FSN E-Commerce Ventures Ltd (Nykaa) | D22: Dot & Key (Dot and Key Wellness Pvt Ltd) | E22: BPC-Skincare | F22: 2021 | H22: 51 | I22: outright_majority | K22: FY21 | M22: =IF(AND(ISNUMBER(G22),ISNUMBER(H22),ISNUMBER(J22),N(J22)>0),G22/(H22/100)/J22,"") | N22: CATEGORY_ENTRY | O22: Nykaa was a retailer with small private labels; Dot & Key was its 'first direct to customer (D2C) beauty brand acquired' (S088), giving it an owned skincare brand. Entry into owning a scaled brand, not into selling skincare (judgement call vs COHORT_EQUITY). | P22: Subsidiary at 90% since 2024-09-20 (39% bought for up to INR 265.3 Cr); FY24 revenue INR 198.3 Cr (7.2x FY22); founders still run it | Q22: S080: 'the Company holds 90% equity shares of Dot & Key Wellness Private Limited effective September 20'; S079: 'Revenue (in INR Crores) FY 2023-24 198.3 FY 2022-23 57.7 FY 2021-22 27.5' | R22: https://www.bseindia.com/xml-data/corpfiling/AttachHis/07eae3e3-fc2e-44b3-9709-da47560b4f0a.pdf | S22: S079;S080;S087;S088 | T22: 2026-10-10 | U22: Low | V22: FLAG: Nykaa was NOT yet listed at the first completion (51% on 2021-09-28 per search snippet; IPO opened 2021-10-28 (S088), listed Nov 2021), so no Reg 30 filing exists for the 2021 tranche. Included because Nykaa is listed today and the 2024 step-up is a T1 Reg 30 deal. consideration_inr_cr UNCONFIRMED: Business Today (S088) says Nykaa 'did not disclose the amount'; a search snippet attributes '~Rs 46.9 Cr secondary + ~Rs 50 Cr primary' to the RHP - lead only, not verified (check Nykaa RHP, 'Recent developments'). revenue FY21 UNCONFIRMED (first disclosed year is FY22 = 27.5 Cr, S079). 2024 step: 'Acquisition of the shares of Dot & Key will be done at a consideration of up to INR 265.3 crores' for 39% (S079) -> implies ~680 Cr for 100% (3.4x FY24 revenue).
A23: Buy | B23: core | C23: FSN E-Commerce Ventures Ltd (Nykaa) | D23: Earth Rhythm (Earth Rhythm Pvt Ltd) | E23: BPC-Skincare | F23: 2024 | G23: 44.5 | I23: outright_majority | J23: 30.7 | K23: FY24 | L23: revenue as stated in Reg 30 annexure | M23: =IF(AND(ISNUMBER(G23),ISNUMBER(H23),ISNUMBER(J23),N(J23)>0),G23/(H23/100)/J23,"") | N23: COHORT_EQUITY | O23: Filing: 'will further strengthen Company's product portfolio into sustainable beauty segment' - the clean/sustainable beauty cohort, inside a category (skincare) Nykaa already owned via Dot & Key. | P23: Subsidiary at ~75.83% (converted basis) after second tranche on 2025-06-09; FY24 revenue INR 30.7 Cr (FY22 18.5) | Q23: S082: 'Following this investment, Nykaa now holds approximately 75.83% in ERPL, on a converted basis' | R23: https://www.bseindia.com/xml-data/corpfiling/AttachHis/07eae3e3-fc2e-44b3-9709-da47560b4f0a.pdf | S23: S077;S079;S081;S082 | T23: 2026-10-10 | U23: Low | V23: Row = the CONTROL step (approved 2024-08-13, S079): further investment 'at a consideration of up to INR 44.5 crores' through primary and secondary, in tranches, making ERPL a subsidiary; first tranche executed Nov 2024 (S081), second tranche (Rs 5 Cr) 2025-06-09 (S082). stake_pct LEFT BLANK: the incremental stake bought for the 44.5 Cr is not stated (pre-deal 18.51% -> ~75.83% after both tranches, partly via primary OCRPS), so no multiple is computed. PRIOR MINORITY ENTRY (2022): Board approved on 2022-04-22 'upto 18.51%' for 'a consideration of Rs 41.65 crores' (S077); FY22 revenue Rs 18.56 Cr (unaudited) -> ~12x implied. deal_structure outright_majority: the first 2024 tranche made ERPL a subsidiary (S081); the 2022 entry would be minority_with_path. Memory said 'Nykaa acquired 51% of Earth Rhythm in 2022' (C023): WRONG, it was 18.51%.
A24: Buy | B24: core | C24: Emami Ltd | D24: The Man Company (Helios Lifestyle Pvt Ltd) | E24: BPC-MensGrooming | F24: 2024 | G24: 177.63 | H24: 49.6 | I24: full_100 | J24: 183 | K24: FY24 | L24: turnover as stated in Reg 30 annexure | M24: =IF(AND(ISNUMBER(G24),ISNUMBER(H24),ISNUMBER(J24),N(J24)>0),G24/(H24/100)/J24,"") -> 1.9569672 | N24: COHORT_EQUITY | O24: Emami already sold men's products (Fair and Handsome - INFERRED); TMC 'caters to premium segment' with a head-to-toe online men's range, a premium cohort Emami lacked. | P24: Wholly owned since 2024-11-21; FY24 turnover INR 183 Cr (4.3x FY21) | Q24: S092: 'in the last tranche of this transaction, 4585 equity shares of Helios have been acquired by the Company today, i.e., 21st November, 2024' | R24: https://www.bseindia.com/xml-data/corpfiling/AttachHis/2c0eecbf-b80b-4bb9-bdab-7ee327518b7d.pdf | S24: S089;S090;S091;S092 | T24: 2026-10-10 | U24: High | V24: Row = the 2024 buyout of the balance: 'The total purchase consideration to be paid for the acquisition of 1,33,572 equity shares (i.e., 49.60% stake) will be Rs. 177.63 Cr' (S091, approved 2024-08-30); Emami already held 50.40%. Completed in tranches to 2024-11-21 (S092). Earlier path (prices undisclosed, 'not been disclosed due to reasons of confidentiality'): entry pre-2020 (UNCONFIRMED date, likely 2017); 33.09% -> 45.96% (2021-06-28, S089); 45.96% -> 48.49% (2021-08-05, S090); crossed 50% at an UNCONFIRMED date before 2024-08. Turnover: FY24 183, FY23 115, FY22 74 (S091); FY21 42.89, FY20 39.34 (S089) (INR Cr). Implied 100% value in 2024 ~358 Cr = 1.95x FY24. deal_structure full_100 because the holding reached 100% in this transaction (same convention as Beardo).
A25: Buy | B25: core | C25: Emami Ltd | D25: Brillare (Brillare Science Pvt Ltd) | E25: BPC-Haircare | F25: 2021 | H25: 22.66 | I25: outright_majority | J25: 9.76 | K25: FY21 | L25: turnover as stated in Reg 30 annexure | M25: =IF(AND(ISNUMBER(G25),ISNUMBER(H25),ISNUMBER(J25),N(J25)>0),G25/(H25/100)/J25,"") | N25: COHORT_EQUITY | O25: Emami had mass hair oils (Navratna, Kesh King); Brillare is a 'professional beauty care brand for salon', i.e. the salon/professional cohort. | P25: Wholly owned since 2024-03-27; FY23 turnover INR 19.71 Cr (2x FY21) - still small | Q25: S095: 'Emami's Shareholding in Brillare has increased from 95.36% to 100% and it has become a wholly owned subsidiary'; 'Turnover... 2022-23 19.71' | R25: https://www.bseindia.com/xml-data/corpfiling/AttachHis/3a8cdf98-78aa-4e2b-ad29-5d1a3158e89b.pdf | S25: S093;S094;S095 | T25: 2026-10-10 | U25: High | V25: Row = the control step: CCPS 'aggregating to Rs 1.50' Cr (subscribed 2020-12-31 and 2021-03-24, S093) converted into equity on 2021-10-01, taking Emami 'from 34.70% to 57.36%' - 'Brillare Science has become Subsidiary Company' (S094). stake_pct = 22.66 incremental. consideration_inr_cr UNCONFIRMED: 'Cost of conversion from CCPS to Equity Shares has not been disclosed'; the Rs 1.5 Cr CCPS outlay is too small to be the economic price of 22.66% (conversion likely ratcheted on performance), so not entered. Confidence High on the T1 facts; price blank. Entry pre-2020 (letters dated 2018-02-05 and 2019-04-26). Later: CCPS 'upon conversion... stake would be 66.29% subject to achievement of agreed future performance' (2021-11-02; that filing is NOT saved in sources/raw - quote UNCONFIRMED, verification 2026-10-10); 100% on 2024-03-27, price undisclosed (S095). Turnover FY21 9.76 / FY20 4.49 / FY19 9.32 (INR Cr).
A26: Buy | B26: core | C26: Emami Ltd | D26: Dermicool (brand acquired from Reckitt Benckiser Healthcare India) | E26: BPC-Skincare | F26: 2022 | G26: 432 | H26: 100 | I26: full_100 | M26: =IF(AND(ISNUMBER(G26),ISNUMBER(H26),ISNUMBER(J26),N(J26)>0),G26/(H26/100)/J26,"") | N26: REVENUE_SCALE | O26: Emami already led cool talc with Navratna; release says 'Combined with Emami's Navratna Cool Talc, Emami will become leader in this niche category' - share, not a new category or cohort. | P26: Owned brand within Emami (brand/trademark purchase, not a company); post-deal sales UNCONFIRMED | Q26: S096: 'the Company has acquired "Dermicool"... from Reckitt Benckiser Healthcare (India) Private Limited' (2022-03-25) | R26: https://www.bseindia.com/xml-data/corpfiling/AttachHis/4bbf5be6-b8d6-4c4b-93e0-d9e5ed244f03.pdf | S26: S096;S098;S099 | T26: 2026-10-10 | U26: Medium | V26: VERIFICATION 2026-10-10: stake_pct 100 is inferred from the deal type (outright brand purchase, S096: 'acquired "Dermicool"'); no % is printed, so the row is downgraded from High to Medium. Consideration is verbatim T1. NEW (not in the lead list). S096 press release: 'total consideration of Rs 432 crores excluding taxes & duties'; Dermicool 'commands ~20% market share' in prickly heat powder. A brand (asset) purchase from a multinational's Indian subsidiary, not a startup; kept because the parent is listed and the brand is Indian-market. Category bucket 'BPC-Skincare' is the nearest fit (talc/prickly heat). revenue UNCONFIRMED: a search snippet says 'Rs 113 crore in 2021, EBITDA margin 35%' but neither saved T3 article (S098, S099) contains it - lead only. If 113 holds, multiple = 3.8x.
A27: Buy | B27: core | C27: Honasa Consumer Ltd | D27: Reginald Men (BTM Ventures Pvt Ltd) | E27: BPC-MensGrooming | F27: 2026 | G27: 197.96 | H27: 95 | I27: outright_majority | J27: 20.15 | K27: FY25 | L27: revenue as stated in Reg 30 annexure | M27: =IF(AND(ISNUMBER(G27),ISNUMBER(H27),ISNUMBER(J27),N(J27)>0),G27/(H27/100)/J27,"") -> 10.341387 | N27: CATEGORY_ENTRY | O27: Filing: 'Expansion in a sizeable and fast-growing category (male personal care)'; Honasa had no dedicated men's brand (INFERRED from its portfolio of Mamaearth, The Derma Co, Aqualogica, BBlunt, Dr. Sheth's). | P27: Subsidiary at 95% since 2026-01-06; remaining 5% after 12 months; TTM revenue to Oct-2025 INR 74 Cr | Q27: S101: 'completed the acquisition of 95% of the issued and paid-up equity share capital of BTM Ventures Private Limited' | R27: https://www.bseindia.com/xml-data/corpfiling/AttachHis/fc202c10-6ea5-4442-b480-7785e67736e9.pdf | S27: S100;S101 | T27: 2026-10-10 | U27: High | V27: NEW (not in the lead list). Approved 2025-12-11 (S100): '95% equity stake via secondary purchase at a Rs 195 Crores enterprise value on a no-cash no-debt basis'; remaining 5% in tranche 2 after 12 months. Completed 2026-01-06 (S101) 'for an equity value of INR 197.96 Crores, which includes cash and cash equivalents of INR 12.71 Crores'. Revenue: FY23 ~Rs 0.7 thousand, FY24 ~Rs 43 thousand, FY25 Rs 20.15 Cr, TTM Oct-2025 Rs 74 Cr. Multiple 10.3x on FY25 but 2.8x on TTM - a young, fast-ramping brand (incorporated 2022-08-25), so FY25 understates scale. Honasa was listed (Nov 2023) at signing. Its 2022 deals (Dr. Sheth's, BBlunt) predate listing and are excluded; see claims_verification_log C020/C021.
A28: Buy | B28: core | C28: Zydus Wellness Ltd | D28: RiteBite Max Protein (Naturell (India) Pvt Ltd) | E28: Food-Snacks&Bars | F28: 2024 | G28: 390 | H28: 100 | I28: full_100 | J28: 128.89 | K28: FY24 | L28: revenue_from_operations (IGAAP; ~119 Cr under Ind AS) | M28: =IF(AND(ISNUMBER(G28),ISNUMBER(H28),ISNUMBER(J28),N(J28)>0),G28/(H28/100)/J28,"") -> 3.025836 | N28: CATEGORY_ENTRY | O28: Filing: 'expanding its footprint in the consumer wellness industry by foraying into the rapidly growing healthy snacking' segment; Zydus Wellness (Complan, Glucon-D, Sugar Free, Nycil) had no snack bars. | P28: Subsidiary at 98.14% from 2024-11-29; balance 1.86% 'expected to be completed shortly' (completion of the last 1.86% UNCONFIRMED) | Q28: S103: 'on November 29, 2024, the Company has acquired 98.14% equity share capital from the Sellers of the Target' | R28: https://www.bseindia.com/xml-data/corpfiling/AttachHis/9eec263b-6a51-4a93-bb9c-4d767c184732.pdf | S28: S102;S103 | T28: 2026-10-10 | U28: High | V28: NEW (not in the lead list). SPA approved 2024-10-30 (S102) for 100%: 'Rs 369 crores... will be paid as upfront consideration (subject to customary adjustments). Over and above this amount of upfront consideration, earnout amount of Rs 21 crores'; total 'consideration of Rs 390 crores'. Revenue: 'Revenue from Operations as per IGAAP... March 31, 2024: Rs 128.89 crores; March 31, 2023: Rs 102.06 crores; March 31, 2022: Rs 59.07 crores'; '(approx. Rs 119 crores as per IND-AS)'. Multiple 3.0x (IGAAP) / 3.3x (Ind AS). deal_structure full_100: 98.14% at first completion with the rest a formality (same convention as Organic India 99.99%).
A29: Buy | B29: core | C29: Bajaj Consumer Care Ltd | D29: Banjara's (Vishal Personal Care Pvt Ltd) | E29: BPC-Haircare | F29: 2025 | G29: 120 | H29: 100 | I29: staged_to_control | J29: 51.53 | K29: FY24 | L29: revenue_from_operations | M29: =IF(AND(ISNUMBER(G29),ISNUMBER(H29),ISNUMBER(J29),N(J29)>0),G29/(H29/100)/J29,"") -> 2.3287405 | N29: COHORT_EQUITY | O29: Bajaj already sold herbal hair care (Almond Drops); filing cites 'size, geography, growth, profitability, and portfolio' - Banjara's (Hyderabad, ayurvedic henna/hair/skin) adds a southern consumer base (INFERRED: Bajaj's north/west skew). | P29: Wholly owned since 2025-05-16 (tranche 2: 51% for INR 61.18 Cr) | Q29: S106: 'completed the acquisition of tranche 2 shares today, i.e., 51%... for a consideration of INR 61,18,23,600. Pursuant to this, the Target Company has now become 100% subsidiary' | R29: https://www.bseindia.com/xml-data/corpfiling/AttachHis/595c2660-0101-4f9b-a8a0-06bfaa5e1f77.pdf | S29: S104;S105;S109;S106 | T29: 2026-10-10 | U29: High | V29: NEW (not in the lead list). Approved 2025-02-14 (S104; S105 is a duplicate filing): 'Estimated cash consideration of approx. INR 120 crore at an Enterprise value of INR 108.3 crore' for 100% in two tranches (49% then 51%); seller incl. Peepul Capital Fund III. Tranche 1 (49%) completed 2025-03-10 (S109); tranche 2 (51%) 2025-05-16 for INR 61.18 Cr (S106), so tranche 1 cost ~INR 59 Cr (DERIVED). consideration/stake recorded as the contracted 100% package. Revenue from operations: FY24 INR 51.53 Cr; FY23 45.36; FY22 39.43. deal_structure staged_to_control: first tranche 49% (<=50%) with a contracted second tranche to 100%. Category bucket inferred: Banjara's sells henna/hair and skin products.
A30: Buy | B30: core | C30: Reliance Industries Ltd (via Reliance Consumer Products Ltd) | D30: Lotus Chocolate (Lotus Chocolate Company Ltd) | E30: Other | F30: 2023 | G30: 74 | H30: 51 | I30: outright_majority | J30: 86.97 | K30: FY22 | L30: 'Income from Operations' as stated in the letter of offer (audited) | M30: =IF(AND(ISNUMBER(G30),ISNUMBER(H30),ISNUMBER(J30),N(J30)>0),G30/(H30/100)/J30,"") -> 1.6683689 | N30: CATEGORY_ENTRY | O30: RCPL had no chocolate/cocoa business; Lotus (cocoa products and chocolates, with a factory) gave entry into confectionery. CAPABILITY (manufacturing) is the runner-up. | P30: Listed subsidiary of RCPL (51% via SPA plus open offer for up to 26% at INR 115.50/share, offer in Mar 2023); later performance UNCONFIRMED | Q30: S110: 'Shares / voting rights acquired... 65,48,935 51.00% 74,00,29,655 Cash'; open offer 'at a price of INR 115.50 per Offer Share' | R30: https://www.bseindia.com/xml-data/corpfiling/AttachHis/fea041df-8810-409c-94b9-e89ad604024e.pdf | S30: S110;S111 | T30: 2026-10-10 | U30: High | V30: SPECIAL CASE: acquirer is Reliance Consumer Products Ltd (RCPL), a wholly owned subsidiary of Reliance Retail Ventures, counted under listed parent Reliance Industries Ltd (D4). RIL itself filed no Reg 30 for this size of deal; T1 evidence is the TARGET's SEBI SAST filings (Lotus is BSE-listed). SPA 2022-12-29: 51% from the promoters 'at a price of INR 113.00 per Sale Share, for a total consideration of INR 74,00,29,655' (S110); plus preferential issue of redeemable preference shares to RCPL (S111). Completion of the SPA ~May 2023 (Reg 29 disclosures 2023-05-27); exact date UNCONFIRMED. Revenue S111: 'Income from Operations' INR Cr - 9M FY23 37.11 (unaudited), FY22 86.97, FY21 47.87, FY20 69.89. Category 'Other' = confectionery (no bucket in the taxonomy).
A31: Buy | B31: core | C31: Reliance Industries Ltd (via Reliance Consumer Products Ltd) | D31: Campa (brand bought from Pure Drinks Group) | E31: Beverages | F31: 2022 | G31: 22 | H31: 100 | I31: full_100 | M31: =IF(AND(ISNUMBER(G31),ISNUMBER(H31),ISNUMBER(J31),N(J31)>0),G31/(H31/100)/J31,"") | N31: CATEGORY_ENTRY | O31: Reliance had no soft-drink brand; Campa was a dormant heritage cola trademark bought to enter carbonated drinks. | P31: Relaunched 2023 and now Reliance's flagship beverage brand; Reliance plans up to INR 8,000 Cr of beverage investment (T4) | Q31: S113 (T4): 'Much of its INR 8,000 crore investment will be devoted to Campa-Cola's expansion'; 'It bought the Campa Cola brand for a measly INR 22 crore' | R31: https://www.dtnext.in/amp/story/news/business/reliance-acquires-soft-drink-brand-campa-as-part-of-expansion | S31: S112;S113 | T31: 2026-10-10 | U31: Low | V31: SPECIAL CASE (RCPL under RIL, see Lotus row). A trademark purchase of a dormant brand - really a BUILD on a bought name; flag for Tab B discussion. consideration 22 from S112 (PTI via DT Next): 'The deal is estimated to be around Rs 22 crore... said sources close to the development' - unnamed sources, T3 only; S113 repeats it (T4). No company disclosure found. Date 2022 (Aug-2022 per press; exact date UNCONFIRMED). revenue LEFT BLANK: brand was dormant at purchase; no turnover attributable. Multiple not meaningful.
A32: Buy | B32: core | C32: Reliance Industries Ltd (via Reliance Consumer Products Ltd) | D32: Sosyo (Sosyo Hajoori Beverages Pvt Ltd) | E32: Beverages | F32: 2023 | H32: 50 | I32: minority_no_path | M32: =IF(AND(ISNUMBER(G32),ISNUMBER(H32),ISNUMBER(J32),N(J32)>0),G32/(H32/100)/J32,"") | N32: CAPABILITY | O32: Release: 'Sosyo's expertise in formulations can be leveraged to develop unique value proposition' for Reliance's beverage portfolio, which already had Campa - the formulation know-how is the stated asset. | P32: 50:50 joint venture with the Hajoori family, who keep running the business; later status UNCONFIRMED | Q32: S114: 'The existing promoters, Hajoori family, will continue to own the remaining stake in SHBPL' | R32: https://www.afaqs.com/news/brands/reliance-consumer-to-acquire-50-stake-in-sasyo-hajoori-beverages | S32: S114;S115 | T32: 2026-10-10 | U32: Medium | V32: SPECIAL CASE (RCPL under RIL). Announced Jan 2023 (S114, S115, both carrying RCPL's release): 'will acquire 50% equity stake in Gujarat-headquartered Sosyo Hajoori Beverages Private Limited'. JOINT VENTURE: a 50:50 JV, confirmed by both sources - S114: 'Speaking on the joint venture with RCPL'; 'The existing promoters, Hajoori family, will continue to own the remaining stake in SHBPL'. deal_structure = minority_no_path (D12 covers non-controlling stakes of 50% or less, including 50:50 JVs): no disclosed route for RCPL to take control. consideration UNCONFIRMED (not disclosed); revenue UNCONFIRMED. Medium = two T3 sources that agree (both rely on the same company release). Completion date UNCONFIRMED.

Sheet Tab_B_Build
A1: route | B1: row_type | C1: parent | D1: brand | E1: category | F1: year_start | G1: consideration_inr_cr | H1: stake_pct | I1: deal_structure | J1: revenue_inr_cr | K1: revenue_fy | L1: revenue_basis | M1: revenue_multiple | N1: what_was_acquired | O1: vocab_rationale | P1: status_today | Q1: status_evidence | R1: base_rate_flag | S1: source_url | T1: source_ids | U1: date_accessed | V1: confidence | W1: notes
A2: Build | B2: calibration | C2: Hindustan Unilever Ltd | D2: Lever Ayush | E2: Other | F2: 2001 | M2: =IF(AND(ISNUMBER(G2),ISNUMBER(H2),ISNUMBER(J2),N(J2)>0),G2/(H2/100)/J2,"") | N2: CATEGORY_ENTRY | O2: HUL's own ayurvedic masterbrand: an attempt to build an ayurveda franchise in-house rather than buy one (contrast Indulekha, bought 2016). | P2: Niche | Q2: P2: in AR FY20 (S128 p.13: 'The master brand LEVER Ayush continued its momentum in the focused market - South India') and FY21 (S129 p.14: 'LEVER Ayush, the master brand maintained focus on its key market in southern India'); 0 mentions FY22-FY26. P3: leverayush.com gives no response (SSL error); HUL brand pages are JS-rendered (D8) - current availability UNCONFIRMED (S207). | R2: included | S2: https://www.bseindia.com/bseplus/AnnualReport/500696/5006960320.pdf | T2: S128;S129;S207 | U2: 2026-10-10 | V2: Low | W2: Launch year conflict: 2001 vs 2002 in secondary write-ups (T4 case studies via search; HUL primary not found) - see conflicts.md. Relaunch: Dec 2016 with ~20 mass-priced products (Rs 30-130) in TN, Kerala, AP, Telangana, Karnataka, a response to Patanjali (T4 case-study sources via search, not saved as evidence). Pullback in the 2000s: only T4 reports ('HUL may pull out the brand') - UNCONFIRMED. Today: regional (South India) brand per HUL's own words in FY20-21; dropped from AR narrative from FY22. Calibration row (pre-2020, named in study scope).
A3: Build | B3: calibration | C3: Hindustan Unilever Ltd | D3: Love Beauty & Planet (Unilever global brand, launched in India by HUL) | E3: BPC-Haircare | F3: 2019 | K3: FY24 | L3: ARR (company-stated annualised run-rate), combined with Simple; brand-only figure not disclosed | M3: =IF(AND(ISNUMBER(G3),ISNUMBER(H3),ISNUMBER(J3),N(J3)>0),G3/(H3/100)/J3,"") | N3: COHORT_EQUITY | O3: Purpose-led 'clean/vegan' masstige brand aimed at a digital, sustainability-minded cohort HUL's mass brands did not reach; built inside the group, not bought. | P3: Stable | Q3: P1: AR FY24 (S132 p.51): 'early success in two of the brands launched by the Premium Beauty Business unit (PBBU) - Simple and Love, Beauty & Planet with their combined ARR scaling Rs 100 crores within 3 years'; AR FY25 (S133 p.22): 'Novology, Simple and Love, Beauty & Planet... delivering strong growth'. P2: mentioned FY20-FY25, 0 in FY26. P3: lovebeautyandplanet.in live (HTTP 200, 2026-10-10). P4: Wayback 49 monthly captures 2021-06 to 2026-03 (S124). | R3: included | S3: https://www.bseindia.com/bseplus/AnnualReport/500696/5006960320.pdf | T3: S128;S132;S133;S124 | U3: 2026-10-10 | V3: Medium | W3: Launch: AR FY20 (S128 p.5): 'During the year, we also launched, a purpose-driven brand from the Unilever stable, Love, Beauty and Planet' -> launched in FY20 (Apr 2019-Mar 2020); month UNCONFIRMED, year_start=2019 is a best estimate, so calibration. AR FY21 also says HUL 'introduced' it in India; secondary search snippets say 2018 (global launch was 2018) - see conflicts.md. Caveat: a Unilever global brand localised by HUL, not an Indian ground-up build. revenue_inr_cr blank: only a combined Simple + LB&P ARR of Rs 100 Cr (FY24) is disclosed; Simple is a Unilever-acquired brand, so not attributable. Not named in FY26 AR (PBBU list there: Minimalist, OZiva, Simple, Nexxus, Liquid I.V.).
A4: Build | B4: core | C4: Hindustan Unilever Ltd | D4: Acne Squad | E4: BPC-Skincare | F4: 2022 | M4: =IF(AND(ISNUMBER(G4),ISNUMBER(H4),ISNUMBER(J4),N(J4)>0),G4/(H4/100)/J4,"") | N4: COHORT_EQUITY | O4: Digital-first acne brand for 'hyper-connected' Gen Z consumers, a cohort HUL's mass skincare (Pond's, Glow & Lovely) did not own; built in-house via HUL's Agile Innovation Hub. | P4: Withdrawn | Q4: P2: AR FY23 only (S131 p.13: 'we launched two new brands Acne Squad and Find Your Happy Place'); 0 mentions FY24-FY26, while FY24 AR credits only Simple and LB&P with 'early success'. P3: acnesquad.in returns HTTP 404 'Store unavailable... This store is currently unavailable' (Shopify), checked 2026-10-10. P4: Wayback has no live (200) capture; last capture 2025-04-06 = 404 (S124). | R4: included | S4: https://www.bseindia.com/xml-data/corpfiling/AttachHis/dbf3868a-97f3-43ed-b5ce-47e83261fdc4.pdf | T4: S131;S132;S124 | U4: 2026-10-10 | V4: Medium | W4: Launch FY23 (Apr 2022-Mar 2023); trade press dates the launch to early Oct 2022 (fashionnetwork, 2022-10-04, search snippet only, T3, not saved). AR FY23 (S131): 'a range of 11 skincare products and curated regime kits'; launched 'using the Agile Innovation platform'. 'Withdrawn' is inferred from the dead D2C store + silence in 3 subsequent ARs; HUL has not announced a discontinuation (none found). Marketplace (Nykaa/Amazon) listing status UNCONFIRMED: Nykaa returned 403 to scripted check (not bypassed). revenue: never disclosed.
A5: Build | B5: core | C5: Hindustan Unilever Ltd | D5: Find Your Happy Place | E5: BPC-Skincare | F5: 2022 | M5: =IF(AND(ISNUMBER(G5),ISNUMBER(H5),ISNUMBER(J5),N(J5)>0),G5/(H5/100)/J5,"") | N5: COHORT_EQUITY | O5: Premium 'mood-transforming' bath & body brand crafted for digital consumers; a premium self-care cohort HUL's mass bath brands did not serve. | P5: Withdrawn | Q5: P2: AR FY23 only (S131 p.18: 'Find Your Happy Place is a premium brand that provides experiential mood transforming Bath and Body ranges'); 0 mentions FY24-FY26. P3: findyourhappyplace.in returns HTTP 402 'Store unavailable... If you would like to reactivate your store contact Shopify support' (2026-10-10). P4: Wayback last live (200) capture 2023-11-13; later captures 403 (S124). | R5: included | S5: https://www.bseindia.com/xml-data/corpfiling/AttachHis/dbf3868a-97f3-43ed-b5ce-47e83261fdc4.pdf | T5: S131;S124 | U5: 2026-10-10 | V5: Medium | W5: Launched FY23 (Apr 2022-Mar 2023); first Wayback capture of the site 2022-11-15 (200), so launch c. H2 2022, year_start=2022 (month UNCONFIRMED). Withdrawal inferred (store frozen + AR silence); no HUL announcement found. Live for ~1 year on the evidence of Wayback captures.
A6: Build | B6: core | C6: Hindustan Unilever Ltd | D6: Novology | E6: BPC-Skincare | F6: 2023 | M6: =IF(AND(ISNUMBER(G6),ISNUMBER(H6),ISNUMBER(J6),N(J6)>0),G6/(H6/100)/J6,"") | N6: COHORT_EQUITY | O6: Masstige derma-therapeutic skincare built in-house to reach the 'actives' cohort that later drove the Minimalist acquisition (2025). | P6: Unclear | Q6: P1: AR FY25 (S133 p.22): 'we expanded our masstige portfolio through Novology, Simple and Love, Beauty & Planet. Each of these brands have a sharp positioning and are delivering strong growth'. P2: AR FY23, FY24, FY25 narrative; FY26 only in an R&D technology table (S134 p.58), not in the FY26 premium list. P3/P4: no brand domain found (novology.in DNS fail, no Wayback captures) - UNCONFIRMED. | R6: excluded_unclear | S6: https://www.bseindia.com/xml-data/corpfiling/AttachHis/dbf3868a-97f3-43ed-b5ce-47e83261fdc4.pdf | T6: S131;S132;S133;S134;S124 | U6: 2026-10-10 | V6: Low | W6: Launch: AR FY23 (S131 p.18): 'We have also launched a masstige beauty brand Novology in the growing segment of Derma-therapeutic Care'; AR FY24 p.63: 'Novology Hyper Pigmentation Serum that was launched in 2023' -> year_start 2023 (Jan-Mar 2023). Technology imported from Unilever under the TCA (AR FY24 p.63). Dropped from FY26 narrative the year after HUL bought Minimalist - a signal worth watching, not proof of withdrawal.
A7: Build | B7: core | C7: Marico Ltd | D7: Saffola Immuniveda (incl. Saffola Arogyam Chyawanamrut) | E7: Wellness-Nutrition&Supplements | F7: 2020 | M7: =IF(AND(ISNUMBER(G7),ISNUMBER(H7),ISNUMBER(J7),N(J7)>0),G7/(H7/100)/J7,"") | N7: CATEGORY_ENTRY | O7: Marico's 'first range of Ayurvedic products' (press release): entry into immunity/ayurveda, a category Marico had no presence in, under the Saffola masterbrand. | P7: Withdrawn | Q7: P2: brand list includes 'Saffola Immuniveda' in AR FY21 (S143 p.16), FY22, FY24 (S146 p.21); absent from the FY25 (S147 p.29) and FY26 (S148 p.22) brand lists. 'Saffola Arogyam' appears in FY21 only. P1: FY21 AR p.24 groups it with Covid-era 'immunity' launches. P3: saffola.in Immuniveda pages return 403 to scripted check (not bypassed) - UNCONFIRMED; P4: no Wayback captures (S207). | R7: included | S7: https://marico.com/media_pdf/press-release-marico-limited-launches-ayurvedic-products.pdf | T7: S118;S143;S146;S147;S148;S207 | U7: 2026-10-10 | V7: Low | W7: Launched 2020-09-16 (S118 p.1: 'Marico Limited, one of India's leading FMCG companies, has strengthened its position in the healthy foods and immunity-boosting segment, with the launch of the Saffola ImmuniVeda range'; Kadha Mix + Golden Turmeric Milk Mix; chyawanprash added 2021). AR FY21 (S143 p.24): 'introduced Saffola Honey, Saffola Arogyam Chyawanamrut Awaleha, Saffola Oodles, Saffola Mealmaker Soya Chunks and traditional immunity boosters under Saffola Immuniveda'. Status 'Withdrawn' = dropped from the parent's own brand list (P2) after the Covid immunity spike faded; no discontinuation announcement found, so Low confidence. Revenue never disclosed.
A8: Build | B8: core | C8: Marico Ltd | D8: Veggie Clean | E8: Other | F8: 2020 | M8: =IF(AND(ISNUMBER(G8),ISNUMBER(H8),ISNUMBER(J8),N(J8)>0),G8/(H8/100)/J8,"") | N8: CATEGORY_ENTRY | O8: Fruit-and-vegetable wash: a Covid-era entry into home hygiene, a category Marico had not been in. | P8: Withdrawn | Q8: P1: AR FY21 (S143 p.24) calls the hygiene launches 'tactical plays into hygiene categories'. P2: in AR FY20 (S142 p.25: 'Marico has introduced Mediker Hand Sanitizer and Veggie Clean in India') and FY21 product tables; 0 mentions FY22-FY26. P4: Marico's Veggie Clean brand page last captured live 2021-09-18, later 406 (S207). | R8: excluded_out_of_scope | S8: https://www.bseindia.com/bseplus/AnnualReport/531642/5316420320.pdf | T8: S142;S143;S207 | U8: 2026-10-10 | V8: Low | W8: Launched c. Mar-Apr 2020 (FY20 AR, published Aug 2020, already lists it; exact date UNCONFIRMED). The parent itself framed it as tactical, i.e. never meant to be scaled - a 'planned' exit rather than a failed bet. Withdrawal inferred from AR silence since FY22.
A9: Build | B9: core | C9: Honasa Consumer Ltd | D9: The Derma Co | E9: BPC-Skincare | F9: 2020 | J9: 750 | K9: FY26 | L9: ARR (company-stated annualised net revenue run-rate, '>INR 750 Cr'); not audited revenue | M9: =IF(AND(ISNUMBER(G9),ISNUMBER(H9),ISNUMBER(J9),N(J9)>0),G9/(H9/100)/J9,"") | N9: COHORT_EQUITY | O9: Mamaearth (toxin-free/natural) did not reach the ingredient-aware 'actives' cohort; The Derma Co was built to serve it. | P9: Scaled | Q9: P1: AR FY26 (S165 p.8): 'Derma Co. crossed Rs 750 Cr ARR'; Q2 FY26 press release (S120 p.2): 'crossing INR 750 Cr ARR milestone'; AR FY24 (S163 p.17): 'Rs 500 Cr+ Net ARR of The Derma Co. within 50 Months of Launch'. P2: mentioned in every Honasa AR FY24-FY26. P3: thedermaco.com live (S125). | R9: included | S9: https://www.bseindia.com/xml-data/corpfiling/AttachHis/7fba52ba-0385-411a-a015-554d602cdb2c.pdf | T9: S165;S120;S163;S121;S125 | U9: 2026-10-10 | V9: High | W9: Launch-month conflict: AR FY24 (S163 p.12) 'Since The Derma Co's launch in March 2020' vs AR FY26 (S165 p.13) 'The Derma Co, launched in February 2020' - year 2020 either way; see conflicts.md. Break-even: 'achieving break-even in all quarters of FY24' (S121 p.2). LISTING CAVEAT: built while Honasa was unlisted (IPO Nov 2023); valid for Tab B because Honasa is listed now and discloses brand-level ARR, but it was not a listed-company build decision (cf. D13 for Tab A).
A10: Build | B10: core | C10: Honasa Consumer Ltd | D10: Aqualogica | E10: BPC-Skincare | F10: 2021 | J10: 200 | K10: FY26 | L10: ARR (company-stated, 'crossed Rs 200 Cr ARR'); not audited revenue | M10: =IF(AND(ISNUMBER(G10),ISNUMBER(H10),ISNUMBER(J10),N(J10)>0),G10/(H10/100)/J10,"") | N10: COHORT_EQUITY | O10: Hydration-led, fruit-plus-actives skincare for younger, climate-specific needs: a sharper sub-cohort than Mamaearth or The Derma Co served. | P10: Scaled | Q10: P1: AR FY26 (S165 p.8): 'Aqualogica and Dr. Sheth's crossed Rs 200 Cr ARR'; AR FY24 (S163 p.17): 'Rs 180 Cr+ Net ARR of Aqualogica within 19 Months of Launch'. P2: in all Honasa ARs FY24-FY26. P3: aqualogica.in live (S125). | R10: included | S10: https://www.bseindia.com/xml-data/corpfiling/AttachHis/7fba52ba-0385-411a-a015-554d602cdb2c.pdf | T10: S165;S163;S125 | U10: 2026-10-10 | V10: Medium | W10: VERIFICATION 2026-10-10: downgraded High -> Medium. The FY26 figure is a joint, undated timeline bullet ('Aqualogica and Dr. Sheth's crossed Rs 200 Cr ARR'); read as each brand >Rs 200 Cr (FY24 already had Aqualogica 180+ and Dr. Sheth's 150+ separately, so a combined 200 would be no milestone), but the split is not stated, and AR FY25 (S164 p.54) still says '180+Cr Net Annual Revenue Run-Rate of Aqualogica'. Brand-only FY26 ARR UNCONFIRMED. Launch: AR FY24 (S163 p.7): 'Aqualogica was launched in 2021'. Growth flattened: ~Rs 180 Cr ARR at 19 months (c. 2022-23) vs ~Rs 200 Cr by FY26, i.e. scaled fast, then plateaued. LISTING CAVEAT: built pre-IPO (Honasa listed Nov 2023).
A11: Build | B11: core | C11: Honasa Consumer Ltd | D11: Ayuga | E11: BPC-Skincare | F11: 2021 | M11: =IF(AND(ISNUMBER(G11),ISNUMBER(H11),ISNUMBER(J11),N(J11)>0),G11/(H11/100)/J11,"") | N11: COHORT_EQUITY | O11: Herbal/ayurvedic skincare ('golden generation of skin rituals') aimed at an ayurveda-leaning millennial cohort. | P11: Withdrawn | Q11: P2: AR FY24 (S163 p.8: 'Ayuga is a natural skincare brand bringing the golden generation of skin rituals back'), 9 mentions; FY25 only in BRSR/legal notes (S164 p.108); 0 mentions FY26 (FY26 brand list: Mamaearth, The Derma Co, Aqualogica, Dr Sheths, BBlunt, Staze, Lumineve). P3: ayuga.in HTTP 402 'Store unavailable' (Shopify), 2026-10-10. P4: Wayback first capture 2021-11-27, last live capture 2025-10-13 (S125). | R11: included | S11: https://www.bseindia.com/xml-data/corpfiling/AttachHis/dec5ef82-91a6-436e-9568-9071207db3aa.pdf | T11: S163;S164;S165;S125 | U11: 2026-10-10 | V11: Medium | W11: year_start 2021 from first Wayback capture of ayuga.in (2021-11-27); launch date not stated in the ARs - UNCONFIRMED beyond the year. Withdrawal inferred (store frozen after Oct 2025 + dropped from the FY26 brand list); no announcement found. Never given an ARR milestone, unlike its siblings. LISTING CAVEAT: launched pre-IPO.
A12: Build | B12: core | C12: Honasa Consumer Ltd | D12: Staze (Staze 9to9) | E12: BPC-ColourCosmetics | F12: 2024 | M12: =IF(AND(ISNUMBER(G12),ISNUMBER(H12),ISNUMBER(J12),N(J12)>0),G12/(H12/100)/J12,"") | N12: CATEGORY_ENTRY | O12: Honasa had no colour-cosmetics brand; Staze is its first ('to capture share of color cosmetics', S122). | P12: Niche | Q12: P1: AR FY25 (S164 p.30): in lipsticks, 'Led by Staze and Mamaearth within Honasa, we are just getting started and currently hold <1% market share online'; AR FY26 (S165 p.10): 'Staze 9to9 keeps building for the Gen Z consumer'. No ARR disclosed. P2: FY24-FY26 ARs. P3: stazebeauty.com live (S125). | R12: included | S12: https://bseindia.com/xml-data/corpfiling/AttachHis/74ed43be-519b-4442-920a-9d400ee5e170.pdf | T12: S122;S164;S165;S125 | U12: 2026-10-10 | V12: Medium | W12: Launched 2024-03-28 (S122 p.2: 'HONASA CONSUMER LAUNCHES STAZE, TO CAPTURE SHARE OF COLOR COSMETICS'); post-IPO build. Niche = still supported but no ARR milestone and <1% online lipstick share (combined with Mamaearth) after ~1 year; 2.5 years old at the check date, so the verdict is provisional.
A13: Build | B13: core | C13: Godrej Consumer Products Ltd | D13: Godrej Fab (liquid detergent) | E13: Other | F13: 2024 | J13: 490 | K13: FY26 | L13: ARR (company-stated 'annualised revenue run rate of nearly Rs 490 crore'); FY25 'topline' >Rs 150 Cr | M13: =IF(AND(ISNUMBER(G13),ISNUMBER(H13),ISNUMBER(J13),N(J13)>0),G13/(H13/100)/J13,"") | N13: REVENUE_SCALE | O13: GCPL already sold liquid detergent (Ezee, north/east); Fab is a mass-priced regional build (South India) to add share and scale in a category it knew. | P13: Scaled | Q13: P1: AR FY26 (S162 p.42): 'In fiscal year 2026, Fab reached an annualised revenue run rate of nearly Rs 490 crore in a category approximately Rs 4,000 crore in size, having moved from loss-making in its early years to near break-even'; AR FY25 (S161 p.39): 'Fab, our new liquid detergent brand, crossed Rs 150 crore topline in its first year'. P2: AR FY24-FY26; one of three 'Speedboats' (FY26 p.43). | R13: excluded_out_of_scope | S13: https://www.bseindia.com/xml-data/corpfiling/AttachHis/44575d54-1aad-467f-b360-4098a29f22d2.pdf | T13: S162;S161;S160 | U13: 2026-10-10 | V13: High | W13: Launched 2024-01-16 in South India at Rs 99/litre (T3 trade press via search: afaqs/exchange4media, not saved; AR FY24 lists 'Fab Liquid Detergent' among new launches). Home care, outside the BPC/food taxonomy (category=Other); kept because it is the cleanest recent in-house scale-up by a Tab A parent. Not a new category for GCPL (Ezee) - this is a value-tier regional build.
A14: Build | B14: core | C14: Godrej Consumer Products Ltd | D14: Godrej Ninja (Godrej Pet Care Ltd) | E14: Other | F14: 2025 | J14: 2.22 | K14: FY26 | L14: total_income ('Total Revenue' of subsidiary Godrej Pet Care Ltd, Rs 222.1 lakh) | M14: =IF(AND(ISNUMBER(G14),ISNUMBER(H14),ISNUMBER(J14),N(J14)>0),G14/(H14/100)/J14,"") | N14: CATEGORY_ENTRY | O14: GCPL had no pet food business; AR FY25 calls Ninja 'our entry into pet food'. | P14: Niche | Q14: P1: S073 (Reg 30, 2026-07-22): 'Total Revenue of Godrej Pet Care for the Financial Year ended March 31, 2026 was Rs 222.1 Lakh'; FY24 73.11 / FY25 46.33 / FY26 222.1 lakh. AR FY25 (S161 p.39): 'Godrej Ninja, our entry into pet food, is a launch we did in record time'. P2: 'Ninja' appears in AR FY25, 0 times in AR FY26 (only 'Pet Care' as a category). P3: godrejninja.com 403 to scripted check (not bypassed); P4: live Wayback captures 2025-09 to 2026-04 (S207). | R14: excluded_out_of_scope | S14: https://www.bseindia.com/xml-data/corpfiling/AttachHis/eafdff8f-cb1c-455f-9402-fff424b8ee37.pdf | T14: S073;S161;S162;S207 | U14: 2026-10-10 | V14: Medium | W14: Entry disclosed 2024-08-07 (per S073); brand launched in Tamil Nadu 2025-04-08 (T3 press via search; GCPL press release PDF returned 403, S119, not bypassed). Planned investment Rs 500 Cr over 5 years (press, T3); actual primary infusion Rs 200 Cr (S073). FY26 revenue Rs 2.22 Cr after ~1 year: Niche, provisional given age. FY24/FY25 revenue predates the brand (entity was Godrej Consumer Care Ltd, renamed 2024-10-28). Low revenue may partly reflect a single-state rollout.
A15: Build | B15: calibration | C15: Godrej Consumer Products Ltd | D15: Godrej Protekt | E15: Other | F15: 2018 | M15: =IF(AND(ISNUMBER(G15),ISNUMBER(H15),ISNUMBER(J15),N(J15)>0),G15/(H15/100)/J15,"") | N15: CATEGORY_ENTRY | O15: Hand and home hygiene beyond soap: Protekt was GCPL's vehicle to enter handwash/sanitiser, where it had no brand. | P15: Withdrawn | Q15: P2: AR FY19 (S127 p.151: launches 'during the year 2018-19: 1. Protekt-Mr. Magic Hand Wash'), FY20 (7 mentions), FY21 (13), FY22 (1, brand table only); 0 mentions FY23-FY26. P1: none - no discontinuation statement found. P3: godrejprotekt.com no response on 2026-10-10; P4: last live Wayback capture 2023-03-13 (S207). | R15: included | S15: https://www.bseindia.com/bseplus/AnnualReport/532424/5324240319.pdf | T15: S127;S156;S157;S158;S207 | U15: 2026-10-10 | V15: Low | W15: Protekt domain has Wayback captures from 2009, so the name may be older than the FY19 Mr. Magic launch - original launch year UNCONFIRMED. Mr. Magic: FY19 launch (Apr 2018-Mar 2019; calendar month UNCONFIRMED; year_start 2018 by the FY rule: an FY-only launch takes the calendar year holding 9 of its 12 months), so calibration. Covid expansion: Jul 2020, 12 new hygiene SKUs and stated ambition to be a 'Rs 500 crore brand over the next three years' (fashionnetwork/exchange4media, T3, search snippet only). Disappears from ARs after FY22: the Covid hygiene spike ended and the ambition went unmet. Withdrawal inferred from AR silence (Low).
A16: Build | B16: core | C16: Dabur India Ltd | D16: Dabur Vita | E16: Wellness-Nutrition&Supplements | F16: 2021 | M16: =IF(AND(ISNUMBER(G16),ISNUMBER(H16),ISNUMBER(J16),N(J16)>0),G16/(H16/100)/J16,"") | N16: CATEGORY_ENTRY | O16: Dabur's 'foray into the Health Food Drink category' (S117); it had chyawanprash and honey but no HFD brand. | P16: Withdrawn | Q16: P1: AR FY25 (S176 p.25): 'we have decided to exit categories such as Vedic Tea, Adult & Baby Diapers, and Dabur Vita, where scalability and profitability remain constrained'; AR FY26 (S177 p.85): 'We exited segments such as Vedic Tea, Adult & Baby Diapers, and Dabur Vita'. P2: AR FY22 12 mentions -> FY23 7 -> FY24 5 -> FY25/FY26 only as an exit. P3: daburvita.com redirects to a still-live brand page on dabur.com (2026-10-10; residual page, stock UNCONFIRMED). P4: last live Wayback capture of daburvita.com 2024-03-04 (S206). | R16: included | S16: https://dabur.com/press-releases/dabur-enters-health-food-drink-category-dabur-vita | T16: S117;S173;S176;S177;S206 | U16: 2026-10-10 | V16: High | W16: Launched 2021-12-30 (S117: 'Dabur India Ltd. today announced its foray into the Health Food Drink category with the launch of Dabur Vita'; e-commerce launch with Flipkart, 7 SKUs Rs 10-430). Explicit, parent-stated exit ~3 years after launch: the clearest T1-documented build failure in the set. Revenue never disclosed.
A17: Build | B17: core | C17: Tata Consumer Products Ltd | D17: Tata Simply Better | E17: Food-Staples&Organic | F17: 2022 | M17: =IF(AND(ISNUMBER(G17),ISNUMBER(H17),ISNUMBER(J17),N(J17)>0),G17/(H17/100)/J17,"") | N17: CATEGORY_ENTRY | O17: Launched as TCPL's 'entry into protein platform' with plant-based meat, a category it had no presence in; later re-purposed for cold-pressed oils. | P17: Stable | Q17: P1: AR FY23 (S152 p.21): 'entered the Protein category with plant-based meat under the brand Tata Simply Better'; AR FY24 (S153 p.140): 'launched last year with an innovative portfolio of plant-based meat... complemented by a new range of cold-pressed oils'; AR FY26 (S155 p.25): 'Tata Simply Better expanded its cold-pressed oils portfolio and extended into dry fruit snacking'. P2: in every TCPL AR FY23-FY26. P3: tatasimplybetter.com live ('Buy Cold Pressed Oils Online'), 2026-10-10; P4: Wayback live 2023-03 to 2026-09 (S206). | R17: included | S17: https://www.bseindia.com/xml-data/corpfiling/AttachHis/c0f1ba05-3b73-4ae8-b105-709cf2f22ea3.pdf | T17: S152;S153;S154;S155;S206 | U17: 2026-10-10 | V17: Medium | W17: Launched FY23 (Apr 2022-Mar 2023) as plant-based meat; year_start 2022 (month UNCONFIRMED). The original proposition (plant-based meat) is no longer mentioned after FY24; the brand survives by pivoting to cold-pressed oils (FY24) and dry-fruit snacks (FY26). 'Stable' = alive and extended, but no revenue disclosed and not one of the growth brands TCPL quantifies. Counted as a pivot, not a success, in the base rate.
A18: Build | B18: core | C18: Tata Consumer Products Ltd | D18: Tata GoFit | E18: Wellness-Nutrition&Supplements | F18: 2022 | M18: =IF(AND(ISNUMBER(G18),ISNUMBER(H18),ISNUMBER(J18),N(J18)>0),G18/(H18/100)/J18,"") | N18: CATEGORY_ENTRY | O18: Plant protein powder: second leg of TCPL's 2022 'protein platform', a category it had not been in. | P18: Niche | Q18: P2: AR FY23 (S152 p.21: 'plant protein powder under Tata GoFit'), FY24 brand list (S153 p.15), FY25 (brand-name cover collage only); 0 mentions in AR FY26, whose brand list (S155 p.15) omits it. P3: tatagofit.com live D2C store ('Tata GoFit Plant Protein | Plant Based Protein Powder for Women'), 2026-10-10. P4: Wayback 31 monthly captures 2023-01 to 2026-03, all live (S206). | R18: included | S18: https://www.bseindia.com/xml-data/corpfiling/AttachHis/c0f1ba05-3b73-4ae8-b105-709cf2f22ea3.pdf | T18: S152;S153;S154;S155;S206 | U18: 2026-10-10 | V18: Low | W18: CORRECTION: first coded Withdrawn from the FY26 AR silence alone; the live D2C store (P3/P4) contradicts that, so Niche: still sold, dropped from the parent's brand list. Lesson: AR silence = de-prioritised, not dead. Launched FY23 alongside Simply Better PBM; year_start 2022 (month UNCONFIRMED). In FY24 AR p.45 TCPL calls it a 'digital brand'. No exit statement found. Note TCPL bought Organic India (2024), which overlaps the wellness space.
A19: Build | B19: calibration | C19: Tata Consumer Products Ltd | D19: Tata Sampann (built by Tata Chemicals Ltd; merged into TCPL 2020) | E19: Food-Staples&Organic | J19: 1109 | K19: FY25 | L19: revenue as charted by TCPL ('Tata Sampann Revenue (INR Crores)'); ops vs total income not stated | M19: =IF(AND(ISNUMBER(G19),ISNUMBER(H19),ISNUMBER(J19),N(J19)>0),G19/(H19/100)/J19,"") | N19: CATEGORY_ENTRY | O19: Group-built pulses/spices staples brand: the Tata group's in-house entry into branded staples beyond salt. | P19: Scaled | Q19: P1: AR FY25 (S154 p.42): '29% Tata Sampann revenue growth', chart 'Tata Sampann Revenue (INR Crores)' with FY25 = 1,109 (FY24 862; 862 x 1.29 = 1,112, consistent). P2: in every TCPL AR FY20-FY26. | R19: included | S19: https://www.bseindia.com/bseplus/AnnualReport/500800/5008000320.pdf | T19: S149;S154 | U19: 2026-10-10 | V19: Medium | W19: ORIGIN: not a TCPL build. AR FY20 (S149 p.5): 'Tata Global Beverages was renamed as Tata Consumer Products, following the merger of the Consumer Products business of Tata Chemicals with itself... Tata Salt and Tata Sampann'. Built in-house by Tata Chemicals Ltd (listed). year_start UNCONFIRMED: recalled as 2017 (C045) but no primary source found; certainly pre-2020. Chart labels in the extracted PDF text are out of order; only FY25=1,109 and FY24=862 are cross-checked via the stated 29% growth.
A20: Build | B20: core | C20: FSN E-Commerce Ventures Ltd (Nykaa) | D20: Nykd by Nykaa | E20: Other | F20: 2020 | J20: 150 | K20: FY25 | L20: GMV (gross merchandise value, '>Rs 150 crores (GMV)'); not revenue | M20: =IF(AND(ISNUMBER(G20),ISNUMBER(H20),ISNUMBER(J20),N(J20)>0),G20/(H20/100)/J20,"") | N20: CATEGORY_ENTRY | O20: Lingerie/athleisure: Nykaa's own-brand entry into intimate wear, a category it had only retailed. | P20: Scaled | Q20: P1: AR FY25 (S169 p.20): 'two brands - 20 Dresses and Nykd, already more than Rs 100 crores (GMV) and Rs 150 crores (GMV) brands, respectively in FY2025'; AR FY24 (S168 p.11): 'Both Kay Beauty and Nykd By Nykaa have an annualised GMV run rate of over Rs 1,500 million (basis Q4FY24)'. P2: AR FY24-FY26. FY26 (S170 p.87): expanded into sleepwear and activewear. | R20: excluded_out_of_scope | S20: https://www.bseindia.com/xml-data/corpfiling/AttachHis/316c7dec-30ff-437b-8fe1-8f515bebcaf8.pdf | T20: S168;S169;S170 | U20: 2026-10-10 | V20: Medium | W20: Launch: AR FY24 (S168 p.67): 'We launched Nykd in 2020'; AR FY26 p.87: 'Introduced in 2020'. GMV, not net revenue: Scaled on GMV only. LISTING CAVEAT: launched pre-IPO (Nykaa listed Nov 2021). Fashion brands as a group slowed in FY25 ('Growth slowdown in FY2025') and FY26 fashion GMV was Rs 388 Cr across 5 brands.
A21: Build | B21: calibration | C21: FSN E-Commerce Ventures Ltd (Nykaa) | D21: Kay Beauty (co-created with Katrina Kaif) | E21: BPC-ColourCosmetics | F21: 2019 | J21: 240 | K21: FY25 | L21: GMV ('crossed the GMV of Rs 240 crores'); FY26 stated as Rs 250-350 Cr NSV jointly with Nykaa Cosmetics | M21: =IF(AND(ISNUMBER(G21),ISNUMBER(H21),ISNUMBER(J21),N(J21)>0),G21/(H21/100)/J21,"") | N21: COHORT_EQUITY | O21: Celebrity-led makeup brand: built to borrow a celebrity's cohort, which Nykaa Cosmetics (value makeup) did not have. | P21: Scaled | Q21: P1: AR FY25 (S169 p.16): 'Kay Beauty and Nykaa Cosmetics have crossed the GMV of Rs 240 crores and Rs 350 crores, respectively'; AR FY26 (S170 p.23): 'Nykaa Cosmetics & Kay Beauty have both reached a Rs 250-350 crores NSV'. P2: AR FY22-FY26. | R21: included | S21: https://www.bseindia.com/xml-data/corpfiling/AttachHis/316c7dec-30ff-437b-8fe1-8f515bebcaf8.pdf | T21: S168;S169;S170 | U21: 2026-10-10 | V21: Medium | W21: Launch: AR FY24 (S168 p.18): 'Kay Beauty, India's first celebrity beauty brand launched in FY20' -> FY20 = Apr 2019-Mar 2020; year_start 2019 (recalled 2019, C052). Calibration (pre-2020). Partly a celebrity partnership, so not a pure in-house build. Entered UK via Space NK (FY26).
A22: Build | B22: calibration | C22: ITC Ltd | D22: Bingo! | E22: Food-Snacks&Bars | F22: 2007 | J22: 2700 | K22: FY20 | L22: annual consumer spend (retail value, 'nearly Rs 2700 cr'); NOT company revenue | M22: =IF(AND(ISNUMBER(G22),ISNUMBER(H22),ISNUMBER(J22),N(J22)>0),G22/(H22/100)/J22,"") | N22: CATEGORY_ENTRY | O22: ITC's in-house entry into branded salty snacks. | P22: Scaled | Q22: P1: AR FY20 (S135 p.10): 'Bingo! nearly Rs 2700 cr' annual consumer spend; 'Bingo! is No. 1 in Bridges segment of Snack Foods'. AR FY25 (S140 p.75): 'remains the market leader in the Bridges segment across the country'. P2: every ITC AR FY20-FY26. | R22: included | S22: https://www.bseindia.com/bseplus/AnnualReport/500875/5008750320.pdf | T22: S135;S140 | U22: 2026-10-10 | V22: Medium | W22: Launch year 2007 from secondary sources only (search snippets, T4) - ITC primary not checked; year Low confidence. Consumer-spend figures are not repeated after FY20 AR.
A23: Build | B23: calibration | C23: ITC Ltd | D23: Sunfeast YiPPee! | E23: Food-Snacks&Bars | F23: 2010 | J23: 1300 | K23: FY20 | L23: annual consumer spend (retail value, 'nearly Rs 1300 cr'); NOT company revenue | M23: =IF(AND(ISNUMBER(G23),ISNUMBER(H23),ISNUMBER(J23),N(J23)>0),G23/(H23/100)/J23,"") | N23: CATEGORY_ENTRY | O23: ITC's in-house entry into instant noodles against an entrenched leader (Maggi). | P23: Scaled | Q23: P1: AR FY20 (S135 p.10): 'YiPPee! nearly Rs 1300 cr' annual consumer spend; AR FY25 (S140 p.75): 'YiPPee! sustained its position as a strong No. 2 brand in the Instant Noodles' segment. P2: every ITC AR FY20-FY26. | R23: included | S23: https://www.bseindia.com/bseplus/AnnualReport/500875/5008750320.pdf | T23: S135;S140 | U23: 2026-10-10 | V23: Medium | W23: Launch year 2010 from secondary sources only (T4); ITC primary not checked.
A24: Build | B24: calibration | C24: ITC Ltd | D24: Fabelle | E24: Other | F24: 2016 | M24: =IF(AND(ISNUMBER(G24),ISNUMBER(H24),ISNUMBER(J24),N(J24)>0),G24/(H24/100)/J24,"") | N24: COHORT_EQUITY | O24: Luxury chocolates sold through ITC Hotels boutiques: built to reach a luxury cohort ITC's mass foods did not touch. | P24: Niche | Q24: P1: AR FY20 (S135 p.90): 'exclusive boutiques across 8 ITC Hotels and kiosks at 3 Welcomhotels'; AR FY25 (S140 p.76): 'opened an exclusive Fabelle store at Bengaluru airport, expanding the availability... beyond the luxury boutiques at ITC Hotels and Quick-Commerce channel'. No scale figure ever disclosed. P2: every ITC AR FY20-FY26 (1-4 mentions/yr). | R24: included | S24: https://www.bseindia.com/bseplus/AnnualReport/500875/5008750320.pdf | T24: S135;S140 | U24: 2026-10-10 | V24: Medium | W24: Launch April 2016 per secondary sources (T4); ITC primary not checked. Niche by design (luxury, hotel-led); ITC's mass chocolate push came later under 'Sunfeast Fantastik' (FY24).
A25: Build | B25: core | C25: Bajaj Consumer Care Ltd | D25: Bajaj Zero Grey | E25: BPC-Haircare | F25: 2020 | M25: =IF(AND(ISNUMBER(G25),ISNUMBER(H25),ISNUMBER(J25),N(J25)>0),G25/(H25/100)/J25,"") | N25: COHORT_EQUITY | O25: Premium anti-greying oil sold 'primarily for E-commerce': aimed at an online, premium cohort that mass Almond Drops did not reach. | P25: Withdrawn | Q25: P2: AR FY20 (S192 p.27: 'Bajaj Zero Grey Anti Greying Hair Oil was launched on Ecommerce platforms and in select Pharmacy outlets earlier this year'), FY21 (S193 p.7: 'our digital first brand that has been launched primarily for E-commerce'); FY22-FY23 only in the corporate timeline; 0 mentions FY24-FY26. P3: bajajzerogrey.com gives no response (SSL error) on 2026-10-10. P4: Wayback last live capture 2025-07-10 (S206). | R25: included | S25: https://www.bseindia.com/bseplus/AnnualReport/533229/65052533229.pdf | T25: S192;S193;S195;S206 | U25: 2026-10-10 | V25: Low | W25: Status Withdrawn (Low): domain dead on the check date and AR silent since FY24, but the site was live as late as 2025-07, so it outlived its AR coverage. Launched early 2020 (AR FY22 S194 p.5 timeline: '2020 ... Launched Bajaj Zero Grey Hair Oil'). Not in the FY24 'Digital Brands' list (which names only 100% Pure and Natyv Soul), i.e. dropped within ~3 years; no exit statement found.
A26: Build | B26: core | C26: Bajaj Consumer Care Ltd | D26: Natyv Soul | E26: BPC-Haircare | F26: 2021 | M26: =IF(AND(ISNUMBER(G26),ISNUMBER(H26),ISNUMBER(J26),N(J26)>0),G26/(H26/100)/J26,"") | N26: COHORT_EQUITY | O26: Premium imported-oil (argan/marula) hair range: a digital-first premium cohort Bajaj's mass hair oils did not serve. | P26: Niche | Q26: P2: AR FY22 14 mentions (S194 p.4: 'the launch of Natyv Soul and Bajaj 100% Pure brands to address the ever-evolving needs of the new-age consumers'), FY23 22, FY24 1 (listed under 'Digital Brands'), FY25 1 (brand tile only), FY26 0. P3: natyvsoul.com now redirects to a brand page on the corporate site (bajajconsumercare.com/natyv-soul), 2026-10-10. P4: Wayback last live capture of the standalone store 2023-10-01 (S206). | R26: included | S26: https://www.bseindia.com/bseplus/AnnualReport/533229/73482533229.pdf | T26: S194;S195;S196;S198;S206 | U26: 2026-10-10 | V26: Low | W26: Launched 2021 (AR FY22 S194 p.5 timeline: '2021 ... Launched two digital first brands: Bajaj 100% Pure and Natyv Soul'). Mentions collapse from 22 (FY23) to 1 (FY24) and to 0 (FY26); standalone D2C store closed after 2023 but products still shown on the corporate site, so Niche (not Withdrawn). Marketplace availability UNCONFIRMED.
A27: Build | B27: core | C27: Bajaj Consumer Care Ltd | D27: Bajaj 100% Pure (coconut oil range) | E27: BPC-Haircare | F27: 2021 | M27: =IF(AND(ISNUMBER(G27),ISNUMBER(H27),ISNUMBER(J27),N(J27)>0),G27/(H27/100)/J27,"") | N27: CATEGORY_ENTRY | O27: Bajaj's entry into pure coconut oil ('we entered the coconut oil category'), a large category it had not been in. | P27: Stable | Q27: P1: AR FY24 (S196 p.5): 'We are scaling up Bajaj 100% Pure Coconut Oil across all the channels... the top line for coconut oil witnessed 36% growth in the financial year'; AR FY26 (S198 p.11): 'Bajaj 100% Pure Coconut Oil delivered a resilient performance this fiscal year'. P2: FY22-FY26 every year (15/21/14/14/3). | R27: included | S27: https://www.bseindia.com/bseplus/AnnualReport/533229/73482533229.pdf | T27: S194;S195;S196;S198 | U27: 2026-10-10 | V27: Medium | W27: Launched 2021 as a 'digital first' brand, then taken to all channels: the one Bajaj digital launch that survived, by becoming a mainstream coconut-oil range. No revenue disclosed; '36% growth' is for the coconut oil topline. Stable, not Scaled (no size disclosed; FY26 mentions fall to 3).
A28: Build | B28: core | C28: Zydus Wellness Ltd | D28: I'mlite | E28: Food-Staples&Organic | F28: 2023 | M28: =IF(AND(ISNUMBER(G28),ISNUMBER(H28),ISNUMBER(J28),N(J28)>0),G28/(H28/100)/J28,"") | N28: REVENUE_SCALE | O28: Sugar blended with stevia: extends Zydus's sugar-substitute franchise (Sugar Free) into the much larger sugar shelf. | P28: Unclear | Q28: P1: AR FY24 (S189 p.13): 'We also celebrated the launch of a new brand, I'mlite, a unique formulation of sugar blended with stevia to offer consumers 50% fewer calories than regular sugar'. P2: in AR FY24-FY26 brand lists (FY26 S191 p.7). No performance figure disclosed. | R28: excluded_unclear | S28: https://www.bseindia.com/xml-data/corpfiling/AttachHis/ef8bd328-7e9d-4789-80b2-216a27e41d31.pdf | T28: S189;S190;S191 | U28: 2026-10-10 | V28: Low | W28: FY24 launch (month UNCONFIRMED; year_start 2023 by the FY rule). Still listed but never quantified; too little evidence to call it Stable or Niche.
A29: Build | B29: core | C29: Reliance Industries Ltd (via Reliance Consumer Products Ltd) | D29: Independence | E29: Food-Staples&Organic | F29: 2022 | J29: 2600 | K29: FY26 | L29: 'sales' as stated (~Rs 2,600 crore); gross vs net not stated | M29: =IF(AND(ISNUMBER(G29),ISNUMBER(H29),ISNUMBER(J29),N(J29)>0),G29/(H29/100)/J29,"") | N29: CATEGORY_ENTRY | O29: RCPL's own FMCG staples brand: Reliance's in-house entry into branded packaged staples (it previously only retailed them). | P29: Scaled | Q29: P1: RIL AR FY26 (S205 p.47): 'Independence brand achieved ~Rs 2,600 crore sales'; AR FY25 (S204 p.34): 'Flagship brands such as Campa and Independence are gaining momentum'. P2: RIL AR FY23-FY26. | R29: excluded_captive_channel | S29: https://rilstaticasset.akamaized.net/sites/default/files/2022-12/Media-Release-RRVL-15122022.pdf | T29: S116;S202;S204;S205 | U29: 2026-10-10 | V29: Medium | W29: Launched 2022-12-15 in Gujarat (S116 p.1: 'Reliance Consumer Products Ltd., the FMCG arm and a fully owned subsidiary of Reliance Retail Ventures Ltd., today launched its indigenous made-for-India consumer packaged goods brand, INDEPENDENCE in Gujarat'). Parent per D4: RCPL counted under RIL (listed). CAVEAT: sold heavily through the group's own retail (Reliance Retail/JioMart), a captive channel no other Tab B parent has - scale is not comparable like-for-like. Medium (single T1 figure, basis unstated).
A30: Build | B30: core | C30: Reliance Industries Ltd (via Reliance Consumer Products Ltd) | D30: Campa (HYBRID: dormant name bought 2022, brand rebuilt in-house) | E30: Beverages | F30: 2023 | J30: 4700 | K30: FY26 | L30: gross sales ('Rs 4,700+ crore in gross sales'); not net revenue | M30: =IF(AND(ISNUMBER(G30),ISNUMBER(H30),ISNUMBER(J30),N(J30)>0),G30/(H30/100)/J30,"") | N30: CATEGORY_ENTRY | O30: Reliance had no beverage brand; it bought only a dormant trademark (recall, no revenue or team) and built the business itself - entry by build on a bought name. | P30: Scaled | Q30: P1: RIL AR FY26 (S205 p.47): 'Campa achieved Rs 4,700+ crore in gross sales in FY 2025-26. In March 2026, it became India's fourth-largest carbonated soft drinks brand'; AR FY25 (S204 p.34): '>10% market share in sparkling beverage category in select states'. P2: RIL AR FY23-FY26. | R30: excluded_hybrid | S30: https://www.bseindia.com/xml-data/corpfiling/AttachHis/b55b5dfc-a3bf-4f24-9d7f-ca09774a1dd9.pdf | T30: S202;S204;S205;S112 | U30: 2026-10-10 | V30: Medium | W30: HYBRID - excluded from the pure-build base rate; discussed in Part 3. Trademark bought from Pure Drinks Group in 2022 (~Rs 22 Cr per PTI citing unnamed sources, S112, T3; also Tab A row). Relaunch 2023 (RIL AR FY23 S202 p.77: 'The FMCG business launched several products during the year including Independence brand and the iconic beverage brand, Campa'); relaunch month Mar 2023 per recall (C056) - month UNCONFIRMED by primary source. Beverage investment of up to Rs 8,000 Cr (S113, T4 - not relied on). Same captive-retail caveat as Independence.

Sheet Vocabulary
A1: field | B1: value | C1: tie_break_rank | D1: inclusion_rule
A2: what_was_acquired | B2: CATEGORY_ENTRY | C2: 1 | D2: Parent had no meaningful revenue in this category before the deal
A3: what_was_acquired | B3: DEFENSIVE | C3: 2 | D3: The main logic is denying the asset to a competitor (contested bidding, reported rival interest)
A4: what_was_acquired | B4: COHORT_EQUITY | C4: 3 | D4: Parent was in the category, but the target had credibility with a consumer cohort the parent lacked
A5: what_was_acquired | B5: FOUNDER_TEAM | C5: 4 | D5: The people are the primary asset: revenue small relative to price, founders retained via earn-out/lock-in, AND the parent states the team is the rationale
A6: what_was_acquired | B6: CAPABILITY | C6: 5 | D6: The main asset is a capability (D2C engine, formulation IP, supply chain), not the brand
A7: what_was_acquired | B7: REVENUE_SCALE | C7: 6 | D7: Parent already had the category and cohort; the deal mainly adds revenue and share
A8: deal_structure | B8: full_100 | D8: 100% acquired at first completion
A9: deal_structure | B9: outright_majority | D9: >50% acquired at first completion; any later top-up of the remainder is noted, not reclassified
A10: deal_structure | B10: staged_to_control | D10: First tranche <=50%, with contracted further tranches taking the parent to majority or 100%
A11: deal_structure | B11: minority_with_path | D11: Minority stake with options/rights to increase, but no committed schedule to control
A12: deal_structure | B12: minority_no_path | D12: Non-controlling stake (<=50%, incl. 50:50 JVs) with no disclosed option, right or schedule to reach control
A13: row_type | B13: core | D13: year_start >= 2020; counts toward the study's minimums (Tab A >= 10; Tab B >= 5)
A14: row_type | B14: calibration | D14: Pre-2020 build or deal, used only to calibrate the Part 1 success rate (e.g. Lever Ayush, Bingo!, Yippee!)
A15: category | B15: BPC-Skincare | D15: Face and body skincare, incl. actives/derma
A16: category | B16: BPC-Haircare | D16: Hair oils, shampoos, hair treatments
A17: category | B17: BPC-MensGrooming | D17: Brands built for men (beard, grooming, men's fragrance/deo)
A18: category | B18: BPC-Baby&Mother | D18: Baby care and maternity personal care
A19: category | B19: BPC-ColourCosmetics | D19: Make-up/colour cosmetics (lips, face, eyes, nails)
... A31: base_rate_flag | B31: excluded_unclear | D31: Status cannot be called on the evidence (status_today = Unclear)

Sheet Assumptions
A1: assumption_id | B1: parameter | C1: value_low | D1: value_base | E1: value_high | F1: unit | G1: build_favourable | H1: Bull | I1: Base | J1: Bear | K1: source_ids | L1: rationale | M1: confidence
A2: A01 | B2: years_to_scale | C2: 4 | D2: 6 | E2: 8 | F2: years from launch (Y1) to Rs 347 Cr revenue; conditional on success | G2: low | H2: =IF($G2="low",$C2,IF($G2="high",$E2,$D2)) -> 4 | I2: =$D2 -> 6 | J2: =IF($G2="low",$E2,IF($G2="high",$C2,$D2)) -> 8 | K2: S007;S163;S165;S208 | L2: Bull = D2C-native pace: Minimalist founded 2020 (S007: 'Founded in 2020'), FY24 turnover Rs 347 Cr (S007) = ~4 yrs; The Derma Co 'Rs 500 Cr+ Net ARR ... within 50 Months of Launch' (S163 PDF p.17) = ~3.5 yrs to Rs 347 Cr. Bear = Aqualogica path: 'Rs 180 Cr+ Net ARR ... within 19 Months' (S163 p.17) then ~Rs 200 Cr ARR by FY26 (S165 p.8), i.e. not at Rs 347 Cr after 5 yrs. Base 6 = an FMCG parent slower than the fastest D2C natives (HUL's own digital-first launches never disclosed revenue). Benchmarks are survivors: conditional-on-success only. | M2: Medium
A3: A02 | B3: y1_revenue | C3: 15 | D3: 25 | E3: 35 | F3: Rs Cr in first launch year | G3: high | H3: =IF($G3="low",$C3,IF($G3="high",$E3,$D3)) -> 35 | I3: =$D3 -> 25 | J3: =IF($G3="low",$E3,IF($G3="high",$C3,$D3)) -> 15 | K3: S007;S208 | L3: Derived. Minimalist FY22 turnover Rs 103 Cr in its ~2nd-3rd year (S007; Entrackr says Rs 108 Cr, S208); year-1 revenue of any benchmark not disclosed. UNCONFIRMED: no year-1 benchmark. | M3: Low
A4: A03 | B4: gross_margin_early | C4: 0.55 | D4: 0.6 | E4: 0.65 | F4: % of revenue in Y1-Y2 | G4: high | H4: =IF($G4="low",$C4,IF($G4="high",$E4,$D4)) -> 0.65 | I4: =$D4 -> 0.6 | J4: =IF($G4="low",$E4,IF($G4="high",$C4,$D4)) -> 0.55 | K4: S163 | L4: Derived: small batches, third-party manufacturing, launch discounting; set ~10 pts below scale margin. Honasa improved GM by procurement efficiencies (S163 PDF p.37). UNCONFIRMED: no launch-year GM disclosed. | M4: Low
A5: A04 | B5: gross_margin_scale | C5: 0.62 | D5: 0.7 | E5: 0.73 | F5: % of revenue from scale year | G5: high | H5: =IF($G5="low",$C5,IF($G5="high",$E5,$D5)) -> 0.73 | I5: =$D5 -> 0.7 | J5: =IF($G5="low",$E5,IF($G5="high",$C5,$D5)) -> 0.62 | K5: S163;S165;S208;S209;S134 | L5: Honasa '69.8% Gross Margin' FY24 (S163 PDF p.4); 'gross margin of 71.2%' FY26 (S165 PDF p.52). Minimalist materials-only margin 73% FY24 (Rs 94 Cr materials / Rs 347 Cr, S208) and 71.5% FY25 (146.7/514.8, S209) - materials only, overstates GM. Low 62 = between Honasa and HUL company GM 'Gross Margin of 50.3%' (S134 PDF p.44). | M5: Medium
A6: A05 | B6: ap_pct_launch | C6: 0.4 | D6: 0.5 | E6: 0.6 | F6: % of revenue in Y1-Y2 | G6: low | H6: =IF($G6="low",$C6,IF($G6="high",$E6,$D6)) -> 0.4 | I6: =$D6 -> 0.5 | J6: =IF($G6="low",$E6,IF($G6="high",$C6,$D6)) -> 0.6 | K6: S163 | L6: Honasa: 'reducing it by over 700 bps over last three years to 34.4% in FY 23-24' (S163 PDF p.16) => >41% in FY21 when Derma Co/Aqualogica were launching; a new single brand without a portfolio halo spends more. Base 50 derived. | M6: Low
A7: A06 | B7: ap_pct_growth | C7: 0.33 | D7: 0.38 | E7: 0.45 | F7: % of revenue from Y3 to scale year | G7: low | H7: =IF($G7="low",$C7,IF($G7="high",$E7,$D7)) -> 0.33 | I7: =$D7 -> 0.38 | J7: =IF($G7="low",$E7,IF($G7="high",$C7,$D7)) -> 0.45 | K7: S163;S208 | L7: Minimalist A&P Rs 65 Cr / Rs 184 Cr = 35% FY23 and Rs 117 Cr / Rs 347 Cr = 34% FY24 (S208); Honasa 'Rs 6,612.80 Million (34.4% of revenue) in FY 23-24 ... Rs 5,302.78 Million (35.5% of revenue) for the FY 22-23' (S163 PDF p.37). Base 38 = HUL brand has no founder-led organic reach. | M7: Medium
A8: A07 | B8: ap_pct_scale | C8: 0.25 | D8: 0.3 | E8: 0.34 | F8: % of revenue after scale | G8: low | H8: =IF($G8="low",$C8,IF($G8="high",$E8,$D8)) -> 0.25 | I8: =$D8 -> 0.3 | J8: =IF($G8="low",$E8,IF($G8="high",$C8,$D8)) -> 0.34 | K8: S209 | L8: Minimalist A&P Rs 154 Cr / Rs 514.8 Cr = 30% FY25 (S209). HUL company A&P Rs 6,261 Cr / Rs 64,468 Cr = 9.7% (S134 PDF p.186 and p.211) is NOT a valid benchmark for a digital brand; shown for contrast only. | M8: Medium
A9: A08 | B9: var_opex_pct | C9: 0.2 | D9: 0.25 | E9: 0.32 | F9: % of revenue (distribution + fulfilment + other overheads) | G9: low | H9: =IF($G9="low",$C9,IF($G9="high",$E9,$D9)) -> 0.2 | I9: =$D9 -> 0.25 | J9: =IF($G9="low",$E9,IF($G9="high",$C9,$D9)) -> 0.32 | K9: S209 | L9: Minimalist FY25: distribution Rs 84.3 Cr (16.4%) + other overheads Rs 82 Cr (15.9%) (S209) = 32% (high). Base 25: 'other overheads' likely includes one-offs; FY24 non-material non-A&P costs = (331-94-117)/347 = 35% incl. employees (S208). | M9: Low
A10: A09 | B10: org_cost_floor | C10: 12 | D10: 20 | E10: 30 | F10: Rs Cr per year (fixed) | G10: low | H10: =IF($G10="low",$C10,IF($G10="high",$E10,$D10)) -> 12 | I10: =$D10 -> 20 | J10: =IF($G10="low",$E10,IF($G10="high",$C10,$D10)) -> 30 | K10: S163;S131 | L10: Cost of a ring-fenced digital team inside FMCG (brand, performance marketing, D2C tech, content studio, e-com ops, regulatory): fixed floor before revenue covers it. Derived; Honasa ran ~6 brands on Rs 170.6 Cr employee cost in FY24 (S163 PDF p.37) = ~Rs 28 Cr per brand. HUL ran its digital-first launches via an 'Agile Innovation Hub' (S131 PDF p.31); cost not disclosed. UNCONFIRMED. | M10: Low
A11: A10 | B11: org_cost_pct | C11: 0.06 | D11: 0.075 | E11: 0.09 | F11: % of revenue (org cost = max(floor; pct x revenue)) | G11: low | H11: =IF($G11="low",$C11,IF($G11="high",$E11,$D11)) -> 0.06 | I11: =$D11 -> 0.075 | J11: =IF($G11="low",$E11,IF($G11="high",$C11,$D11)) -> 0.09 | K11: S163;S209 | L11: Minimalist employee cost Rs 36.8 Cr / Rs 514.8 Cr = 7.1% FY25 (S209); Honasa 'Rs 1,705.63 Million (8.9% of revenue) in FY 23-24 from ... (11% of revenue) in FY 22-23' (S163 PDF p.37). | M11: Medium
A12: A11 | B12: rnd_floor | C12: 3 | D12: 5 | E12: 8 | F12: Rs Cr per year (fixed; from Y0) | G12: low | H12: =IF($G12="low",$C12,IF($G12="high",$E12,$D12)) -> 3 | I12: =$D12 -> 5 | J12: =IF($G12="low",$E12,IF($G12="high",$C12,$D12)) -> 8 | K12: S134 | L12: UNCONFIRMED: neither Honasa nor Minimalist discloses R&D spend (Honasa BRSR gives only % of R&D in sustainable tech). HUL's goodwill on Minimalist is 'on account of expected synergies arising from Research & Development, innovations' (S134 Note 43(F), PDF p.225). Derived floor: formulation team + stability/safety testing. | M12: Low
A13: A12 | B13: rnd_pct | C13: 0.01 | D13: 0.02 | E13: 0.03 | F13: % of revenue on top of floor | G13: low | H13: =IF($G13="low",$C13,IF($G13="high",$E13,$D13)) -> 0.01 | I13: =$D13 -> 0.02 | J13: =IF($G13="low",$E13,IF($G13="high",$C13,$D13)) -> 0.03 | K13: S134 | L13: UNCONFIRMED: derived (see A11). | M13: Low
... A19: A18 | B19: acquired_rev_y0 | C19: 652 | D19: 690 | E19: 690 | F19: Rs Cr (FY26 revenue of Minimalist) | G19: low | H19: =IF($G19="low",$C19,IF($G19="high",$E19,$D19)) -> 652 | I19: =$D19 -> 690 | J19: =IF($G19="low",$E19,IF($G19="high",$C19,$D19)) -> 690 | K19: S134 | L19: 'From the date of acquisition, USPL has contributed Rs 652 crores of revenue' (S134 Note 43(I), PDF p.225) for 21 Apr 2025-31 Mar 2026 (345 days). Base = annualised 652 x 365/345 = Rs 690 Cr (+34% on FY25 Rs 514.8 Cr, S209). Low = as reported. NOTE: same note says pro-forma revenue 'would have been Rs 89 crores' - clearly an incremental or typo figure; not used. | M19: Medium
A20: A19 | B20: integration_cost | C20: 25 | D20: 50 | E20: 100 | F20: Rs Cr one-off | G20: high | H20: =IF($G20="low",$C20,IF($G20="high",$E20,$D20)) -> 100 | I20: =$D20 -> 50 | J20: =IF($G20="low",$E20,IF($G20="high",$C20,$D20)) -> 25 | L20: UNCONFIRMED: HUL has not disclosed integration costs for Minimalist. Derived (offline rollout, systems, people retention). | M20: Low
A21: A20 | B21: remaining_stake_cost | C21: 284 | D21: 501 | E21: 650 | F21: Rs Cr for the remaining 9.5% | G21: high | H21: =IF($G21="low",$C21,IF($G21="high",$E21,$D21)) -> 650 | I21: =$D21 -> 501 | J21: =IF($G21="low",$E21,IF($G21="high",$C21,$D21)) -> 284 | K21: S134;S002 | L21: Base: HUL recognised the forward rights on the 9.5% NCI at PV 'Rs 501 crores' (S134 Note 43(C), PDF p.224). Low: 9.5% at the completion price, 2,706.45 / 90.5 x 9.5 = Rs 284 Cr (S002). High 650: derived, if FY27 performance lifts the formula price. | M21: Medium
A22: A21 | B22: cash_acquired | C22: 41 | D22: 41 | E22: 71 | F22: Rs Cr | G22: low | H22: =IF($G22="low",$C22,IF($G22="high",$E22,$D22)) -> 41 | I22: =$D22 -> 41 | J22: =IF($G22="low",$E22,IF($G22="high",$C22,$D22)) -> 71 | K22: S134 | L22: 'Cash and cash equivalents acquired from USPL (41)'; 'Net cash paid 2,665' (S134 Note 43, PDF p.225). High adds 'Bank balances other than cash and cash equivalents 30'. | M22: High
A23: A22 | B23: transaction_costs | C23: 17 | D23: 17 | E23: 17 | F23: Rs Cr | G23: base | H23: =IF($G23="low",$C23,IF($G23="high",$E23,$D23)) -> 17 | I23: =$D23 -> 17 | J23: =IF($G23="low",$E23,IF($G23="high",$C23,$D23)) -> 17 | K23: S134 | L23: 'related transaction costs of Rs 17 crores' (S134 Note 43(H), PDF p.225). | M23: High
A24: A23 | B24: failed_attempt_years | C24: 2 | D24: 3 | E24: 4 | F24: years a failed build runs before it is shut | G24: base | H24: =IF($G24="low",$C24,IF($G24="high",$E24,$D24)) -> 3 | I24: =$D24 -> 3 | J24: =IF($G24="low",$E24,IF($G24="high",$C24,$D24)) -> 3 | K24: data/tab_b.csv | L24: Acne Squad: launched FY23, absent from ARs from FY24, store dead by 2025; Find Your Happy Place: live ~1 year (tab_b status_evidence). Used only in the refined cross-check (failed attempts cost less than a full ramp). | M24: Low
A25: A24 | B25: terminal_growth | C25: 0.05 | D25: 0.05 | E25: 0.05 | F25: % per year after Y10 | G25: base | H25: =IF($G25="low",$C25,IF($G25="high",$E25,$D25)) -> 0.05 | I25: =$D25 -> 0.05 | J25: =IF($G25="low",$E25,IF($G25="high",$C25,$D25)) -> 0.05 | K25: S134 | L25: HUL impairment test: 'Terminal growth rate linearly declining for ten years from year 6 and at 5% thereafter' (S134 PDF p.149). Used to capitalise the Y10 revenue gap (share loss). | M25: High
A26: A25 | B26: target_revenue | C26: 347 | D26: 347 | E26: 347 | F26: Rs Cr | G26: base | H26: =IF($G26="low",$C26,IF($G26="high",$E26,$D26)) -> 347 | I26: =$D26 -> 347 | J26: =IF($G26="low",$E26,IF($G26="high",$C26,$D26)) -> 347 | K26: S007 | L26: Minimalist FY24 'turnover of the Business' Rs 347 Cr (S007); Entrackr 'revenue from operations ... Rs 347 crore' (S208). | M26: High
A28: Model constants (hard-coded in scripts/build_model.py)
A29: headline_price | B29: Headline price paid for 90.5% (cash at completion) | D29: 2706.45 | K29: S002 HUL completion letter
A30: m0 | B30: Minimalist EBITDA margin at Y0 (FY25: ₹18 Cr / ₹514.8 Cr) | D30: 0.035 | K30: S209
A31: psg1 | B31: Built brand growth, 1st year after scale (Minimalist FY25) | D31: 0.48 | K31: S209
A32: psg2 | B32: Built brand growth, 2nd year after scale (Minimalist FY26 annualised) | D32: 0.34 | K32: S134
A33: ramp | B33: Years for EBITDA margin to reach steady state | D33: 5 | K33: Modelling choice
A35: Blue = input. Yellow = formula. % drivers are stored as fractions (60% = 0.60). Bull = every driver at its build-favourable end, Bear = the opposite; valuation inputs (discount rate, terminal growth, target, transaction costs, failed-attempt years) stay at base.

Sheet Build_Model
A1: Part 1: what would it cost HUL to build Minimalist? Live model (all inputs on Assumptions)
A2: ₹ Cr, pre-tax, Y0 = FY26. Build revenue is conditional on success; P(success) enters via risk-adjusted cost. Mirrors scripts/build_model.py.
A4: Scenario: Base
B5: Years to scale T (rounded) | C5: =ROUND(Assumptions!$I$2,0) -> 6
B6: Growth to scale g = (target / Y1 revenue)^(1/(T-1)) | C6: =(Assumptions!$I$26/Assumptions!$I$3)^(1/($C$5-1)) -> 1.6923021
B7: Failed-attempt years (int) | C7: =INT(Assumptions!$I$24) -> 3
B9: Year (Y0 = FY26) | C9: 0 | D9: 1 | E9: 2 | F9: 3 | G9: 4 | H9: 5 | I9: 6 | J9: 7 | K9: 8 | L9: 9 | M9: 10
B10: Revenue (build, if it succeeds) | C10: =IF(C$9=0,0,IF(C$9<=$C$5,Assumptions!$I$3*$C$6^(C$9-1),0)) -> 0 | D10: =IF(D$9=0,0,IF(D$9<=$C$5,Assumptions!$I$3*$C$6^(D$9-1),C10*(1+IF(D$9-$C$5=1,Assumptions!$D$31,IF(D$9-$C$5=2,Assumptions!$D$32,Assumptions!$I$16))))) -> 25 | E10: =IF(E$9=0,0,IF(E$9<=$C$5,Assumptions!$I$3*$C$6^(E$9-1),D10*(1+IF(E$9-$C$5=1,Assumptions!$D$31,IF(E$9-$C$5=2,Assumptions!$D$32,Assumptions!$I$16))))) -> 42.307552 | F10: =IF(F$9=0,0,IF(F$9<=$C$5,Assumptions!$I$3*$C$6^(F$9-1),E10*(1+IF(F$9-$C$5=1,Assumptions!$D$31,IF(F$9-$C$5=2,Assumptions!$D$32,Assumptions!$I$16))))) -> 71.59716 | G10: =IF(G$9=0,0,IF(G$9<=$C$5,Assumptions!$I$3*$C$6^(G$9-1),F10*(1+IF(G$9-$C$5=1,Assumptions!$D$31,IF(G$9-$C$5=2,Assumptions!$D$32,Assumptions!$I$16))))) -> 121.16402 | H10: =IF(H$9=0,0,IF(H$9<=$C$5,Assumptions!$I$3*$C$6^(H$9-1),G10*(1+IF(H$9-$C$5=1,Assumptions!$D$31,IF(H$9-$C$5=2,Assumptions!$D$32,Assumptions!$I$16))))) -> 205.04613 | I10: =IF(I$9=0,0,IF(I$9<=$C$5,Assumptions!$I$3*$C$6^(I$9-1),H10*(1+IF(I$9-$C$5=1,Assumptions!$D$31,IF(I$9-$C$5=2,Assumptions!$D$32,Assumptions!$I$16))))) -> 347 | J10: =IF(J$9=0,0,IF(J$9<=$C$5,Assumptions!$I$3*$C$6^(J$9-1),I10*(1+IF(J$9-$C$5=1,Assumptions!$D$31,IF(J$9-$C$5=2,Assumptions!$D$32,Assumptions!$I$16))))) -> 513.56 | K10: =IF(K$9=0,0,IF(K$9<=$C$5,Assumptions!$I$3*$C$6^(K$9-1),J10*(1+IF(K$9-$C$5=1,Assumptions!$D$31,IF(K$9-$C$5=2,Assumptions!$D$32,Assumptions!$I$16))))) -> 688.1704 | ... M10: =IF(M$9=0,0,IF(M$9<=$C$5,Assumptions!$I$3*$C$6^(M$9-1),L10*(1+IF(M$9-$C$5=1,Assumptions!$D$31,IF(M$9-$C$5=2,Assumptions!$D$32,Assumptions!$I$16))))) -> 863.24095
B11: Gross margin % | C11: =IF(C$9=0,0,IF(C$9<=$C$5,IF(C$9<=2,Assumptions!$I$4,Assumptions!$I$4+(C$9-2)/MAX($C$5-2,1)*(Assumptions!$I$5-Assumptions!$I$4)),Assumptions!$I$5)) -> 0 | D11: =IF(D$9=0,0,IF(D$9<=$C$5,IF(D$9<=2,Assumptions!$I$4,Assumptions!$I$4+(D$9-2)/MAX($C$5-2,1)*(Assumptions!$I$5-Assumptions!$I$4)),Assumptions!$I$5)) -> 0.6 | E11: =IF(E$9=0,0,IF(E$9<=$C$5,IF(E$9<=2,Assumptions!$I$4,Assumptions!$I$4+(E$9-2)/MAX($C$5-2,1)*(Assumptions!$I$5-Assumptions!$I$4)),Assumptions!$I$5)) -> 0.6 | F11: =IF(F$9=0,0,IF(F$9<=$C$5,IF(F$9<=2,Assumptions!$I$4,Assumptions!$I$4+(F$9-2)/MAX($C$5-2,1)*(Assumptions!$I$5-Assumptions!$I$4)),Assumptions!$I$5)) -> 0.625 | G11: =IF(G$9=0,0,IF(G$9<=$C$5,IF(G$9<=2,Assumptions!$I$4,Assumptions!$I$4+(G$9-2)/MAX($C$5-2,1)*(Assumptions!$I$5-Assumptions!$I$4)),Assumptions!$I$5)) -> 0.65 | H11: =IF(H$9=0,0,IF(H$9<=$C$5,IF(H$9<=2,Assumptions!$I$4,Assumptions!$I$4+(H$9-2)/MAX($C$5-2,1)*(Assumptions!$I$5-Assumptions!$I$4)),Assumptions!$I$5)) -> 0.675 | I11: =IF(I$9=0,0,IF(I$9<=$C$5,IF(I$9<=2,Assumptions!$I$4,Assumptions!$I$4+(I$9-2)/MAX($C$5-2,1)*(Assumptions!$I$5-Assumptions!$I$4)),Assumptions!$I$5)) -> 0.7 | J11: =IF(J$9=0,0,IF(J$9<=$C$5,IF(J$9<=2,Assumptions!$I$4,Assumptions!$I$4+(J$9-2)/MAX($C$5-2,1)*(Assumptions!$I$5-Assumptions!$I$4)),Assumptions!$I$5)) -> 0.7 | ... M11: =IF(M$9=0,0,IF(M$9<=$C$5,IF(M$9<=2,Assumptions!$I$4,Assumptions!$I$4+(M$9-2)/MAX($C$5-2,1)*(Assumptions!$I$5-Assumptions!$I$4)),Assumptions!$I$5)) -> 0.7
B12: A&P % of revenue | C12: =IF(C$9=0,0,IF(C$9<=$C$5,IF(C$9<=2,Assumptions!$I$6,Assumptions!$I$7),Assumptions!$I$8)) -> 0 | D12: =IF(D$9=0,0,IF(D$9<=$C$5,IF(D$9<=2,Assumptions!$I$6,Assumptions!$I$7),Assumptions!$I$8)) -> 0.5 | E12: =IF(E$9=0,0,IF(E$9<=$C$5,IF(E$9<=2,Assumptions!$I$6,Assumptions!$I$7),Assumptions!$I$8)) -> 0.5 | F12: =IF(F$9=0,0,IF(F$9<=$C$5,IF(F$9<=2,Assumptions!$I$6,Assumptions!$I$7),Assumptions!$I$8)) -> 0.38 | G12: =IF(G$9=0,0,IF(G$9<=$C$5,IF(G$9<=2,Assumptions!$I$6,Assumptions!$I$7),Assumptions!$I$8)) -> 0.38 | H12: =IF(H$9=0,0,IF(H$9<=$C$5,IF(H$9<=2,Assumptions!$I$6,Assumptions!$I$7),Assumptions!$I$8)) -> 0.38 | I12: =IF(I$9=0,0,IF(I$9<=$C$5,IF(I$9<=2,Assumptions!$I$6,Assumptions!$I$7),Assumptions!$I$8)) -> 0.38 | J12: =IF(J$9=0,0,IF(J$9<=$C$5,IF(J$9<=2,Assumptions!$I$6,Assumptions!$I$7),Assumptions!$I$8)) -> 0.3 | ... M12: =IF(M$9=0,0,IF(M$9<=$C$5,IF(M$9<=2,Assumptions!$I$6,Assumptions!$I$7),Assumptions!$I$8)) -> 0.3
B13: Gross profit | C13: =C11*C10 -> 0 | D13: =D11*D10 -> 15 | E13: =E11*E10 -> 25.384531 | F13: =F11*F10 -> 44.748225 | G13: =G11*G10 -> 78.756616 | H13: =H11*H10 -> 138.40614 | I13: =I11*I10 -> 242.9 | J13: =J11*J10 -> 359.492 | ... M13: =M11*M10 -> 604.26866
B14: Marketing (A&P) | C14: =C12*C10 -> 0 | D14: =D12*D10 -> 12.5 | E14: =E12*E10 -> 21.153776 | F14: =F12*F10 -> 27.206921 | G14: =G12*G10 -> 46.042329 | H14: =H12*H10 -> 77.91753 | I14: =I12*I10 -> 131.86 | J14: =J12*J10 -> 154.068 | ... M14: =M12*M10 -> 258.97228
B15: R&D | C15: =Assumptions!$I$12+Assumptions!$I$13*C10 -> 5 | D15: =Assumptions!$I$12+Assumptions!$I$13*D10 -> 5.5 | E15: =Assumptions!$I$12+Assumptions!$I$13*E10 -> 5.846151 | F15: =Assumptions!$I$12+Assumptions!$I$13*F10 -> 6.4319432 | G15: =Assumptions!$I$12+Assumptions!$I$13*G10 -> 7.4232805 | H15: =Assumptions!$I$12+Assumptions!$I$13*H10 -> 9.1009226 | I15: =Assumptions!$I$12+Assumptions!$I$13*I10 -> 11.94 | J15: =Assumptions!$I$12+Assumptions!$I$13*J10 -> 15.2712 | ... M15: =Assumptions!$I$12+Assumptions!$I$13*M10 -> 22.264819
B16: Org cost | C16: =IF(C$9=0,0.5*Assumptions!$I$10,MAX(Assumptions!$I$10,Assumptions!$I$11*C10)) -> 10 | D16: =IF(D$9=0,0.5*Assumptions!$I$10,MAX(Assumptions!$I$10,Assumptions!$I$11*D10)) -> 20 | E16: =IF(E$9=0,0.5*Assumptions!$I$10,MAX(Assumptions!$I$10,Assumptions!$I$11*E10)) -> 20 | F16: =IF(F$9=0,0.5*Assumptions!$I$10,MAX(Assumptions!$I$10,Assumptions!$I$11*F10)) -> 20 | G16: =IF(G$9=0,0.5*Assumptions!$I$10,MAX(Assumptions!$I$10,Assumptions!$I$11*G10)) -> 20 | H16: =IF(H$9=0,0.5*Assumptions!$I$10,MAX(Assumptions!$I$10,Assumptions!$I$11*H10)) -> 20 | I16: =IF(I$9=0,0.5*Assumptions!$I$10,MAX(Assumptions!$I$10,Assumptions!$I$11*I10)) -> 26.025 | J16: =IF(J$9=0,0.5*Assumptions!$I$10,MAX(Assumptions!$I$10,Assumptions!$I$11*J10)) -> 38.517 | ... M16: =IF(M$9=0,0.5*Assumptions!$I$10,MAX(Assumptions!$I$10,Assumptions!$I$11*M10)) -> 64.743071
B17: Distribution & overheads (pre-scale rule) | C17: =IF(C$9=0,0,Assumptions!$I$9*C10) -> 0 | D17: =IF(D$9=0,0,Assumptions!$I$9*D10) -> 6.25 | E17: =IF(E$9=0,0,Assumptions!$I$9*E10) -> 10.576888 | F17: =IF(F$9=0,0,Assumptions!$I$9*F10) -> 17.89929 | G17: =IF(G$9=0,0,Assumptions!$I$9*G10) -> 30.291006 | H17: =IF(H$9=0,0,Assumptions!$I$9*H10) -> 51.261533 | I17: =IF(I$9=0,0,Assumptions!$I$9*I10) -> 86.75 | J17: =IF(J$9=0,0,Assumptions!$I$9*J10) -> 128.39 | ... M17: =IF(M$9=0,0,Assumptions!$I$9*M10) -> 215.81024
B18: EBITDA (pre-scale rule) | C18: =C13-C14-C17-C16-C15 -> -15 | D18: =D13-D14-D17-D16-D15 -> -29.25 | E18: =E13-E14-E17-E16-E15 -> -32.192284 | F18: =F13-F14-F17-F16-F15 -> -26.789929 | G18: =G13-G14-G17-G16-G15 -> -25 | H18: =H13-H14-H17-H16-H15 -> -19.873847 | I18: =I13-I14-I17-I16-I15 -> -13.675 | J18: =J13-J14-J17-J16-J15 -> 23.2458 | ... M18: =M13-M14-M17-M16-M15 -> 42.478252
B19: Distribution & overheads (plug after scale) | C19: =IF(C$9<=$C$5,C17,C13-C14-C16-C15-C20) -> 0 | D19: =IF(D$9<=$C$5,D17,D13-D14-D16-D15-D20) -> 6.25 | E19: =IF(E$9<=$C$5,E17,E13-E14-E16-E15-E20) -> 10.576888 | F19: =IF(F$9<=$C$5,F17,F13-F14-F16-F15-F20) -> 17.89929 | G19: =IF(G$9<=$C$5,G17,G13-G14-G16-G15-G20) -> 30.291006 | H19: =IF(H$9<=$C$5,H17,H13-H14-H16-H15-H20) -> 51.261533 | I19: =IF(I$9<=$C$5,I17,I13-I14-I16-I15-I20) -> 86.75 | J19: =IF(J$9<=$C$5,J17,J13-J14-J16-J15-J20) -> 116.71372 | ... M19: =IF(M$9<=$C$5,M17,M13-M14-M16-M15-M20) -> 114.12725
B20: EBITDA | C20: =IF(C$9<=$C$5,C18,($C$29+(Assumptions!$I$18-$C$29)*MIN(MAX(C$9-$C$5,0)/Assumptions!$D$33,1))*C10) -> -15 | D20: =IF(D$9<=$C$5,D18,($C$29+(Assumptions!$I$18-$C$29)*MIN(MAX(D$9-$C$5,0)/Assumptions!$D$33,1))*D10) -> -29.25 | E20: =IF(E$9<=$C$5,E18,($C$29+(Assumptions!$I$18-$C$29)*MIN(MAX(E$9-$C$5,0)/Assumptions!$D$33,1))*E10) -> -32.192284 | F20: =IF(F$9<=$C$5,F18,($C$29+(Assumptions!$I$18-$C$29)*MIN(MAX(F$9-$C$5,0)/Assumptions!$D$33,1))*F10) -> -26.789929 | G20: =IF(G$9<=$C$5,G18,($C$29+(Assumptions!$I$18-$C$29)*MIN(MAX(G$9-$C$5,0)/Assumptions!$D$33,1))*G10) -> -25 | H20: =IF(H$9<=$C$5,H18,($C$29+(Assumptions!$I$18-$C$29)*MIN(MAX(H$9-$C$5,0)/Assumptions!$D$33,1))*H10) -> -19.873847 | I20: =IF(I$9<=$C$5,I18,($C$29+(Assumptions!$I$18-$C$29)*MIN(MAX(I$9-$C$5,0)/Assumptions!$D$33,1))*I10) -> -13.675 | J20: =IF(J$9<=$C$5,J18,($C$29+(Assumptions!$I$18-$C$29)*MIN(MAX(J$9-$C$5,0)/Assumptions!$D$33,1))*J10) -> 34.92208 | ... M20: =IF(M$9<=$C$5,M18,($C$29+(Assumptions!$I$18-$C$29)*MIN(MAX(M$9-$C$5,0)/Assumptions!$D$33,1))*M10) -> 144.16124
B21: Net working capital | C21: =Assumptions!$I$14/365*C10 -> 0 | D21: =Assumptions!$I$14/365*D10 -> 2.0547945 | E21: =Assumptions!$I$14/365*E10 -> 3.4773331 | F21: =Assumptions!$I$14/365*F10 -> 5.8846981 | G21: =Assumptions!$I$14/365*G10 -> 9.9586869 | H21: =Assumptions!$I$14/365*H10 -> 16.853107 | I21: =Assumptions!$I$14/365*I10 -> 28.520548 | J21: =Assumptions!$I$14/365*J10 -> 42.210411 | ... M21: =Assumptions!$I$14/365*M10 -> 70.951311
B22: Working-capital investment | C22: =C21 -> 0 | D22: =D21-C21 -> 2.0547945 | E22: =E21-D21 -> 1.4225386 | F22: =F21-E21 -> 2.407365 | G22: =G21-F21 -> 4.0739888 | H22: =H21-G21 -> 6.8944199 | I22: =I21-H21 -> 11.667441 | J22: =J21-I21 -> 13.689863 | K22: =K21-J21 -> 14.35154 | ... M22: =M21-L21 -> 7.6019262
B23: Free cash flow | C23: =C20-C22 -> -15 | D23: =D20-D22 -> -31.304795 | E23: =E20-E22 -> -33.614822 | F23: =F20-F22 -> -29.197294 | G23: =G20-G22 -> -29.073989 | H23: =H20-H22 -> -26.768267 | I23: =I20-I22 -> -25.342441 | J23: =J20-J22 -> 21.232217 | ... M23: =M20-M22 -> 136.55931
B24: Cash burn | C24: =MAX(-C23,0) -> 15 | D24: =MAX(-D23,0) -> 31.304795 | E24: =MAX(-E23,0) -> 33.614822 | F24: =MAX(-F23,0) -> 29.197294 | G24: =MAX(-G23,0) -> 29.073989 | H24: =MAX(-H23,0) -> 26.768267 | I24: =MAX(-I23,0) -> 25.342441 | J24: =MAX(-J23,0) -> 0 | ... M24: =MAX(-M23,0) -> 0
B25: Cumulative cash | C25: =C23 -> -15 | D25: =C25+D23 -> -46.304795 | E25: =D25+E23 -> -79.919617 | F25: =E25+F23 -> -109.11691 | G25: =F25+G23 -> -138.1909 | H25: =G25+H23 -> -164.95917 | I25: =H25+I23 -> -190.30161 | J25: =I25+J23 -> -169.06939 | K25: =J25+K23 -> -113.91572 | ... M25: =L25+M23 -> 119.13677
B26: Discount factor | C26: =(1+Assumptions!$I$15)^(-C$9) -> 1 | D26: =(1+Assumptions!$I$15)^(-D$9) -> 0.8984726 | E26: =(1+Assumptions!$I$15)^(-E$9) -> 0.80725301 | F26: =(1+Assumptions!$I$15)^(-F$9) -> 0.72529471 | G26: =(1+Assumptions!$I$15)^(-G$9) -> 0.65165742 | H26: =(1+Assumptions!$I$15)^(-H$9) -> 0.58549633 | I26: =(1+Assumptions!$I$15)^(-I$9) -> 0.52605241 | J26: =(1+Assumptions!$I$15)^(-J$9) -> 0.47264367 | ... M26: =(1+Assumptions!$I$15)^(-M$9) -> 0.34280595
B27: Bought brand revenue (Minimalist) | C27: =Assumptions!$I$19*(1+Assumptions!$I$16)^C$9 -> 690 | D27: =Assumptions!$I$19*(1+Assumptions!$I$16)^D$9 -> 772.8 | E27: =Assumptions!$I$19*(1+Assumptions!$I$16)^E$9 -> 865.536 | F27: =Assumptions!$I$19*(1+Assumptions!$I$16)^F$9 -> 969.40032 | G27: =Assumptions!$I$19*(1+Assumptions!$I$16)^G$9 -> 1085.7284 | H27: =Assumptions!$I$19*(1+Assumptions!$I$16)^H$9 -> 1216.0158 | I27: =Assumptions!$I$19*(1+Assumptions!$I$16)^I$9 -> 1361.9377 | J27: =Assumptions!$I$19*(1+Assumptions!$I$16)^J$9 -> 1525.3702 | ... M27: =Assumptions!$I$19*(1+Assumptions!$I$16)^M$9 -> 2143.0353
B28: Bought brand EBITDA | C28: =(Assumptions!$D$30+(Assumptions!$I$18-Assumptions!$D$30)*MIN(C$9/Assumptions!$D$33,1))*C27 -> 24.15 | D28: =(Assumptions!$D$30+(Assumptions!$I$18-Assumptions!$D$30)*MIN(D$9/Assumptions!$D$33,1))*D27 -> 52.5504 | E28: =(Assumptions!$D$30+(Assumptions!$I$18-Assumptions!$D$30)*MIN(E$9/Assumptions!$D$33,1))*E27 -> 87.419136 | F28: =(Assumptions!$D$30+(Assumptions!$I$18-Assumptions!$D$30)*MIN(F$9/Assumptions!$D$33,1))*F27 -> 129.89964 | G28: =(Assumptions!$D$30+(Assumptions!$I$18-Assumptions!$D$30)*MIN(G$9/Assumptions!$D$33,1))*G27 -> 181.31664 | H28: =(Assumptions!$D$30+(Assumptions!$I$18-Assumptions!$D$30)*MIN(H$9/Assumptions!$D$33,1))*H27 -> 243.20315 | I28: =(Assumptions!$D$30+(Assumptions!$I$18-Assumptions!$D$30)*MIN(I$9/Assumptions!$D$33,1))*I27 -> 272.38753 | J28: =(Assumptions!$D$30+(Assumptions!$I$18-Assumptions!$D$30)*MIN(J$9/Assumptions!$D$33,1))*J27 -> 305.07403 | ... M28: =(Assumptions!$D$30+(Assumptions!$I$18-Assumptions!$D$30)*MIN(M$9/Assumptions!$D$33,1))*M27 -> 428.60705
B29: EBITDA margin at scale year (start of ramp) | C29: =MAX(Assumptions!$D$30,INDEX(C18:M18,$C$5+1)/INDEX(C10:M10,$C$5+1)) -> 0.035
B31: PV of cash burn to scale (Y0..T) | C31: =SUMPRODUCT($C$24:$M$24,$C$26:$M$26,($C$9:$M$9<=$C$5)*1) -> 139.38926
B32: Peak cumulative burn | C32: =-MIN($C$25:$M$25) -> 190.30161
B33: P(success) | C33: =Assumptions!$I$17 -> 0.11
B34: Risk-adjusted build cost = PV burn / p | C34: =$C$31/$C$33 -> 1267.1751
B35: Forgone profits (bought EBITDA minus build EBITDA after scale, PV Y1-Y10) | C35: =SUMPRODUCT($C$28:$M$28-$C$20:$M$20*($C$9:$M$9>$C$5),$C$26:$M$26,($C$9:$M$9>=1)*1) -> 1063.2233
B36: Y10 revenue gap (bought minus build) | C36: =$M$27-$M$10 -> 1279.7943
B37: Permanent share loss (Y10 gap capitalised, PV) | C37: =$C$36*Assumptions!$I$18/(Assumptions!$I$15-Assumptions!$I$25)*$M$26 -> 1392.7654
B38: Cost of delay = forgone profits + share loss | C38: =$C$35+$C$37 -> 2455.9888
B39: Build-equivalent cost | C39: =$C$34+$C$38 -> 3723.1639
B40: Other buy costs (last 9.5% + transaction + integration - cash acquired) | C40: =Assumptions!$I$21+Assumptions!$I$23+Assumptions!$I$20-Assumptions!$I$22 -> 527
B41: Buy all-in (100%) | C41: =Assumptions!$D$29+$C$40 -> 3233.45
B42: BREAKEVEN headline price for 90.5% | C42: =$C$39-$C$40 -> 3196.1639
B43: Headroom vs ₹2,706 Cr paid | C43: =$C$42-Assumptions!$D$29 -> 489.71389
B44: PV of a failed attempt (Y0..k) | C44: =SUMPRODUCT($C$24:$M$24,$C$26:$M$26,($C$9:$M$9<=$C$7)*1) -> 91.438809
B45: Refined build cost = PV burn + (1/p - 1) x PV failed attempt | C45: =$C$31+(1/$C$33-1)*$C$44 -> 879.21236
B46: Refined breakeven | C46: =$C$45+$C$38-$C$40 -> 2808.2011
B47: Cross-check: bought-brand DCF (100%, EBITDA proxy) | C47: =SUMPRODUCT($C$28:$M$28,$C$26:$M$26,($C$9:$M$9>=1)*1)+$M$28*(1+Assumptions!$I$25)/(Assumptions!$I$15-Assumptions!$I$25)*$M$26 -> 3646.8878
A49: Scenario: Bull
B50: Years to scale T (rounded) | C50: =ROUND(Assumptions!$H$2,0) -> 4
B51: Growth to scale g = (target / Y1 revenue)^(1/(T-1)) | C51: =(Assumptions!$H$26/Assumptions!$H$3)^(1/($C$50-1)) -> 2.1482615
B52: Failed-attempt years (int) | C52: =INT(Assumptions!$H$24) -> 3
B54: Year (Y0 = FY26) | C54: 0 | D54: 1 | E54: 2 | F54: 3 | G54: 4 | H54: 5 | I54: 6 | J54: 7 | K54: 8 | L54: 9 | M54: 10
B55: Revenue (build, if it succeeds) | C55: =IF(C$54=0,0,IF(C$54<=$C$50,Assumptions!$H$3*$C$51^(C$54-1),0)) -> 0 | D55: =IF(D$54=0,0,IF(D$54<=$C$50,Assumptions!$H$3*$C$51^(D$54-1),C55*(1+IF(D$54-$C$50=1,Assumptions!$D$31,IF(D$54-$C$50=2,Assumptions!$D$32,Assumptions!$H$16))))) -> 35 | E55: =IF(E$54=0,0,IF(E$54<=$C$50,Assumptions!$H$3*$C$51^(E$54-1),D55*(1+IF(E$54-$C$50=1,Assumptions!$D$31,IF(E$54-$C$50=2,Assumptions!$D$32,Assumptions!$H$16))))) -> 75.189152 | F55: =IF(F$54=0,0,IF(F$54<=$C$50,Assumptions!$H$3*$C$51^(F$54-1),E55*(1+IF(F$54-$C$50=1,Assumptions!$D$31,IF(F$54-$C$50=2,Assumptions!$D$32,Assumptions!$H$16))))) -> 161.52596 | G55: =IF(G$54=0,0,IF(G$54<=$C$50,Assumptions!$H$3*$C$51^(G$54-1),F55*(1+IF(G$54-$C$50=1,Assumptions!$D$31,IF(G$54-$C$50=2,Assumptions!$D$32,Assumptions!$H$16))))) -> 347 | H55: =IF(H$54=0,0,IF(H$54<=$C$50,Assumptions!$H$3*$C$51^(H$54-1),G55*(1+IF(H$54-$C$50=1,Assumptions!$D$31,IF(H$54-$C$50=2,Assumptions!$D$32,Assumptions!$H$16))))) -> 513.56 | I55: =IF(I$54=0,0,IF(I$54<=$C$50,Assumptions!$H$3*$C$51^(I$54-1),H55*(1+IF(I$54-$C$50=1,Assumptions!$D$31,IF(I$54-$C$50=2,Assumptions!$D$32,Assumptions!$H$16))))) -> 688.1704 | J55: =IF(J$54=0,0,IF(J$54<=$C$50,Assumptions!$H$3*$C$51^(J$54-1),I55*(1+IF(J$54-$C$50=1,Assumptions!$D$31,IF(J$54-$C$50=2,Assumptions!$D$32,Assumptions!$H$16))))) -> 750.10574 | K55: =IF(K$54=0,0,IF(K$54<=$C$50,Assumptions!$H$3*$C$51^(K$54-1),J55*(1+IF(K$54-$C$50=1,Assumptions!$D$31,IF(K$54-$C$50=2,Assumptions!$D$32,Assumptions!$H$16))))) -> 817.61525 | ... M55: =IF(M$54=0,0,IF(M$54<=$C$50,Assumptions!$H$3*$C$51^(M$54-1),L55*(1+IF(M$54-$C$50=1,Assumptions!$D$31,IF(M$54-$C$50=2,Assumptions!$D$32,Assumptions!$H$16))))) -> 971.40868
B56: Gross margin % | C56: =IF(C$54=0,0,IF(C$54<=$C$50,IF(C$54<=2,Assumptions!$H$4,Assumptions!$H$4+(C$54-2)/MAX($C$50-2,1)*(Assumptions!$H$5-Assumptions!$H$4)),Assumptions!$H$5)) -> 0 | D56: =IF(D$54=0,0,IF(D$54<=$C$50,IF(D$54<=2,Assumptions!$H$4,Assumptions!$H$4+(D$54-2)/MAX($C$50-2,1)*(Assumptions!$H$5-Assumptions!$H$4)),Assumptions!$H$5)) -> 0.65 | E56: =IF(E$54=0,0,IF(E$54<=$C$50,IF(E$54<=2,Assumptions!$H$4,Assumptions!$H$4+(E$54-2)/MAX($C$50-2,1)*(Assumptions!$H$5-Assumptions!$H$4)),Assumptions!$H$5)) -> 0.65 | F56: =IF(F$54=0,0,IF(F$54<=$C$50,IF(F$54<=2,Assumptions!$H$4,Assumptions!$H$4+(F$54-2)/MAX($C$50-2,1)*(Assumptions!$H$5-Assumptions!$H$4)),Assumptions!$H$5)) -> 0.69 | G56: =IF(G$54=0,0,IF(G$54<=$C$50,IF(G$54<=2,Assumptions!$H$4,Assumptions!$H$4+(G$54-2)/MAX($C$50-2,1)*(Assumptions!$H$5-Assumptions!$H$4)),Assumptions!$H$5)) -> 0.73 | H56: =IF(H$54=0,0,IF(H$54<=$C$50,IF(H$54<=2,Assumptions!$H$4,Assumptions!$H$4+(H$54-2)/MAX($C$50-2,1)*(Assumptions!$H$5-Assumptions!$H$4)),Assumptions!$H$5)) -> 0.73 | I56: =IF(I$54=0,0,IF(I$54<=$C$50,IF(I$54<=2,Assumptions!$H$4,Assumptions!$H$4+(I$54-2)/MAX($C$50-2,1)*(Assumptions!$H$5-Assumptions!$H$4)),Assumptions!$H$5)) -> 0.73 | J56: =IF(J$54=0,0,IF(J$54<=$C$50,IF(J$54<=2,Assumptions!$H$4,Assumptions!$H$4+(J$54-2)/MAX($C$50-2,1)*(Assumptions!$H$5-Assumptions!$H$4)),Assumptions!$H$5)) -> 0.73 | ... M56: =IF(M$54=0,0,IF(M$54<=$C$50,IF(M$54<=2,Assumptions!$H$4,Assumptions!$H$4+(M$54-2)/MAX($C$50-2,1)*(Assumptions!$H$5-Assumptions!$H$4)),Assumptions!$H$5)) -> 0.73
B57: A&P % of revenue | C57: =IF(C$54=0,0,IF(C$54<=$C$50,IF(C$54<=2,Assumptions!$H$6,Assumptions!$H$7),Assumptions!$H$8)) -> 0 | D57: =IF(D$54=0,0,IF(D$54<=$C$50,IF(D$54<=2,Assumptions!$H$6,Assumptions!$H$7),Assumptions!$H$8)) -> 0.4 | E57: =IF(E$54=0,0,IF(E$54<=$C$50,IF(E$54<=2,Assumptions!$H$6,Assumptions!$H$7),Assumptions!$H$8)) -> 0.4 | F57: =IF(F$54=0,0,IF(F$54<=$C$50,IF(F$54<=2,Assumptions!$H$6,Assumptions!$H$7),Assumptions!$H$8)) -> 0.33 | G57: =IF(G$54=0,0,IF(G$54<=$C$50,IF(G$54<=2,Assumptions!$H$6,Assumptions!$H$7),Assumptions!$H$8)) -> 0.33 | H57: =IF(H$54=0,0,IF(H$54<=$C$50,IF(H$54<=2,Assumptions!$H$6,Assumptions!$H$7),Assumptions!$H$8)) -> 0.25 | I57: =IF(I$54=0,0,IF(I$54<=$C$50,IF(I$54<=2,Assumptions!$H$6,Assumptions!$H$7),Assumptions!$H$8)) -> 0.25 | J57: =IF(J$54=0,0,IF(J$54<=$C$50,IF(J$54<=2,Assumptions!$H$6,Assumptions!$H$7),Assumptions!$H$8)) -> 0.25 | ... M57: =IF(M$54=0,0,IF(M$54<=$C$50,IF(M$54<=2,Assumptions!$H$6,Assumptions!$H$7),Assumptions!$H$8)) -> 0.25
B58: Gross profit | C58: =C56*C55 -> 0 | D58: =D56*D55 -> 22.75 | E58: =E56*E55 -> 48.872949 | F58: =F56*F55 -> 111.45291 | G58: =G56*G55 -> 253.31 | H58: =H56*H55 -> 374.8988 | I58: =I56*I55 -> 502.36439 | J58: =J56*J55 -> 547.57719 | ... M58: =M56*M55 -> 709.12834
B59: Marketing (A&P) | C59: =C57*C55 -> 0 | D59: =D57*D55 -> 14 | E59: =E57*E55 -> 30.075661 | F59: =F57*F55 -> 53.303567 | G59: =G57*G55 -> 114.51 | H59: =H57*H55 -> 128.39 | I59: =I57*I55 -> 172.0426 | J59: =J57*J55 -> 187.52643 | ... M59: =M57*M55 -> 242.85217
B60: R&D | C60: =Assumptions!$H$12+Assumptions!$H$13*C55 -> 3 | D60: =Assumptions!$H$12+Assumptions!$H$13*D55 -> 3.35 | E60: =Assumptions!$H$12+Assumptions!$H$13*E55 -> 3.7518915 | F60: =Assumptions!$H$12+Assumptions!$H$13*F55 -> 4.6152596 | G60: =Assumptions!$H$12+Assumptions!$H$13*G55 -> 6.47 | H60: =Assumptions!$H$12+Assumptions!$H$13*H55 -> 8.1356 | I60: =Assumptions!$H$12+Assumptions!$H$13*I55 -> 9.881704 | J60: =Assumptions!$H$12+Assumptions!$H$13*J55 -> 10.501057 | ... M60: =Assumptions!$H$12+Assumptions!$H$13*M55 -> 12.714087
B61: Org cost | C61: =IF(C$54=0,0.5*Assumptions!$H$10,MAX(Assumptions!$H$10,Assumptions!$H$11*C55)) -> 6 | D61: =IF(D$54=0,0.5*Assumptions!$H$10,MAX(Assumptions!$H$10,Assumptions!$H$11*D55)) -> 12 | E61: =IF(E$54=0,0.5*Assumptions!$H$10,MAX(Assumptions!$H$10,Assumptions!$H$11*E55)) -> 12 | F61: =IF(F$54=0,0.5*Assumptions!$H$10,MAX(Assumptions!$H$10,Assumptions!$H$11*F55)) -> 12 | G61: =IF(G$54=0,0.5*Assumptions!$H$10,MAX(Assumptions!$H$10,Assumptions!$H$11*G55)) -> 20.82 | H61: =IF(H$54=0,0.5*Assumptions!$H$10,MAX(Assumptions!$H$10,Assumptions!$H$11*H55)) -> 30.8136 | I61: =IF(I$54=0,0.5*Assumptions!$H$10,MAX(Assumptions!$H$10,Assumptions!$H$11*I55)) -> 41.290224 | J61: =IF(J$54=0,0.5*Assumptions!$H$10,MAX(Assumptions!$H$10,Assumptions!$H$11*J55)) -> 45.006344 | ... M61: =IF(M$54=0,0.5*Assumptions!$H$10,MAX(Assumptions!$H$10,Assumptions!$H$11*M55)) -> 58.284521
B62: Distribution & overheads (pre-scale rule) | C62: =IF(C$54=0,0,Assumptions!$H$9*C55) -> 0 | D62: =IF(D$54=0,0,Assumptions!$H$9*D55) -> 7 | E62: =IF(E$54=0,0,Assumptions!$H$9*E55) -> 15.03783 | F62: =IF(F$54=0,0,Assumptions!$H$9*F55) -> 32.305192 | G62: =IF(G$54=0,0,Assumptions!$H$9*G55) -> 69.4 | H62: =IF(H$54=0,0,Assumptions!$H$9*H55) -> 102.712 | I62: =IF(I$54=0,0,Assumptions!$H$9*I55) -> 137.63408 | J62: =IF(J$54=0,0,Assumptions!$H$9*J55) -> 150.02115 | ... M62: =IF(M$54=0,0,Assumptions!$H$9*M55) -> 194.28174
B63: EBITDA (pre-scale rule) | C63: =C58-C59-C62-C61-C60 -> -9 | D63: =D58-D59-D62-D61-D60 -> -13.6 | E63: =E58-E59-E62-E61-E60 -> -11.992434 | F63: =F58-F59-F62-F61-F60 -> 9.228894 | G63: =G58-G59-G62-G61-G60 -> 42.11 | H63: =H58-H59-H62-H61-H60 -> 104.8476 | I63: =I58-I59-I62-I61-I60 -> 141.51578 | J63: =J58-J59-J62-J61-J60 -> 154.5222 | ... M63: =M58-M59-M62-M61-M60 -> 200.99582
B64: Distribution & overheads (plug after scale) | C64: =IF(C$54<=$C$50,C62,C58-C59-C61-C60-C65) -> 0 | D64: =IF(D$54<=$C$50,D62,D58-D59-D61-D60-D65) -> 7 | E64: =IF(E$54<=$C$50,E62,E58-E59-E61-E60-E65) -> 15.03783 | F64: =IF(F$54<=$C$50,F62,F58-F59-F61-F60-F65) -> 32.305192 | G64: =IF(G$54<=$C$50,G62,G58-G59-G61-G60-G65) -> 69.4 | H64: =IF(H$54<=$C$50,H62,H58-H59-H61-H60-H65) -> 142.29456 | I64: =IF(I$54<=$C$50,I62,I58-I59-I61-I60-I65) -> 187.75211 | J64: =IF(J$54<=$C$50,J62,J58-J59-J61-J60-J65) -> 200.62236 | ... M64: =IF(M$54<=$C$50,M62,M58-M59-M61-M60-M65) -> 249.56626
B65: EBITDA | C65: =IF(C$54<=$C$50,C63,($C$74+(Assumptions!$H$18-$C$74)*MIN(MAX(C$54-$C$50,0)/Assumptions!$D$33,1))*C55) -> -9 | D65: =IF(D$54<=$C$50,D63,($C$74+(Assumptions!$H$18-$C$74)*MIN(MAX(D$54-$C$50,0)/Assumptions!$D$33,1))*D55) -> -13.6 | E65: =IF(E$54<=$C$50,E63,($C$74+(Assumptions!$H$18-$C$74)*MIN(MAX(E$54-$C$50,0)/Assumptions!$D$33,1))*E55) -> -11.992434 | F65: =IF(F$54<=$C$50,F63,($C$74+(Assumptions!$H$18-$C$74)*MIN(MAX(F$54-$C$50,0)/Assumptions!$D$33,1))*F55) -> 9.228894 | G65: =IF(G$54<=$C$50,G63,($C$74+(Assumptions!$H$18-$C$74)*MIN(MAX(G$54-$C$50,0)/Assumptions!$D$33,1))*G55) -> 42.11 | H65: =IF(H$54<=$C$50,H63,($C$74+(Assumptions!$H$18-$C$74)*MIN(MAX(H$54-$C$50,0)/Assumptions!$D$33,1))*H55) -> 65.26504 | I65: =IF(I$54<=$C$50,I63,($C$74+(Assumptions!$H$18-$C$74)*MIN(MAX(I$54-$C$50,0)/Assumptions!$D$33,1))*I55) -> 91.397755 | J65: =IF(J$54<=$C$50,J63,($C$74+(Assumptions!$H$18-$C$74)*MIN(MAX(J$54-$C$50,0)/Assumptions!$D$33,1))*J55) -> 103.92099 | ... M65: =IF(M$54<=$C$50,M63,($C$74+(Assumptions!$H$18-$C$74)*MIN(MAX(M$54-$C$50,0)/Assumptions!$D$33,1))*M55) -> 145.7113
B66: Net working capital | C66: =Assumptions!$H$14/365*C55 -> 0 | D66: =Assumptions!$H$14/365*D55 -> -1.2465753 | E66: =Assumptions!$H$14/365*E55 -> -2.6779698 | F66: =Assumptions!$H$14/365*F55 -> -5.7529794 | G66: =Assumptions!$H$14/365*G55 -> -12.358904 | H66: =Assumptions!$H$14/365*H55 -> -18.291178 | I66: =Assumptions!$H$14/365*I55 -> -24.510179 | J66: =Assumptions!$H$14/365*J55 -> -26.716095 | ... M66: =Assumptions!$H$14/365*M55 -> -34.598117
B67: Working-capital investment | C67: =C66 -> 0 | D67: =D66-C66 -> -1.2465753 | E67: =E66-D66 -> -1.4313945 | F67: =F66-E66 -> -3.0750096 | G67: =G66-F66 -> -6.6059247 | H67: =H66-G66 -> -5.932274 | I67: =I66-H66 -> -6.2190005 | J67: =J66-I66 -> -2.2059161 | K67: =K66-J66 -> -2.4044485 | ... M67: =M66-L66 -> -2.8567253
B68: Free cash flow | C68: =C65-C67 -> -9 | D68: =D65-D67 -> -12.353425 | E68: =E65-E67 -> -10.561039 | F68: =F65-F67 -> 12.303904 | G68: =G65-G67 -> 48.715925 | H68: =H65-H67 -> 71.197314 | I68: =I65-I67 -> 97.616756 | J68: =J65-J67 -> 106.1269 | ... M68: =M65-M67 -> 148.56803
B69: Cash burn | C69: =MAX(-C68,0) -> 9 | D69: =MAX(-D68,0) -> 12.353425 | E69: =MAX(-E68,0) -> 10.561039 | F69: =MAX(-F68,0) -> 0 | G69: =MAX(-G68,0) -> 0 | H69: =MAX(-H68,0) -> 0 | I69: =MAX(-I68,0) -> 0 | J69: =MAX(-J68,0) -> 0 | ... M69: =MAX(-M68,0) -> 0
B70: Cumulative cash | C70: =C68 -> -9 | D70: =C70+D68 -> -21.353425 | E70: =D70+E68 -> -31.914464 | F70: =E70+F68 -> -19.61056 | G70: =F70+G68 -> 29.105364 | H70: =G70+H68 -> 100.30268 | I70: =H70+I68 -> 197.91943 | J70: =I70+J68 -> 304.04634 | K70: =J70+K68 -> 424.40887 | ... M70: =L70+M68 -> 709.27784
B71: Discount factor | C71: =(1+Assumptions!$H$15)^(-C$54) -> 1 | D71: =(1+Assumptions!$H$15)^(-D$54) -> 0.8984726 | E71: =(1+Assumptions!$H$15)^(-E$54) -> 0.80725301 | F71: =(1+Assumptions!$H$15)^(-F$54) -> 0.72529471 | G71: =(1+Assumptions!$H$15)^(-G$54) -> 0.65165742 | H71: =(1+Assumptions!$H$15)^(-H$54) -> 0.58549633 | I71: =(1+Assumptions!$H$15)^(-I$54) -> 0.52605241 | J71: =(1+Assumptions!$H$15)^(-J$54) -> 0.47264367 | ... M71: =(1+Assumptions!$H$15)^(-M$54) -> 0.34280595
B72: Bought brand revenue (Minimalist) | C72: =Assumptions!$H$19*(1+Assumptions!$H$16)^C$54 -> 652 | D72: =Assumptions!$H$19*(1+Assumptions!$H$16)^D$54 -> 710.68 | E72: =Assumptions!$H$19*(1+Assumptions!$H$16)^E$54 -> 774.6412 | F72: =Assumptions!$H$19*(1+Assumptions!$H$16)^F$54 -> 844.35891 | G72: =Assumptions!$H$19*(1+Assumptions!$H$16)^G$54 -> 920.35121 | H72: =Assumptions!$H$19*(1+Assumptions!$H$16)^H$54 -> 1003.1828 | I72: =Assumptions!$H$19*(1+Assumptions!$H$16)^I$54 -> 1093.4693 | J72: =Assumptions!$H$19*(1+Assumptions!$H$16)^J$54 -> 1191.8815 | ... M72: =Assumptions!$H$19*(1+Assumptions!$H$16)^M$54 -> 1543.5211
B73: Bought brand EBITDA | C73: =(Assumptions!$D$30+(Assumptions!$H$18-Assumptions!$D$30)*MIN(C$54/Assumptions!$D$33,1))*C72 -> 22.82 | D73: =(Assumptions!$D$30+(Assumptions!$H$18-Assumptions!$D$30)*MIN(D$54/Assumptions!$D$33,1))*D72 -> 41.21944 | E73: =(Assumptions!$D$30+(Assumptions!$H$18-Assumptions!$D$30)*MIN(E$54/Assumptions!$D$33,1))*E72 -> 62.745937 | F73: =(Assumptions!$D$30+(Assumptions!$H$18-Assumptions!$D$30)*MIN(F$54/Assumptions!$D$33,1))*F72 -> 87.813326 | G73: =(Assumptions!$D$30+(Assumptions!$H$18-Assumptions!$D$30)*MIN(G$54/Assumptions!$D$33,1))*G72 -> 116.8846 | H73: =(Assumptions!$D$30+(Assumptions!$H$18-Assumptions!$D$30)*MIN(H$54/Assumptions!$D$33,1))*H72 -> 150.47742 | I73: =(Assumptions!$D$30+(Assumptions!$H$18-Assumptions!$D$30)*MIN(I$54/Assumptions!$D$33,1))*I72 -> 164.02039 | J73: =(Assumptions!$D$30+(Assumptions!$H$18-Assumptions!$D$30)*MIN(J$54/Assumptions!$D$33,1))*J72 -> 178.78223 | ... M73: =(Assumptions!$D$30+(Assumptions!$H$18-Assumptions!$D$30)*MIN(M$54/Assumptions!$D$33,1))*M72 -> 231.52817
B74: EBITDA margin at scale year (start of ramp) | C74: =MAX(Assumptions!$D$30,INDEX(C63:M63,$C$50+1)/INDEX(C55:M55,$C$50+1)) -> 0.12135447
B76: PV of cash burn to scale (Y0..T) | C76: =SUMPRODUCT($C$69:$M$69,$C$71:$M$71,($C$54:$M$54<=$C$50)*1) -> 28.624644
B77: Peak cumulative burn | C77: =-MIN($C$70:$M$70) -> 31.914464
B78: P(success) | C78: =Assumptions!$H$17 -> 0.29
B79: Risk-adjusted build cost = PV burn / p | C79: =$C$76/$C$78 -> 98.70567
B80: Forgone profits (bought EBITDA minus build EBITDA after scale, PV Y1-Y10) | C80: =SUMPRODUCT($C$73:$M$73-$C$65:$M$65*($C$54:$M$54>$C$50),$C$71:$M$71,($C$54:$M$54>=1)*1) -> 443.14334
B81: Y10 revenue gap (bought minus build) | C81: =$M$72-$M$55 -> 572.11243
B82: Permanent share loss (Y10 gap capitalised, PV) | C82: =$C$81*Assumptions!$H$18/(Assumptions!$H$15-Assumptions!$H$25)*$M$71 -> 466.96083
B83: Cost of delay = forgone profits + share loss | C83: =$C$80+$C$82 -> 910.10417
B84: Build-equivalent cost | C84: =$C$79+$C$83 -> 1008.8098
B85: Other buy costs (last 9.5% + transaction + integration - cash acquired) | C85: =Assumptions!$H$21+Assumptions!$H$23+Assumptions!$H$20-Assumptions!$H$22 -> 726
B86: Buy all-in (100%) | C86: =Assumptions!$D$29+$C$85 -> 3432.45
B87: BREAKEVEN headline price for 90.5% | C87: =$C$84-$C$85 -> 282.80984
B88: Headroom vs ₹2,706 Cr paid | C88: =$C$87-Assumptions!$D$29 -> -2423.6402
B89: PV of a failed attempt (Y0..k) | C89: =SUMPRODUCT($C$69:$M$69,$C$71:$M$71,($C$54:$M$54<=$C$52)*1) -> 28.624644
B90: Refined build cost = PV burn + (1/p - 1) x PV failed attempt | C90: =$C$76+(1/$C$78-1)*$C$89 -> 98.70567
B91: Refined breakeven | C91: =$C$90+$C$83-$C$85 -> 282.80984
B92: Cross-check: bought-brand DCF (100%, EBITDA proxy) | C92: =SUMPRODUCT($C$73:$M$73,$C$71:$M$71,($C$54:$M$54>=1)*1)+$M$73*(1+Assumptions!$H$25)/(Assumptions!$H$15-Assumptions!$H$25)*$M$71 -> 2052.4211
A94: Scenario: Bear
B95: Years to scale T (rounded) | C95: =ROUND(Assumptions!$J$2,0) -> 8
B96: Growth to scale g = (target / Y1 revenue)^(1/(T-1)) | C96: =(Assumptions!$J$26/Assumptions!$J$3)^(1/($C$95-1)) -> 1.5663585
B97: Failed-attempt years (int) | C97: =INT(Assumptions!$J$24) -> 3
B99: Year (Y0 = FY26) | C99: 0 | D99: 1 | E99: 2 | F99: 3 | G99: 4 | H99: 5 | I99: 6 | J99: 7 | K99: 8 | L99: 9 | M99: 10
B100: Revenue (build, if it succeeds) | C100: =IF(C$99=0,0,IF(C$99<=$C$95,Assumptions!$J$3*$C$96^(C$99-1),0)) -> 0 | D100: =IF(D$99=0,0,IF(D$99<=$C$95,Assumptions!$J$3*$C$96^(D$99-1),C100*(1+IF(D$99-$C$95=1,Assumptions!$D$31,IF(D$99-$C$95=2,Assumptions!$D$32,Assumptions!$J$16))))) -> 15 | E100: =IF(E$99=0,0,IF(E$99<=$C$95,Assumptions!$J$3*$C$96^(E$99-1),D100*(1+IF(E$99-$C$95=1,Assumptions!$D$31,IF(E$99-$C$95=2,Assumptions!$D$32,Assumptions!$J$16))))) -> 23.495378 | F100: =IF(F$99=0,0,IF(F$99<=$C$95,Assumptions!$J$3*$C$96^(F$99-1),E100*(1+IF(F$99-$C$95=1,Assumptions!$D$31,IF(F$99-$C$95=2,Assumptions!$D$32,Assumptions!$J$16))))) -> 36.802185 | G100: =IF(G$99=0,0,IF(G$99<=$C$95,Assumptions!$J$3*$C$96^(G$99-1),F100*(1+IF(G$99-$C$95=1,Assumptions!$D$31,IF(G$99-$C$95=2,Assumptions!$D$32,Assumptions!$J$16))))) -> 57.645416 | H100: =IF(H$99=0,0,IF(H$99<=$C$95,Assumptions!$J$3*$C$96^(H$99-1),G100*(1+IF(H$99-$C$95=1,Assumptions!$D$31,IF(H$99-$C$95=2,Assumptions!$D$32,Assumptions!$J$16))))) -> 90.293389 | I100: =IF(I$99=0,0,IF(I$99<=$C$95,Assumptions!$J$3*$C$96^(I$99-1),H100*(1+IF(I$99-$C$95=1,Assumptions!$D$31,IF(I$99-$C$95=2,Assumptions!$D$32,Assumptions!$J$16))))) -> 141.43182 | J100: =IF(J$99=0,0,IF(J$99<=$C$95,Assumptions!$J$3*$C$96^(J$99-1),I100*(1+IF(J$99-$C$95=1,Assumptions!$D$31,IF(J$99-$C$95=2,Assumptions!$D$32,Assumptions!$J$16))))) -> 221.53293 | K100: =IF(K$99=0,0,IF(K$99<=$C$95,Assumptions!$J$3*$C$96^(K$99-1),J100*(1+IF(K$99-$C$95=1,Assumptions!$D$31,IF(K$99-$C$95=2,Assumptions!$D$32,Assumptions!$J$16))))) -> 347 | ... M100: =IF(M$99=0,0,IF(M$99<=$C$95,Assumptions!$J$3*$C$96^(M$99-1),L100*(1+IF(M$99-$C$95=1,Assumptions!$D$31,IF(M$99-$C$95=2,Assumptions!$D$32,Assumptions!$J$16))))) -> 688.1704
B101: Gross margin % | C101: =IF(C$99=0,0,IF(C$99<=$C$95,IF(C$99<=2,Assumptions!$J$4,Assumptions!$J$4+(C$99-2)/MAX($C$95-2,1)*(Assumptions!$J$5-Assumptions!$J$4)),Assumptions!$J$5)) -> 0 | D101: =IF(D$99=0,0,IF(D$99<=$C$95,IF(D$99<=2,Assumptions!$J$4,Assumptions!$J$4+(D$99-2)/MAX($C$95-2,1)*(Assumptions!$J$5-Assumptions!$J$4)),Assumptions!$J$5)) -> 0.55 | E101: =IF(E$99=0,0,IF(E$99<=$C$95,IF(E$99<=2,Assumptions!$J$4,Assumptions!$J$4+(E$99-2)/MAX($C$95-2,1)*(Assumptions!$J$5-Assumptions!$J$4)),Assumptions!$J$5)) -> 0.55 | F101: =IF(F$99=0,0,IF(F$99<=$C$95,IF(F$99<=2,Assumptions!$J$4,Assumptions!$J$4+(F$99-2)/MAX($C$95-2,1)*(Assumptions!$J$5-Assumptions!$J$4)),Assumptions!$J$5)) -> 0.56166667 | G101: =IF(G$99=0,0,IF(G$99<=$C$95,IF(G$99<=2,Assumptions!$J$4,Assumptions!$J$4+(G$99-2)/MAX($C$95-2,1)*(Assumptions!$J$5-Assumptions!$J$4)),Assumptions!$J$5)) -> 0.57333333 | H101: =IF(H$99=0,0,IF(H$99<=$C$95,IF(H$99<=2,Assumptions!$J$4,Assumptions!$J$4+(H$99-2)/MAX($C$95-2,1)*(Assumptions!$J$5-Assumptions!$J$4)),Assumptions!$J$5)) -> 0.585 | I101: =IF(I$99=0,0,IF(I$99<=$C$95,IF(I$99<=2,Assumptions!$J$4,Assumptions!$J$4+(I$99-2)/MAX($C$95-2,1)*(Assumptions!$J$5-Assumptions!$J$4)),Assumptions!$J$5)) -> 0.59666667 | J101: =IF(J$99=0,0,IF(J$99<=$C$95,IF(J$99<=2,Assumptions!$J$4,Assumptions!$J$4+(J$99-2)/MAX($C$95-2,1)*(Assumptions!$J$5-Assumptions!$J$4)),Assumptions!$J$5)) -> 0.60833333 | ... M101: =IF(M$99=0,0,IF(M$99<=$C$95,IF(M$99<=2,Assumptions!$J$4,Assumptions!$J$4+(M$99-2)/MAX($C$95-2,1)*(Assumptions!$J$5-Assumptions!$J$4)),Assumptions!$J$5)) -> 0.62
B102: A&P % of revenue | C102: =IF(C$99=0,0,IF(C$99<=$C$95,IF(C$99<=2,Assumptions!$J$6,Assumptions!$J$7),Assumptions!$J$8)) -> 0 | D102: =IF(D$99=0,0,IF(D$99<=$C$95,IF(D$99<=2,Assumptions!$J$6,Assumptions!$J$7),Assumptions!$J$8)) -> 0.6 | E102: =IF(E$99=0,0,IF(E$99<=$C$95,IF(E$99<=2,Assumptions!$J$6,Assumptions!$J$7),Assumptions!$J$8)) -> 0.6 | F102: =IF(F$99=0,0,IF(F$99<=$C$95,IF(F$99<=2,Assumptions!$J$6,Assumptions!$J$7),Assumptions!$J$8)) -> 0.45 | G102: =IF(G$99=0,0,IF(G$99<=$C$95,IF(G$99<=2,Assumptions!$J$6,Assumptions!$J$7),Assumptions!$J$8)) -> 0.45 | H102: =IF(H$99=0,0,IF(H$99<=$C$95,IF(H$99<=2,Assumptions!$J$6,Assumptions!$J$7),Assumptions!$J$8)) -> 0.45 | I102: =IF(I$99=0,0,IF(I$99<=$C$95,IF(I$99<=2,Assumptions!$J$6,Assumptions!$J$7),Assumptions!$J$8)) -> 0.45 | J102: =IF(J$99=0,0,IF(J$99<=$C$95,IF(J$99<=2,Assumptions!$J$6,Assumptions!$J$7),Assumptions!$J$8)) -> 0.45 | ... M102: =IF(M$99=0,0,IF(M$99<=$C$95,IF(M$99<=2,Assumptions!$J$6,Assumptions!$J$7),Assumptions!$J$8)) -> 0.34
B103: Gross profit | C103: =C101*C100 -> 0 | D103: =D101*D100 -> 8.25 | E103: =E101*E100 -> 12.922458 | F103: =F101*F100 -> 20.670561 | G103: =G101*G100 -> 33.050039 | H103: =H101*H100 -> 52.821633 | I103: =I101*I100 -> 84.387652 | J103: =J101*J100 -> 134.76587 | ... M103: =M101*M100 -> 426.66565
B104: Marketing (A&P) | C104: =C102*C100 -> 0 | D104: =D102*D100 -> 9 | E104: =E102*E100 -> 14.097227 | F104: =F102*F100 -> 16.560983 | G104: =G102*G100 -> 25.940437 | H104: =H102*H100 -> 40.632025 | I104: =I102*I100 -> 63.644319 | J104: =J102*J100 -> 99.689821 | ... M104: =M102*M100 -> 233.97794
B105: R&D | C105: =Assumptions!$J$12+Assumptions!$J$13*C100 -> 8 | D105: =Assumptions!$J$12+Assumptions!$J$13*D100 -> 8.45 | E105: =Assumptions!$J$12+Assumptions!$J$13*E100 -> 8.7048613 | F105: =Assumptions!$J$12+Assumptions!$J$13*F100 -> 9.1040656 | G105: =Assumptions!$J$12+Assumptions!$J$13*G100 -> 9.7293625 | H105: =Assumptions!$J$12+Assumptions!$J$13*H100 -> 10.708802 | I105: =Assumptions!$J$12+Assumptions!$J$13*I100 -> 12.242955 | J105: =Assumptions!$J$12+Assumptions!$J$13*J100 -> 14.645988 | ... M105: =Assumptions!$J$12+Assumptions!$J$13*M100 -> 28.645112
B106: Org cost | C106: =IF(C$99=0,0.5*Assumptions!$J$10,MAX(Assumptions!$J$10,Assumptions!$J$11*C100)) -> 15 | D106: =IF(D$99=0,0.5*Assumptions!$J$10,MAX(Assumptions!$J$10,Assumptions!$J$11*D100)) -> 30 | E106: =IF(E$99=0,0.5*Assumptions!$J$10,MAX(Assumptions!$J$10,Assumptions!$J$11*E100)) -> 30 | F106: =IF(F$99=0,0.5*Assumptions!$J$10,MAX(Assumptions!$J$10,Assumptions!$J$11*F100)) -> 30 | G106: =IF(G$99=0,0.5*Assumptions!$J$10,MAX(Assumptions!$J$10,Assumptions!$J$11*G100)) -> 30 | H106: =IF(H$99=0,0.5*Assumptions!$J$10,MAX(Assumptions!$J$10,Assumptions!$J$11*H100)) -> 30 | I106: =IF(I$99=0,0.5*Assumptions!$J$10,MAX(Assumptions!$J$10,Assumptions!$J$11*I100)) -> 30 | J106: =IF(J$99=0,0.5*Assumptions!$J$10,MAX(Assumptions!$J$10,Assumptions!$J$11*J100)) -> 30 | ... M106: =IF(M$99=0,0.5*Assumptions!$J$10,MAX(Assumptions!$J$10,Assumptions!$J$11*M100)) -> 61.935336
B107: Distribution & overheads (pre-scale rule) | C107: =IF(C$99=0,0,Assumptions!$J$9*C100) -> 0 | D107: =IF(D$99=0,0,Assumptions!$J$9*D100) -> 4.8 | E107: =IF(E$99=0,0,Assumptions!$J$9*E100) -> 7.5185209 | F107: =IF(F$99=0,0,Assumptions!$J$9*F100) -> 11.776699 | G107: =IF(G$99=0,0,Assumptions!$J$9*G100) -> 18.446533 | H107: =IF(H$99=0,0,Assumptions!$J$9*H100) -> 28.893884 | I107: =IF(I$99=0,0,Assumptions!$J$9*I100) -> 45.258182 | J107: =IF(J$99=0,0,Assumptions!$J$9*J100) -> 70.890539 | ... M107: =IF(M$99=0,0,Assumptions!$J$9*M100) -> 220.21453
B108: EBITDA (pre-scale rule) | C108: =C103-C104-C107-C106-C105 -> -23 | D108: =D103-D104-D107-D106-D105 -> -44 | E108: =E103-E104-E107-E106-E105 -> -47.398151 | F108: =F103-F104-F107-F106-F105 -> -46.771187 | G108: =G103-G104-G107-G106-G105 -> -51.066294 | H108: =H103-H104-H107-H106-H105 -> -57.413079 | I108: =I103-I104-I107-I106-I105 -> -66.757803 | J108: =J103-J104-J107-J106-J105 -> -80.460479 | ... M108: =M103-M104-M107-M106-M105 -> -118.10726
...

Sheet Sensitivity
A1: Sensitivity: breakeven headline price for 90.5% (₹ Cr)
A3: Key outputs (live, from Build_Model) | P3: Static outputs from scripts/build_model.py (not live)
B4: Base | C4: Bull | D4: Bear | P4: Tornado: breakeven with one driver at low / high
A5: Years from decision to ₹347 Cr | B5: =Build_Model!$C$5+1 -> 7 | C5: =Build_Model!$C$50+1 -> 5 | D5: =Build_Model!$C$95+1 -> 9 | P5: driver | Q5: at low | R5: at high | S5: swing
A6: PV of cash burn to scale | B6: =Build_Model!$C$31 -> 139.38926 | C6: =Build_Model!$C$76 -> 28.624644 | D6: =Build_Model!$C$121 -> 361.01857 | P6: category_growth | Q6: 2510.9 | R6: 6037.5 | S6: 3526.5
A7: P(success) | B7: =Build_Model!$C$33 -> 0.11 | C7: =Build_Model!$C$78 -> 0.29 | D7: =Build_Model!$C$123 -> 0.05 | P7: p_success | Q7: 4716.8 | R7: 2409.6 | S7: 2307.1
A8: Risk-adjusted build cost (PV burn ÷ p) | B8: =Build_Model!$C$34 -> 1267.1751 | C8: =Build_Model!$C$79 -> 98.70567 | D8: =Build_Model!$C$124 -> 7220.3714 | P8: steady_ebitda_margin | Q8: 2589.6 | R8: 4433.5 | S8: 1843.9
A9: Cost of delay | B9: =Build_Model!$C$38 -> 2455.9888 | C9: =Build_Model!$C$83 -> 910.10417 | D9: =Build_Model!$C$128 -> 8635.9298 | P9: discount_rate | Q9: 3829.7 | R9: 2604.9 | S9: 1224.8
A10: Build-equivalent cost | B10: =Build_Model!$C$39 -> 3723.1639 | C10: =Build_Model!$C$84 -> 1008.8098 | D10: =Build_Model!$C$129 -> 15856.301 | P10: years_to_scale | Q10: 2571.6 | R10: 3660.1 | S10: 1088.5
A11: Buy all-in (100%) | B11: =Build_Model!$C$41 -> 3233.45 | C11: =Build_Model!$C$86 -> 3432.45 | D11: =Build_Model!$C$131 -> 2961.45 | P11: org_cost_floor | Q11: 2911 | R11: 3594.1 | S11: 683.1
A12: Breakeven price for 90.5% | B12: =Build_Model!$C$42 -> 3196.1639 | C12: =Build_Model!$C$87 -> 282.80984 | D12: =Build_Model!$C$132 -> 15601.301 | P12: var_opex_pct | Q12: 2973.4 | R12: 3508 | S12: 534.6
A13: Headroom vs price paid | B13: =Build_Model!$C$43 -> 489.71389 | C13: =Build_Model!$C$88 -> -2423.6402 | D13: =Build_Model!$C$133 -> 12894.851 | P13: wc_days | Q13: 2967.2 | R13: 3499.6 | S13: 532.4
A14: Price paid at completion (90.5%) | B14: =Assumptions!$D$29 -> 2706.45 | P14: ap_pct_growth | Q14: 2999.1 | R14: 3472 | S14: 472.9
P15: remaining_stake_cost | Q15: 3413.2 | R15: 3047.2 | S15: 366
A16: Grid: P(success) (rows) x years from launch to ₹347 Cr (columns); other drivers at base. Red = breakeven above the price paid, i.e. buying was cheaper. | P16: gross_margin_scale | Q16: 3432.6 | R16: 3107.5 | S16: 325
A17: P(success) \ years | B17: 3 | C17: 4 | D17: 5 | E17: 6 | F17: 7 | G17: 8 | H17: 9 | P17: rnd_floor | Q17: 3101.7 | R17: 3337.8 | S17: 236.1
A18: 0.05 | B18: =$C$54/$A18+$C$61-$C$63 -> 3362.8648 | C18: =$C$99/$A18+$C$106-$C$108 -> 3845.8226 | D18: =$C$144/$A18+$C$151-$C$153 -> 4303.5323 | E18: =$C$189/$A18+$C$196-$C$198 -> 4716.774 | F18: =$C$234/$A18+$C$241-$C$243 -> 5077.3208 | G18: =$C$279/$A18+$C$286-$C$288 -> 5391.5253 | H18: =$C$324/$A18+$C$331-$C$333 -> 5775.3813 | P18: acquired_rev_y0 | Q18: 3001.7 | R18: 3196.2 | S18: 194.4
A19: 0.08 | B19: =$C$54/$A19+$C$61-$C$63 -> 2570.3957 | C19: =$C$99/$A19+$C$106-$C$108 -> 2969.8061 | D19: =$C$144/$A19+$C$151-$C$153 -> 3340.2318 | E19: =$C$189/$A19+$C$196-$C$198 -> 3671.3546 | F19: =$C$234/$A19+$C$241-$C$243 -> 3956.2264 | G19: =$C$279/$A19+$C$286-$C$288 -> 4201.1567 | H19: =$C$324/$A19+$C$331-$C$333 -> 4521.768 | P19: gross_margin_early | Q19: 3271.2 | R19: 3121.1 | S19: 150
A20: 0.11 | B20: =$C$54/$A20+$C$61-$C$63 -> 2210.1824 | C20: =$C$99/$A20+$C$106-$C$108 -> 2571.6168 | D20: =$C$144/$A20+$C$151-$C$153 -> 2902.368 | E20: =$C$189/$A20+$C$196-$C$198 -> 3196.1639 | F20: =$C$234/$A20+$C$241-$C$243 -> 3446.6381 | G20: =$C$279/$A20+$C$286-$C$288 -> 3660.0801 | H20: =$C$324/$A20+$C$331-$C$333 -> 3951.9438 | P20: ap_pct_launch | Q20: 3144.7 | R20: 3247.6 | S20: 102.9
A21: 0.15 | B21: =$C$54/$A21+$C$61-$C$63 -> 1954.0308 | C21: =$C$99/$A21+$C$106-$C$108 -> 2288.46 | D21: =$C$144/$A21+$C$151-$C$153 -> 2590.9981 | E21: =$C$189/$A21+$C$196-$C$198 -> 2858.2505 | F21: =$C$234/$A21+$C$241-$C$243 -> 3084.2641 | G21: =$C$279/$A21+$C$286-$C$288 -> 3275.3145 | H21: =$C$324/$A21+$C$331-$C$333 -> 3546.7354 | P21: rnd_pct | Q21: 3151.6 | R21: 3240.7 | S21: 89.1
A22: 0.2 | B22: =$C$54/$A22+$C$61-$C$63 -> 1777.9266 | C22: =$C$99/$A22+$C$106-$C$108 -> 2093.7896 | D22: =$C$144/$A22+$C$151-$C$153 -> 2376.9314 | E22: =$C$189/$A22+$C$196-$C$198 -> 2625.9351 | F22: =$C$234/$A22+$C$241-$C$243 -> 2835.1321 | G22: =$C$279/$A22+$C$286-$C$288 -> 3010.7882 | H22: =$C$324/$A22+$C$331-$C$333 -> 3268.1547 | P22: integration_cost | Q22: 3221.2 | R22: 3146.2 | S22: 75
A23: 0.29 | B23: =$C$54/$A23+$C$61-$C$63 -> 1613.9674 | C23: =$C$99/$A23+$C$106-$C$108 -> 1912.5448 | D23: =$C$144/$A23+$C$151-$C$153 -> 2177.6278 | E23: =$C$189/$A23+$C$196-$C$198 -> 2409.6414 | F23: =$C$234/$A23+$C$241-$C$243 -> 2603.1815 | G23: =$C$279/$A23+$C$286-$C$288 -> 2764.505 | H23: =$C$324/$A23+$C$331-$C$333 -> 3008.7864 | P23: y1_revenue | Q23: 3159.5 | R23: 3231 | S23: 71.4
P24: org_cost_pct | Q24: 3171.3 | R24: 3221.1 | S24: 49.8
P25: cash_acquired | Q25: 3196.2 | R25: 3226.2 | S25: 30
A26: Calculation blocks for the grid (base drivers, years-to-scale overridden by the column header above) | P26: ap_pct_scale | Q26: 3196.2 | R26: 3196.2 | S26: 0
A27: Grid block: years to scale = column B header
B28: Years to scale T (rounded) | C28: =ROUND(Sensitivity!$B$17,0) -> 3 | P28: Monte Carlo (10,000 triangular draws, seed 42)
B29: Growth to scale g = (target / Y1 revenue)^(1/(T-1)) | C29: =(Assumptions!$I$26/Assumptions!$I$3)^(1/($C$28-1)) -> 3.7255872 | P29: breakeven_P10 | Q29: 2484.2859
B30: Failed-attempt years (int) | C30: =INT(Assumptions!$I$24) -> 3 | P30: breakeven_P50 | Q30: 3597.6649
P31: breakeven_P90 | Q31: 5218.0735
B32: Year (Y0 = FY26) | C32: 0 | D32: 1 | E32: 2 | F32: 3 | G32: 4 | H32: 5 | I32: 6 | J32: 7 | K32: 8 | L32: 9 | M32: 10 | P32: risk_adjusted_build_P10 | Q32: 649.3433
B33: Revenue (build, if it succeeds) | C33: =IF(C$32=0,0,IF(C$32<=$C$28,Assumptions!$I$3*$C$29^(C$32-1),0)) -> 0 | D33: =IF(D$32=0,0,IF(D$32<=$C$28,Assumptions!$I$3*$C$29^(D$32-1),C33*(1+IF(D$32-$C$28=1,Assumptions!$D$31,IF(D$32-$C$28=2,Assumptions!$D$32,Assumptions!$I$16))))) -> 25 | E33: =IF(E$32=0,0,IF(E$32<=$C$28,Assumptions!$I$3*$C$29^(E$32-1),D33*(1+IF(E$32-$C$28=1,Assumptions!$D$31,IF(E$32-$C$28=2,Assumptions!$D$32,Assumptions!$I$16))))) -> 93.13968 | F33: =IF(F$32=0,0,IF(F$32<=$C$28,Assumptions!$I$3*$C$29^(F$32-1),E33*(1+IF(F$32-$C$28=1,Assumptions!$D$31,IF(F$32-$C$28=2,Assumptions!$D$32,Assumptions!$I$16))))) -> 347 | G33: =IF(G$32=0,0,IF(G$32<=$C$28,Assumptions!$I$3*$C$29^(G$32-1),F33*(1+IF(G$32-$C$28=1,Assumptions!$D$31,IF(G$32-$C$28=2,Assumptions!$D$32,Assumptions!$I$16))))) -> 513.56 | H33: =IF(H$32=0,0,IF(H$32<=$C$28,Assumptions!$I$3*$C$29^(H$32-1),G33*(1+IF(H$32-$C$28=1,Assumptions!$D$31,IF(H$32-$C$28=2,Assumptions!$D$32,Assumptions!$I$16))))) -> 688.1704 | I33: =IF(I$32=0,0,IF(I$32<=$C$28,Assumptions!$I$3*$C$29^(I$32-1),H33*(1+IF(I$32-$C$28=1,Assumptions!$D$31,IF(I$32-$C$28=2,Assumptions!$D$32,Assumptions!$I$16))))) -> 770.75085 | J33: =IF(J$32=0,0,IF(J$32<=$C$28,Assumptions!$I$3*$C$29^(J$32-1),I33*(1+IF(J$32-$C$28=1,Assumptions!$D$31,IF(J$32-$C$28=2,Assumptions!$D$32,Assumptions!$I$16))))) -> 863.24095 | K33: =IF(K$32=0,0,IF(K$32<=$C$28,Assumptions!$I$3*$C$29^(K$32-1),J33*(1+IF(K$32-$C$28=1,Assumptions!$D$31,IF(K$32-$C$28=2,Assumptions!$D$32,Assumptions!$I$16))))) -> 966.82986 | ... M33: =IF(M$32=0,0,IF(M$32<=$C$28,Assumptions!$I$3*$C$29^(M$32-1),L33*(1+IF(M$32-$C$28=1,Assumptions!$D$31,IF(M$32-$C$28=2,Assumptions!$D$32,Assumptions!$I$16))))) -> 1212.7914 | P33: cost_of_delay_P10 | Q33: 2011.9011
B34: Gross margin % | C34: =IF(C$32=0,0,IF(C$32<=$C$28,IF(C$32<=2,Assumptions!$I$4,Assumptions!$I$4+(C$32-2)/MAX($C$28-2,1)*(Assumptions!$I$5-Assumptions!$I$4)),Assumptions!$I$5)) -> 0 | D34: =IF(D$32=0,0,IF(D$32<=$C$28,IF(D$32<=2,Assumptions!$I$4,Assumptions!$I$4+(D$32-2)/MAX($C$28-2,1)*(Assumptions!$I$5-Assumptions!$I$4)),Assumptions!$I$5)) -> 0.6 | E34: =IF(E$32=0,0,IF(E$32<=$C$28,IF(E$32<=2,Assumptions!$I$4,Assumptions!$I$4+(E$32-2)/MAX($C$28-2,1)*(Assumptions!$I$5-Assumptions!$I$4)),Assumptions!$I$5)) -> 0.6 | F34: =IF(F$32=0,0,IF(F$32<=$C$28,IF(F$32<=2,Assumptions!$I$4,Assumptions!$I$4+(F$32-2)/MAX($C$28-2,1)*(Assumptions!$I$5-Assumptions!$I$4)),Assumptions!$I$5)) -> 0.7 | G34: =IF(G$32=0,0,IF(G$32<=$C$28,IF(G$32<=2,Assumptions!$I$4,Assumptions!$I$4+(G$32-2)/MAX($C$28-2,1)*(Assumptions!$I$5-Assumptions!$I$4)),Assumptions!$I$5)) -> 0.7 | H34: =IF(H$32=0,0,IF(H$32<=$C$28,IF(H$32<=2,Assumptions!$I$4,Assumptions!$I$4+(H$32-2)/MAX($C$28-2,1)*(Assumptions!$I$5-Assumptions!$I$4)),Assumptions!$I$5)) -> 0.7 | I34: =IF(I$32=0,0,IF(I$32<=$C$28,IF(I$32<=2,Assumptions!$I$4,Assumptions!$I$4+(I$32-2)/MAX($C$28-2,1)*(Assumptions!$I$5-Assumptions!$I$4)),Assumptions!$I$5)) -> 0.7 | J34: =IF(J$32=0,0,IF(J$32<=$C$28,IF(J$32<=2,Assumptions!$I$4,Assumptions!$I$4+(J$32-2)/MAX($C$28-2,1)*(Assumptions!$I$5-Assumptions!$I$4)),Assumptions!$I$5)) -> 0.7 | ... M34: =IF(M$32=0,0,IF(M$32<=$C$28,IF(M$32<=2,Assumptions!$I$4,Assumptions!$I$4+(M$32-2)/MAX($C$28-2,1)*(Assumptions!$I$5-Assumptions!$I$4)),Assumptions!$I$5)) -> 0.7 | P34: risk_adjusted_build_P50 | Q34: 1077.6989
B35: A&P % of revenue | C35: =IF(C$32=0,0,IF(C$32<=$C$28,IF(C$32<=2,Assumptions!$I$6,Assumptions!$I$7),Assumptions!$I$8)) -> 0 | D35: =IF(D$32=0,0,IF(D$32<=$C$28,IF(D$32<=2,Assumptions!$I$6,Assumptions!$I$7),Assumptions!$I$8)) -> 0.5 | E35: =IF(E$32=0,0,IF(E$32<=$C$28,IF(E$32<=2,Assumptions!$I$6,Assumptions!$I$7),Assumptions!$I$8)) -> 0.5 | F35: =IF(F$32=0,0,IF(F$32<=$C$28,IF(F$32<=2,Assumptions!$I$6,Assumptions!$I$7),Assumptions!$I$8)) -> 0.38 | G35: =IF(G$32=0,0,IF(G$32<=$C$28,IF(G$32<=2,Assumptions!$I$6,Assumptions!$I$7),Assumptions!$I$8)) -> 0.3 | H35: =IF(H$32=0,0,IF(H$32<=$C$28,IF(H$32<=2,Assumptions!$I$6,Assumptions!$I$7),Assumptions!$I$8)) -> 0.3 | I35: =IF(I$32=0,0,IF(I$32<=$C$28,IF(I$32<=2,Assumptions!$I$6,Assumptions!$I$7),Assumptions!$I$8)) -> 0.3 | J35: =IF(J$32=0,0,IF(J$32<=$C$28,IF(J$32<=2,Assumptions!$I$6,Assumptions!$I$7),Assumptions!$I$8)) -> 0.3 | ... M35: =IF(M$32=0,0,IF(M$32<=$C$28,IF(M$32<=2,Assumptions!$I$6,Assumptions!$I$7),Assumptions!$I$8)) -> 0.3 | P35: cost_of_delay_P50 | Q35: 2904.3537
B36: Gross profit | C36: =C34*C33 -> 0 | D36: =D34*D33 -> 15 | E36: =E34*E33 -> 55.883808 | F36: =F34*F33 -> 242.9 | G36: =G34*G33 -> 359.492 | H36: =H34*H33 -> 481.71928 | I36: =I34*I33 -> 539.52559 | J36: =J34*J33 -> 604.26866 | ... M36: =M34*M33 -> 848.95397 | P36: risk_adjusted_build_P90 | Q36: 1849.1016
B37: Marketing (A&P) | C37: =C35*C33 -> 0 | D37: =D35*D33 -> 12.5 | E37: =E35*E33 -> 46.56984 | F37: =F35*F33 -> 131.86 | G37: =G35*G33 -> 154.068 | H37: =H35*H33 -> 206.45112 | I37: =I35*I33 -> 231.22525 | J37: =J35*J33 -> 258.97228 | ... M37: =M35*M33 -> 363.83741 | P37: cost_of_delay_P90 | Q37: 4334.3398
B38: R&D | C38: =Assumptions!$I$12+Assumptions!$I$13*C33 -> 5 | D38: =Assumptions!$I$12+Assumptions!$I$13*D33 -> 5.5 | E38: =Assumptions!$I$12+Assumptions!$I$13*E33 -> 6.8627936 | F38: =Assumptions!$I$12+Assumptions!$I$13*F33 -> 11.94 | G38: =Assumptions!$I$12+Assumptions!$I$13*G33 -> 15.2712 | H38: =Assumptions!$I$12+Assumptions!$I$13*H33 -> 18.763408 | I38: =Assumptions!$I$12+Assumptions!$I$13*I33 -> 20.415017 | J38: =Assumptions!$I$12+Assumptions!$I$13*J33 -> 22.264819 | ... M38: =Assumptions!$I$12+Assumptions!$I$13*M33 -> 29.255828 | P38: share_breakeven_above_price | Q38: 0.8363
B39: Org cost | C39: =IF(C$32=0,0.5*Assumptions!$I$10,MAX(Assumptions!$I$10,Assumptions!$I$11*C33)) -> 10 | D39: =IF(D$32=0,0.5*Assumptions!$I$10,MAX(Assumptions!$I$10,Assumptions!$I$11*D33)) -> 20 | E39: =IF(E$32=0,0.5*Assumptions!$I$10,MAX(Assumptions!$I$10,Assumptions!$I$11*E33)) -> 20 | F39: =IF(F$32=0,0.5*Assumptions!$I$10,MAX(Assumptions!$I$10,Assumptions!$I$11*F33)) -> 26.025 | G39: =IF(G$32=0,0.5*Assumptions!$I$10,MAX(Assumptions!$I$10,Assumptions!$I$11*G33)) -> 38.517 | H39: =IF(H$32=0,0.5*Assumptions!$I$10,MAX(Assumptions!$I$10,Assumptions!$I$11*H33)) -> 51.61278 | I39: =IF(I$32=0,0.5*Assumptions!$I$10,MAX(Assumptions!$I$10,Assumptions!$I$11*I33)) -> 57.806314 | J39: =IF(J$32=0,0.5*Assumptions!$I$10,MAX(Assumptions!$I$10,Assumptions!$I$11*J33)) -> 64.743071 | ... M39: =IF(M$32=0,0.5*Assumptions!$I$10,MAX(Assumptions!$I$10,Assumptions!$I$11*M33)) -> 90.959354 | P39: n_draws | Q39: 10000
B40: Distribution & overheads (pre-scale rule) | C40: =IF(C$32=0,0,Assumptions!$I$9*C33) -> 0 | D40: =IF(D$32=0,0,Assumptions!$I$9*D33) -> 6.25 | E40: =IF(E$32=0,0,Assumptions!$I$9*E33) -> 23.28492 | F40: =IF(F$32=0,0,Assumptions!$I$9*F33) -> 86.75 | G40: =IF(G$32=0,0,Assumptions!$I$9*G33) -> 128.39 | H40: =IF(H$32=0,0,Assumptions!$I$9*H33) -> 172.0426 | I40: =IF(I$32=0,0,Assumptions!$I$9*I33) -> 192.68771 | J40: =IF(J$32=0,0,Assumptions!$I$9*J33) -> 215.81024 | ... M40: =IF(M$32=0,0,Assumptions!$I$9*M33) -> 303.19785
B41: EBITDA (pre-scale rule) | C41: =C36-C37-C40-C39-C38 -> -15 | D41: =D36-D37-D40-D39-D38 -> -29.25 | E41: =E36-E37-E40-E39-E38 -> -40.833746 | F41: =F36-F37-F40-F39-F38 -> -13.675 | G41: =G36-G37-G40-G39-G38 -> 23.2458 | H41: =H36-H37-H40-H39-H38 -> 32.849372 | I41: =I36-I37-I40-I39-I38 -> 37.391297 | J41: =J36-J37-J40-J39-J38 -> 42.478252 | ... M41: =M36-M37-M40-M39-M38 -> 61.703526
B42: Distribution & overheads (plug after scale) | C42: =IF(C$32<=$C$28,C40,C36-C37-C39-C38-C43) -> 0 | D42: =IF(D$32<=$C$28,D40,D36-D37-D39-D38-D43) -> 6.25 | E42: =IF(E$32<=$C$28,E40,E36-E37-E39-E38-E43) -> 23.28492 | F42: =IF(F$32<=$C$28,F40,F36-F37-F39-F38-F43) -> 86.75 | G42: =IF(G$32<=$C$28,G40,G36-G37-G39-G38-G43) -> 116.71372 | H42: =IF(H$32<=$C$28,H40,H36-H37-H39-H38-H43) -> 135.38676 | I42: =IF(I$32<=$C$28,I40,I36-I37-I39-I38-I43) -> 126.7984 | J42: =IF(J$32<=$C$28,J40,J36-J37-J39-J38-J43) -> 114.12725 | ... M42: =IF(M$32<=$C$28,M40,M36-M37-M39-M38-M43) -> 122.3431
B43: EBITDA | C43: =IF(C$32<=$C$28,C41,($C$52+(Assumptions!$I$18-$C$52)*MIN(MAX(C$32-$C$28,0)/Assumptions!$D$33,1))*C33) -> -15 | D43: =IF(D$32<=$C$28,D41,($C$52+(Assumptions!$I$18-$C$52)*MIN(MAX(D$32-$C$28,0)/Assumptions!$D$33,1))*D33) -> -29.25 | E43: =IF(E$32<=$C$28,E41,($C$52+(Assumptions!$I$18-$C$52)*MIN(MAX(E$32-$C$28,0)/Assumptions!$D$33,1))*E33) -> -40.833746 | F43: =IF(F$32<=$C$28,F41,($C$52+(Assumptions!$I$18-$C$52)*MIN(MAX(F$32-$C$28,0)/Assumptions!$D$33,1))*F33) -> -13.675 | G43: =IF(G$32<=$C$28,G41,($C$52+(Assumptions!$I$18-$C$52)*MIN(MAX(G$32-$C$28,0)/Assumptions!$D$33,1))*G33) -> 34.92208 | H43: =IF(H$32<=$C$28,H41,($C$52+(Assumptions!$I$18-$C$52)*MIN(MAX(H$32-$C$28,0)/Assumptions!$D$33,1))*H33) -> 69.50521 | I43: =IF(I$32<=$C$28,I41,($C$52+(Assumptions!$I$18-$C$52)*MIN(MAX(I$32-$C$28,0)/Assumptions!$D$33,1))*I33) -> 103.28061 | J43: =IF(J$32<=$C$28,J41,($C$52+(Assumptions!$I$18-$C$52)*MIN(MAX(J$32-$C$28,0)/Assumptions!$D$33,1))*J33) -> 144.16124 | ... M43: =IF(M$32<=$C$28,M41,($C$52+(Assumptions!$I$18-$C$52)*MIN(MAX(M$32-$C$28,0)/Assumptions!$D$33,1))*M33) -> 242.55828
B44: Net working capital | C44: =Assumptions!$I$14/365*C33 -> 0 | D44: =Assumptions!$I$14/365*D33 -> 2.0547945 | E44: =Assumptions!$I$14/365*E33 -> 7.6553162 | F44: =Assumptions!$I$14/365*F33 -> 28.520548 | G44: =Assumptions!$I$14/365*G33 -> 42.210411 | H44: =Assumptions!$I$14/365*H33 -> 56.561951 | I44: =Assumptions!$I$14/365*I33 -> 63.349385 | J44: =Assumptions!$I$14/365*J33 -> 70.951311 | ... M44: =Assumptions!$I$14/365*M33 -> 99.681483
B45: Working-capital investment | C45: =C44 -> 0 | D45: =D44-C44 -> 2.0547945 | E45: =E44-D44 -> 5.6005216 | F45: =F44-E44 -> 20.865232 | G45: =G44-F44 -> 13.689863 | H45: =H44-G44 -> 14.35154 | I45: =I44-H44 -> 6.7874341 | J45: =J44-I44 -> 7.6019262 | K45: =K44-J44 -> 8.5141573 | ... M45: =M44-L44 -> 10.680159
B46: Free cash flow | C46: =C43-C45 -> -15 | D46: =D43-D45 -> -31.304795 | E46: =E43-E45 -> -46.434267 | F46: =F43-F45 -> -34.540232 | G46: =G43-G45 -> 21.232217 | H46: =H43-H45 -> 55.153671 | I46: =I43-I45 -> 96.49318 | J46: =J43-J45 -> 136.55931 | ... M46: =M43-M45 -> 231.87812
B47: Cash burn | C47: =MAX(-C46,0) -> 15 | D47: =MAX(-D46,0) -> 31.304795 | E47: =MAX(-E46,0) -> 46.434267 | F47: =MAX(-F46,0) -> 34.540232 | G47: =MAX(-G46,0) -> 0 | H47: =MAX(-H46,0) -> 0 | I47: =MAX(-I46,0) -> 0 | J47: =MAX(-J46,0) -> 0 | ... M47: =MAX(-M46,0) -> 0
B48: Cumulative cash | C48: =C46 -> -15 | D48: =C48+D46 -> -46.304795 | E48: =D48+E46 -> -92.739062 | F48: =E48+F46 -> -127.27929 | G48: =F48+G46 -> -106.04708 | H48: =G48+H46 -> -50.893406 | I48: =H48+I46 -> 45.599774 | J48: =I48+J46 -> 182.15909 | K48: =J48+K46 -> 367.0109 | ... M48: =L48+M46 -> 805.92305
B49: Discount factor | C49: =(1+Assumptions!$I$15)^(-C$32) -> 1 | D49: =(1+Assumptions!$I$15)^(-D$32) -> 0.8984726 | E49: =(1+Assumptions!$I$15)^(-E$32) -> 0.80725301 | F49: =(1+Assumptions!$I$15)^(-F$32) -> 0.72529471 | G49: =(1+Assumptions!$I$15)^(-G$32) -> 0.65165742 | H49: =(1+Assumptions!$I$15)^(-H$32) -> 0.58549633 | I49: =(1+Assumptions!$I$15)^(-I$32) -> 0.52605241 | J49: =(1+Assumptions!$I$15)^(-J$32) -> 0.47264367 | ... M49: =(1+Assumptions!$I$15)^(-M$32) -> 0.34280595
B50: Bought brand revenue (Minimalist) | C50: =Assumptions!$I$19*(1+Assumptions!$I$16)^C$32 -> 690 | D50: =Assumptions!$I$19*(1+Assumptions!$I$16)^D$32 -> 772.8 | E50: =Assumptions!$I$19*(1+Assumptions!$I$16)^E$32 -> 865.536 | F50: =Assumptions!$I$19*(1+Assumptions!$I$16)^F$32 -> 969.40032 | G50: =Assumptions!$I$19*(1+Assumptions!$I$16)^G$32 -> 1085.7284 | H50: =Assumptions!$I$19*(1+Assumptions!$I$16)^H$32 -> 1216.0158 | I50: =Assumptions!$I$19*(1+Assumptions!$I$16)^I$32 -> 1361.9377 | J50: =Assumptions!$I$19*(1+Assumptions!$I$16)^J$32 -> 1525.3702 | ... M50: =Assumptions!$I$19*(1+Assumptions!$I$16)^M$32 -> 2143.0353
B51: Bought brand EBITDA | C51: =(Assumptions!$D$30+(Assumptions!$I$18-Assumptions!$D$30)*MIN(C$32/Assumptions!$D$33,1))*C50 -> 24.15 | D51: =(Assumptions!$D$30+(Assumptions!$I$18-Assumptions!$D$30)*MIN(D$32/Assumptions!$D$33,1))*D50 -> 52.5504 | E51: =(Assumptions!$D$30+(Assumptions!$I$18-Assumptions!$D$30)*MIN(E$32/Assumptions!$D$33,1))*E50 -> 87.419136 | F51: =(Assumptions!$D$30+(Assumptions!$I$18-Assumptions!$D$30)*MIN(F$32/Assumptions!$D$33,1))*F50 -> 129.89964 | G51: =(Assumptions!$D$30+(Assumptions!$I$18-Assumptions!$D$30)*MIN(G$32/Assumptions!$D$33,1))*G50 -> 181.31664 | H51: =(Assumptions!$D$30+(Assumptions!$I$18-Assumptions!$D$30)*MIN(H$32/Assumptions!$D$33,1))*H50 -> 243.20315 | I51: =(Assumptions!$D$30+(Assumptions!$I$18-Assumptions!$D$30)*MIN(I$32/Assumptions!$D$33,1))*I50 -> 272.38753 | J51: =(Assumptions!$D$30+(Assumptions!$I$18-Assumptions!$D$30)*MIN(J$32/Assumptions!$D$33,1))*J50 -> 305.07403 | ... M51: =(Assumptions!$D$30+(Assumptions!$I$18-Assumptions!$D$30)*MIN(M$32/Assumptions!$D$33,1))*M50 -> 428.60705
B52: EBITDA margin at scale year (start of ramp) | C52: =MAX(Assumptions!$D$30,INDEX(C41:M41,$C$28+1)/INDEX(C33:M33,$C$28+1)) -> 0.035
B54: PV of cash burn to scale (Y0..T) | C54: =SUMPRODUCT($C$47:$M$47,$C$49:$M$49,($C$32:$M$32<=$C$28)*1) -> 105.66255
B55: Peak cumulative burn | C55: =-MIN($C$48:$M$48) -> 127.27929
B56: P(success) | C56: =Assumptions!$I$17 -> 0.11
B57: Risk-adjusted build cost = PV burn / p | C57: =$C$54/$C$56 -> 960.56863
B58: Forgone profits (bought EBITDA minus build EBITDA after scale, PV Y1-Y10) | C58: =SUMPRODUCT($C$51:$M$51-$C$43:$M$43*($C$32:$M$32>$C$28),$C$49:$M$49,($C$32:$M$32>=1)*1) -> 764.25463
B59: Y10 revenue gap (bought minus build) | C59: =$M$50-$M$33 -> 930.24388
B60: Permanent share loss (Y10 gap capitalised, PV) | C60: =$C$59*Assumptions!$I$18/(Assumptions!$I$15-Assumptions!$I$25)*$M$49 -> 1012.3592
B61: Cost of delay = forgone profits + share loss | C61: =$C$58+$C$60 -> 1776.6138
B62: Build-equivalent cost | C62: =$C$57+$C$61 -> 2737.1824
B63: Other buy costs (last 9.5% + transaction + integration - cash acquired) | C63: =Assumptions!$I$21+Assumptions!$I$23+Assumptions!$I$20-Assumptions!$I$22 -> 527
B64: Buy all-in (100%) | C64: =Assumptions!$D$29+$C$63 -> 3233.45
B65: BREAKEVEN headline price for 90.5% | C65: =$C$62-$C$63 -> 2210.1824
B66: Headroom vs ₹2,706 Cr paid | C66: =$C$65-Assumptions!$D$29 -> -496.26756
B67: PV of a failed attempt (Y0..k) | C67: =SUMPRODUCT($C$47:$M$47,$C$49:$M$49,($C$32:$M$32<=$C$30)*1) -> 105.66255
B68: Refined build cost = PV burn + (1/p - 1) x PV failed attempt | C68: =$C$54+(1/$C$56-1)*$C$67 -> 960.56863
B69: Refined breakeven | C69: =$C$68+$C$61-$C$63 -> 2210.1824
B70: Cross-check: bought-brand DCF (100%, EBITDA proxy) | C70: =SUMPRODUCT($C$51:$M$51,$C$49:$M$49,($C$32:$M$32>=1)*1)+$M$51*(1+Assumptions!$I$25)/(Assumptions!$I$15-Assumptions!$I$25)*$M$49 -> 3646.8878
A72: Grid block: years to scale = column C header
B73: Years to scale T (rounded) | C73: =ROUND(Sensitivity!$C$17,0) -> 4
B74: Growth to scale g = (target / Y1 revenue)^(1/(T-1)) | C74: =(Assumptions!$I$26/Assumptions!$I$3)^(1/($C$73-1)) -> 2.4032364
B75: Failed-attempt years (int) | C75: =INT(Assumptions!$I$24) -> 3
B77: Year (Y0 = FY26) | C77: 0 | D77: 1 | E77: 2 | F77: 3 | G77: 4 | H77: 5 | I77: 6 | J77: 7 | K77: 8 | L77: 9 | M77: 10
B78: Revenue (build, if it succeeds) | C78: =IF(C$77=0,0,IF(C$77<=$C$73,Assumptions!$I$3*$C$74^(C$77-1),0)) -> 0 | D78: =IF(D$77=0,0,IF(D$77<=$C$73,Assumptions!$I$3*$C$74^(D$77-1),C78*(1+IF(D$77-$C$73=1,Assumptions!$D$31,IF(D$77-$C$73=2,Assumptions!$D$32,Assumptions!$I$16))))) -> 25 | E78: =IF(E$77=0,0,IF(E$77<=$C$73,Assumptions!$I$3*$C$74^(E$77-1),D78*(1+IF(E$77-$C$73=1,Assumptions!$D$31,IF(E$77-$C$73=2,Assumptions!$D$32,Assumptions!$I$16))))) -> 60.080909 | F78: =IF(F$77=0,0,IF(F$77<=$C$73,Assumptions!$I$3*$C$74^(F$77-1),E78*(1+IF(F$77-$C$73=1,Assumptions!$D$31,IF(F$77-$C$73=2,Assumptions!$D$32,Assumptions!$I$16))))) -> 144.38863 | G78: =IF(G$77=0,0,IF(G$77<=$C$73,Assumptions!$I$3*$C$74^(G$77-1),F78*(1+IF(G$77-$C$73=1,Assumptions!$D$31,IF(G$77-$C$73=2,Assumptions!$D$32,Assumptions!$I$16))))) -> 347 | H78: =IF(H$77=0,0,IF(H$77<=$C$73,Assumptions!$I$3*$C$74^(H$77-1),G78*(1+IF(H$77-$C$73=1,Assumptions!$D$31,IF(H$77-$C$73=2,Assumptions!$D$32,Assumptions!$I$16))))) -> 513.56 | I78: =IF(I$77=0,0,IF(I$77<=$C$73,Assumptions!$I$3*$C$74^(I$77-1),H78*(1+IF(I$77-$C$73=1,Assumptions!$D$31,IF(I$77-$C$73=2,Assumptions!$D$32,Assumptions!$I$16))))) -> 688.1704 | J78: =IF(J$77=0,0,IF(J$77<=$C$73,Assumptions!$I$3*$C$74^(J$77-1),I78*(1+IF(J$77-$C$73=1,Assumptions!$D$31,IF(J$77-$C$73=2,Assumptions!$D$32,Assumptions!$I$16))))) -> 770.75085 | K78: =IF(K$77=0,0,IF(K$77<=$C$73,Assumptions!$I$3*$C$74^(K$77-1),J78*(1+IF(K$77-$C$73=1,Assumptions!$D$31,IF(K$77-$C$73=2,Assumptions!$D$32,Assumptions!$I$16))))) -> 863.24095 | ... M78: =IF(M$77=0,0,IF(M$77<=$C$73,Assumptions!$I$3*$C$74^(M$77-1),L78*(1+IF(M$77-$C$73=1,Assumptions!$D$31,IF(M$77-$C$73=2,Assumptions!$D$32,Assumptions!$I$16))))) -> 1082.8494
B79: Gross margin % | C79: =IF(C$77=0,0,IF(C$77<=$C$73,IF(C$77<=2,Assumptions!$I$4,Assumptions!$I$4+(C$77-2)/MAX($C$73-2,1)*(Assumptions!$I$5-Assumptions!$I$4)),Assumptions!$I$5)) -> 0 | D79: =IF(D$77=0,0,IF(D$77<=$C$73,IF(D$77<=2,Assumptions!$I$4,Assumptions!$I$4+(D$77-2)/MAX($C$73-2,1)*(Assumptions!$I$5-Assumptions!$I$4)),Assumptions!$I$5)) -> 0.6 | E79: =IF(E$77=0,0,IF(E$77<=$C$73,IF(E$77<=2,Assumptions!$I$4,Assumptions!$I$4+(E$77-2)/MAX($C$73-2,1)*(Assumptions!$I$5-Assumptions!$I$4)),Assumptions!$I$5)) -> 0.6 | F79: =IF(F$77=0,0,IF(F$77<=$C$73,IF(F$77<=2,Assumptions!$I$4,Assumptions!$I$4+(F$77-2)/MAX($C$73-2,1)*(Assumptions!$I$5-Assumptions!$I$4)),Assumptions!$I$5)) -> 0.65 | G79: =IF(G$77=0,0,IF(G$77<=$C$73,IF(G$77<=2,Assumptions!$I$4,Assumptions!$I$4+(G$77-2)/MAX($C$73-2,1)*(Assumptions!$I$5-Assumptions!$I$4)),Assumptions!$I$5)) -> 0.7 | H79: =IF(H$77=0,0,IF(H$77<=$C$73,IF(H$77<=2,Assumptions!$I$4,Assumptions!$I$4+(H$77-2)/MAX($C$73-2,1)*(Assumptions!$I$5-Assumptions!$I$4)),Assumptions!$I$5)) -> 0.7 | I79: =IF(I$77=0,0,IF(I$77<=$C$73,IF(I$77<=2,Assumptions!$I$4,Assumptions!$I$4+(I$77-2)/MAX($C$73-2,1)*(Assumptions!$I$5-Assumptions!$I$4)),Assumptions!$I$5)) -> 0.7 | J79: =IF(J$77=0,0,IF(J$77<=$C$73,IF(J$77<=2,Assumptions!$I$4,Assumptions!$I$4+(J$77-2)/MAX($C$73-2,1)*(Assumptions!$I$5-Assumptions!$I$4)),Assumptions!$I$5)) -> 0.7 | ... M79: =IF(M$77=0,0,IF(M$77<=$C$73,IF(M$77<=2,Assumptions!$I$4,Assumptions!$I$4+(M$77-2)/MAX($C$73-2,1)*(Assumptions!$I$5-Assumptions!$I$4)),Assumptions!$I$5)) -> 0.7
B80: A&P % of revenue | C80: =IF(C$77=0,0,IF(C$77<=$C$73,IF(C$77<=2,Assumptions!$I$6,Assumptions!$I$7),Assumptions!$I$8)) -> 0 | D80: =IF(D$77=0,0,IF(D$77<=$C$73,IF(D$77<=2,Assumptions!$I$6,Assumptions!$I$7),Assumptions!$I$8)) -> 0.5 | E80: =IF(E$77=0,0,IF(E$77<=$C$73,IF(E$77<=2,Assumptions!$I$6,Assumptions!$I$7),Assumptions!$I$8)) -> 0.5 | F80: =IF(F$77=0,0,IF(F$77<=$C$73,IF(F$77<=2,Assumptions!$I$6,Assumptions!$I$7),Assumptions!$I$8)) -> 0.38 | G80: =IF(G$77=0,0,IF(G$77<=$C$73,IF(G$77<=2,Assumptions!$I$6,Assumptions!$I$7),Assumptions!$I$8)) -> 0.38 | H80: =IF(H$77=0,0,IF(H$77<=$C$73,IF(H$77<=2,Assumptions!$I$6,Assumptions!$I$7),Assumptions!$I$8)) -> 0.3 | I80: =IF(I$77=0,0,IF(I$77<=$C$73,IF(I$77<=2,Assumptions!$I$6,Assumptions!$I$7),Assumptions!$I$8)) -> 0.3 | J80: =IF(J$77=0,0,IF(J$77<=$C$73,IF(J$77<=2,Assumptions!$I$6,Assumptions!$I$7),Assumptions!$I$8)) -> 0.3 | ... M80: =IF(M$77=0,0,IF(M$77<=$C$73,IF(M$77<=2,Assumptions!$I$6,Assumptions!$I$7),Assumptions!$I$8)) -> 0.3
B81: Gross profit | C81: =C79*C78 -> 0 | D81: =D79*D78 -> 15 | E81: =E79*E78 -> 36.048546 | F81: =F79*F78 -> 93.852607 | G81: =G79*G78 -> 242.9 | H81: =H79*H78 -> 359.492 | I81: =I79*I78 -> 481.71928 | J81: =J79*J78 -> 539.52559 | ... M81: =M79*M78 -> 757.99461
B82: Marketing (A&P) | C82: =C80*C78 -> 0 | D82: =D80*D78 -> 12.5 | E82: =E80*E78 -> 30.040455 | F82: =F80*F78 -> 54.867678 | G82: =G80*G78 -> 131.86 | H82: =H80*H78 -> 154.068 | I82: =I80*I78 -> 206.45112 | J82: =J80*J78 -> 231.22525 | ... M82: =M80*M78 -> 324.85483
B83: R&D | C83: =Assumptions!$I$12+Assumptions!$I$13*C78 -> 5 | D83: =Assumptions!$I$12+Assumptions!$I$13*D78 -> 5.5 | E83: =Assumptions!$I$12+Assumptions!$I$13*E78 -> 6.2016182 | F83: =Assumptions!$I$12+Assumptions!$I$13*F78 -> 7.8877725 | G83: =Assumptions!$I$12+Assumptions!$I$13*G78 -> 11.94 | H83: =Assumptions!$I$12+Assumptions!$I$13*H78 -> 15.2712 | I83: =Assumptions!$I$12+Assumptions!$I$13*I78 -> 18.763408 | J83: =Assumptions!$I$12+Assumptions!$I$13*J78 -> 20.415017 | ... M83: =Assumptions!$I$12+Assumptions!$I$13*M78 -> 26.656989
B84: Org cost | C84: =IF(C$77=0,0.5*Assumptions!$I$10,MAX(Assumptions!$I$10,Assumptions!$I$11*C78)) -> 10 | D84: =IF(D$77=0,0.5*Assumptions!$I$10,MAX(Assumptions!$I$10,Assumptions!$I$11*D78)) -> 20 | E84: =IF(E$77=0,0.5*Assumptions!$I$10,MAX(Assumptions!$I$10,Assumptions!$I$11*E78)) -> 20 | F84: =IF(F$77=0,0.5*Assumptions!$I$10,MAX(Assumptions!$I$10,Assumptions!$I$11*F78)) -> 20 | G84: =IF(G$77=0,0.5*Assumptions!$I$10,MAX(Assumptions!$I$10,Assumptions!$I$11*G78)) -> 26.025 | H84: =IF(H$77=0,0.5*Assumptions!$I$10,MAX(Assumptions!$I$10,Assumptions!$I$11*H78)) -> 38.517 | I84: =IF(I$77=0,0.5*Assumptions!$I$10,MAX(Assumptions!$I$10,Assumptions!$I$11*I78)) -> 51.61278 | J84: =IF(J$77=0,0.5*Assumptions!$I$10,MAX(Assumptions!$I$10,Assumptions!$I$11*J78)) -> 57.806314 | ... M84: =IF(M$77=0,0.5*Assumptions!$I$10,MAX(Assumptions!$I$10,Assumptions!$I$11*M78)) -> 81.213709
B85: Distribution & overheads (pre-scale rule) | C85: =IF(C$77=0,0,Assumptions!$I$9*C78) -> 0 | D85: =IF(D$77=0,0,Assumptions!$I$9*D78) -> 6.25 | E85: =IF(E$77=0,0,Assumptions!$I$9*E78) -> 15.020227 | F85: =IF(F$77=0,0,Assumptions!$I$9*F78) -> 36.097157 | G85: =IF(G$77=0,0,Assumptions!$I$9*G78) -> 86.75 | H85: =IF(H$77=0,0,Assumptions!$I$9*H78) -> 128.39 | I85: =IF(I$77=0,0,Assumptions!$I$9*I78) -> 172.0426 | J85: =IF(J$77=0,0,Assumptions!$I$9*J78) -> 192.68771 | ... M85: =IF(M$77=0,0,Assumptions!$I$9*M78) -> 270.71236
B86: EBITDA (pre-scale rule) | C86: =C81-C82-C85-C84-C83 -> -15 | D86: =D81-D82-D85-D84-D83 -> -29.25 | E86: =E81-E82-E85-E84-E83 -> -35.213755 | F86: =F81-F82-F85-F84-F83 -> -25 | G86: =G81-G82-G85-G84-G83 -> -13.675 | H86: =H81-H82-H85-H84-H83 -> 23.2458 | I86: =I81-I82-I85-I84-I83 -> 32.849372 | J86: =J81-J82-J85-J84-J83 -> 37.391297 | ... M86: =M81-M82-M85-M84-M83 -> 54.55672
B87: Distribution & overheads (plug after scale) | C87: =IF(C$77<=$C$73,C85,C81-C82-C84-C83-C88) -> 0 | D87: =IF(D$77<=$C$73,D85,D81-D82-D84-D83-D88) -> 6.25 | E87: =IF(E$77<=$C$73,E85,E81-E82-E84-E83-E88) -> 15.020227 | F87: =IF(F$77<=$C$73,F85,F81-F82-F84-F83-F88) -> 36.097157 | G87: =IF(G$77<=$C$73,G85,G81-G82-G84-G83-G88) -> 86.75 | H87: =IF(H$77<=$C$73,H85,H81-H82-H84-H83-H88) -> 116.71372 | I87: =IF(I$77<=$C$73,I85,I81-I82-I84-I83-I88) -> 135.38676 | J87: =IF(J$77<=$C$73,J85,J81-J82-J84-J83-J88) -> 126.7984 | ... M87: =IF(M$77<=$C$73,M85,M81-M82-M84-M83-M88) -> 108.69919
B88: EBITDA | C88: =IF(C$77<=$C$73,C86,($C$97+(Assumptions!$I$18-$C$97)*MIN(MAX(C$77-$C$73,0)/Assumptions!$D$33,1))*C78) -> -15 | D88: =IF(D$77<=$C$73,D86,($C$97+(Assumptions!$I$18-$C$97)*MIN(MAX(D$77-$C$73,0)/Assumptions!$D$33,1))*D78) -> -29.25 | E88: =IF(E$77<=$C$73,E86,($C$97+(Assumptions!$I$18-$C$97)*MIN(MAX(E$77-$C$73,0)/Assumptions!$D$33,1))*E78) -> -35.213755 | F88: =IF(F$77<=$C$73,F86,($C$97+(Assumptions!$I$18-$C$97)*MIN(MAX(F$77-$C$73,0)/Assumptions!$D$33,1))*F78) -> -25 | G88: =IF(G$77<=$C$73,G86,($C$97+(Assumptions!$I$18-$C$97)*MIN(MAX(G$77-$C$73,0)/Assumptions!$D$33,1))*G78) -> -13.675 | H88: =IF(H$77<=$C$73,H86,($C$97+(Assumptions!$I$18-$C$97)*MIN(MAX(H$77-$C$73,0)/Assumptions!$D$33,1))*H78) -> 34.92208 | I88: =IF(I$77<=$C$73,I86,($C$97+(Assumptions!$I$18-$C$97)*MIN(MAX(I$77-$C$73,0)/Assumptions!$D$33,1))*I78) -> 69.50521 | J88: =IF(J$77<=$C$73,J86,($C$97+(Assumptions!$I$18-$C$97)*MIN(MAX(J$77-$C$73,0)/Assumptions!$D$33,1))*J78) -> 103.28061 | ... M88: =IF(M$77<=$C$73,M86,($C$97+(Assumptions!$I$18-$C$97)*MIN(MAX(M$77-$C$73,0)/Assumptions!$D$33,1))*M78) -> 216.56989
B89: Net working capital | C89: =Assumptions!$I$14/365*C78 -> 0 | D89: =Assumptions!$I$14/365*D78 -> 2.0547945 | E89: =Assumptions!$I$14/365*E78 -> 4.9381569 | F89: =Assumptions!$I$14/365*F78 -> 11.867558 | G89: =Assumptions!$I$14/365*G78 -> 28.520548 | H89: =Assumptions!$I$14/365*H78 -> 42.210411 | I89: =Assumptions!$I$14/365*I78 -> 56.561951 | J89: =Assumptions!$I$14/365*J78 -> 63.349385 | ... M89: =Assumptions!$I$14/365*M78 -> 89.001324
B90: Working-capital investment | C90: =C89 -> 0 | D90: =D89-C89 -> 2.0547945 | E90: =E89-D89 -> 2.8833624 | F90: =F89-E89 -> 6.9294014 | G90: =G89-F89 -> 16.65299 | H90: =H89-G89 -> 13.689863 | I90: =I89-H89 -> 14.35154 | J90: =J89-I89 -> 6.7874341 | K90: =K89-J89 -> 7.6019262 | ... M90: =M89-L89 -> 9.5358562
B91: Free cash flow | C91: =C88-C90 -> -15 | D91: =D88-D90 -> -31.304795 | E91: =E88-E90 -> -38.097117 | F91: =F88-F90 -> -31.929401 | G91: =G88-G90 -> -30.32799 | H91: =H88-H90 -> 21.232217 | I91: =I88-I90 -> 55.153671 | J91: =J88-J90 -> 96.49318 | ... M91: =M88-M90 -> 207.03403
B92: Cash burn | C92: =MAX(-C91,0) -> 15 | D92: =MAX(-D91,0) -> 31.304795 | E92: =MAX(-E91,0) -> 38.097117 | F92: =MAX(-F91,0) -> 31.929401 | G92: =MAX(-G91,0) -> 30.32799 | H92: =MAX(-H91,0) -> 0 | I92: =MAX(-I91,0) -> 0 | J92: =MAX(-J91,0) -> 0 | ... M92: =MAX(-M91,0) -> 0
B93: Cumulative cash | C93: =C91 -> -15 | D93: =C93+D91 -> -46.304795 | E93: =D93+E91 -> -84.401912 | F93: =E93+F91 -> -116.33131 | G93: =F93+G91 -> -146.6593 | H93: =G93+H91 -> -125.42709 | I93: =H93+I91 -> -70.273415 | J93: =I93+J91 -> 26.219765 | K93: =J93+K91 -> 162.77908 | ... M93: =L93+M91 -> 554.66493
B94: Discount factor | C94: =(1+Assumptions!$I$15)^(-C$77) -> 1 | D94: =(1+Assumptions!$I$15)^(-D$77) -> 0.8984726 | E94: =(1+Assumptions!$I$15)^(-E$77) -> 0.80725301 | F94: =(1+Assumptions!$I$15)^(-F$77) -> 0.72529471 | G94: =(1+Assumptions!$I$15)^(-G$77) -> 0.65165742 | H94: =(1+Assumptions!$I$15)^(-H$77) -> 0.58549633 | I94: =(1+Assumptions!$I$15)^(-I$77) -> 0.52605241 | J94: =(1+Assumptions!$I$15)^(-J$77) -> 0.47264367 | ... M94: =(1+Assumptions!$I$15)^(-M$77) -> 0.34280595
B95: Bought brand revenue (Minimalist) | C95: =Assumptions!$I$19*(1+Assumptions!$I$16)^C$77 -> 690 | D95: =Assumptions!$I$19*(1+Assumptions!$I$16)^D$77 -> 772.8 | E95: =Assumptions!$I$19*(1+Assumptions!$I$16)^E$77 -> 865.536 | F95: =Assumptions!$I$19*(1+Assumptions!$I$16)^F$77 -> 969.40032 | G95: =Assumptions!$I$19*(1+Assumptions!$I$16)^G$77 -> 1085.7284 | H95: =Assumptions!$I$19*(1+Assumptions!$I$16)^H$77 -> 1216.0158 | I95: =Assumptions!$I$19*(1+Assumptions!$I$16)^I$77 -> 1361.9377 | J95: =Assumptions!$I$19*(1+Assumptions!$I$16)^J$77 -> 1525.3702 | ... M95: =Assumptions!$I$19*(1+Assumptions!$I$16)^M$77 -> 2143.0353
B96: Bought brand EBITDA | C96: =(Assumptions!$D$30+(Assumptions!$I$18-Assumptions!$D$30)*MIN(C$77/Assumptions!$D$33,1))*C95 -> 24.15 | D96: =(Assumptions!$D$30+(Assumptions!$I$18-Assumptions!$D$30)*MIN(D$77/Assumptions!$D$33,1))*D95 -> 52.5504 | E96: =(Assumptions!$D$30+(Assumptions!$I$18-Assumptions!$D$30)*MIN(E$77/Assumptions!$D$33,1))*E95 -> 87.419136 | F96: =(Assumptions!$D$30+(Assumptions!$I$18-Assumptions!$D$30)*MIN(F$77/Assumptions!$D$33,1))*F95 -> 129.89964 | G96: =(Assumptions!$D$30+(Assumptions!$I$18-Assumptions!$D$30)*MIN(G$77/Assumptions!$D$33,1))*G95 -> 181.31664 | H96: =(Assumptions!$D$30+(Assumptions!$I$18-Assumptions!$D$30)*MIN(H$77/Assumptions!$D$33,1))*H95 -> 243.20315 | I96: =(Assumptions!$D$30+(Assumptions!$I$18-Assumptions!$D$30)*MIN(I$77/Assumptions!$D$33,1))*I95 -> 272.38753 | J96: =(Assumptions!$D$30+(Assumptions!$I$18-Assumptions!$D$30)*MIN(J$77/Assumptions!$D$33,1))*J95 -> 305.07403 | ... M96: =(Assumptions!$D$30+(Assumptions!$I$18-Assumptions!$D$30)*MIN(M$77/Assumptions!$D$33,1))*M95 -> 428.60705
B97: EBITDA margin at scale year (start of ramp) | C97: =MAX(Assumptions!$D$30,INDEX(C86:M86,$C$73+1)/INDEX(C78:M78,$C$73+1)) -> 0.035
B99: PV of cash burn to scale (Y0..T) | C99: =SUMPRODUCT($C$92:$M$92,$C$94:$M$94,($C$77:$M$77<=$C$73)*1) -> 116.8022
B100: Peak cumulative burn | C100: =-MIN($C$93:$M$93) -> 146.6593
B101: P(success) | C101: =Assumptions!$I$17 -> 0.11
B102: Risk-adjusted build cost = PV burn / p | C102: =$C$99/$C$101 -> 1061.8382
B103: Forgone profits (bought EBITDA minus build EBITDA after scale, PV Y1-Y10) | C103: =SUMPRODUCT($C$96:$M$96-$C$88:$M$88*($C$77:$M$77>$C$73),$C$94:$M$94,($C$77:$M$77>=1)*1) -> 883.00718
B104: Y10 revenue gap (bought minus build) | C104: =$M$95-$M$78 -> 1060.1858
B105: Permanent share loss (Y10 gap capitalised, PV) | C105: =$C$104*Assumptions!$I$18/(Assumptions!$I$15-Assumptions!$I$25)*$M$94 -> 1153.7715
...

Sheet Source_Log
A1: source_id | B1: url | C1: title | D1: publisher | E1: tier | F1: date_published | G1: date_accessed | H1: notes
A2: S001 | B2: https://bseindia.com/xml-data/corpfiling/AttachHis/52af87d5-25a4-45c8-aad3-78626bd1a474.pdf | C2: S001_hul_bse_filing_52af87d5 | D2: BSE / Hindustan Unilever Ltd | E2: T1 | G2: 2026-10-10 | H2: pdf: sources/pdf/S001_hul_bse_filing_52af87d5.pdf. Reg 30 annexure for Nutritionalab (Wellbeing Nutrition) + joint press release covering OZiva
A3: S002 | B3: https://nsearchives.nseindia.com/corporate/HINDUNILVR_21042025201301_MinimalistSEIntimation21042025signed.pdf | C3: HUL intimation: completion of acquisition of Uprising Science (Minimalist) | D3: NSE / Hindustan Unilever Ltd | E3: T1 | F3: 2025-04-21 | G3: 2026-10-10 | H3: pdf: sources/pdf/S002_hul_minimalist_completion.pdf
A4: S003 | B4: https://www.hul.co.in/files/update-on-acquisition-of-shares-of-zywie-ventures-private-limited.pdf | C4: HUL: Update on acquisition of shares of Zywie Ventures Pvt Ltd (OZiva) | D4: Hindustan Unilever Ltd | E4: T1 | G4: 2026-10-10 | H4: pdf: sources/pdf/S003_hul_oziva_update.pdf
A5: S004 | B5: https://bsmedia.business-standard.com/_media/bs/data/announcements/bse/18122025/44cb5b88-2099-437b-952c-0366aa7fe7d0.pdf | C5: BSE announcement 2025-12-18 (44cb5b88) | D5: BSE announcement via Business Standard media mirror | E5: T1 | G5: 2026-10-10 | H5: pdf: sources/pdf/S004_bse_announcement_44cb5b88.pdf. NOT RELEVANT: HUL stake in renewable-energy SPV (found while searching); kept for audit trail
A6: S005 | B6: https://bseindia.com/xml-data/corpfiling/AttachHis/1c2d765b-c83b-4e87-b1cf-15f4bea39542.pdf | C6: S005_hul_bse_filing_1c2d765b | D6: BSE / Hindustan Unilever Ltd | E6: T1 | G6: 2026-10-10 | H6: pdf: sources/pdf/S005_hul_bse_filing_1c2d765b.pdf
A7: S006 | B7: https://www.unilever.com/news/press-and-media/press-releases/2025/hul-to-acquire-premium-beauty-brand-minimalist/ | C7: HUL to acquire premium beauty brand Minimalist (press release) | D7: Unilever plc / HUL | E7: T1 | F7: 2025-01-23 | G7: 2026-10-10 | H7: html
A8: S007 | B8: https://www.bseindia.com/xml-data/corpfiling/AttachHis/7ecb9005-13d6-4ea3-8cad-7fe05bffd54e.pdf | C8: HUL Reg 30 disclosure: acquisition of Uprising Science (Minimalist) | D8: BSE / Hindustan Unilever Ltd | E8: T1 | F8: 2025-01-22 | G8: 2026-10-10 | H8: pdf: sources/pdf/S007_hul_minimalist_reg30.pdf
A9: S008 | B9: https://www.bseindia.com/xml-data/corpfiling/AttachHis/a9bee337-d3ac-428e-b3eb-9fe3bf141942.pdf | C9: HUL Reg 30 disclosure: proposed acquisition of Zywie Ventures (OZiva) | D9: BSE / Hindustan Unilever Ltd | E9: T1 | F9: 2022-12-08 | G9: 2026-10-10 | H9: pdf: sources/pdf/S008_hul_oziva_reg30.pdf
A10: S009 | B10: https://www.bseindia.com/xml-data/corpfiling/AttachHis/3e15d4b2-c14b-4013-a49f-d166f1078be7.pdf | C10: HUL Reg 30: proposed acquisition of balance 49% of Zywie Ventures (OZiva) | D10: BSE / Hindustan Unilever Ltd | E10: T1 | F10: 2026-02-12 | G10: 2026-10-10 | H10: pdf: sources/pdf/S009_hul_oziva_balance49.pdf
A11: S010 | B11: https://www.bseindia.com/xml-data/corpfiling/AttachHis/1cafc68f-8547-4920-9727-ce8cf50cb540.pdf | C11: HUL Reg 30: Diversification/Disinvestment 2026-02-12 | D11: BSE / Hindustan Unilever Ltd | E11: T1 | F11: 2026-02-12 | G11: 2026-10-10 | H11: pdf: sources/pdf/S010_hul_disinvest_20260212.pdf. DUPLICATE of S009 (same PDF attached under a second BSE headline)
A12: S011 | B12: https://www.bseindia.com/xml-data/corpfiling/AttachHis/85664ebb-3e33-4717-b011-309cb8c3bb8c.pdf | C12: HUL Reg 30: Diversification/Disinvestment 2026-03-04 | D12: BSE / Hindustan Unilever Ltd | E12: T1 | F12: 2026-03-04 | G12: 2026-10-10 | H12: pdf: sources/pdf/S011_hul_disinvest_20260304.pdf
A13: S012 | B13: https://www.bseindia.com/xml-data/corpfiling/AttachHis/d954777a-1d5b-4f96-82fb-710b2fdaf7bf.pdf | C13: HUL Reg 30: completion of acquisition of 19.8% of Nutritionalab (Wellbeing Nutrition) | D13: BSE / Hindustan Unilever Ltd | E13: T1 | F13: 2023-01-04 | G13: 2026-10-10 | H13: pdf: sources/pdf/S012_hul_wellbeing_completion.pdf
A14: S013 | B14: https://www.bseindia.com/xml-data/corpfiling/AttachHis/2919b815-f54c-41e2-894d-65994e51f770.pdf | C14: ITC Reg 30: binding term sheet to acquire Sproutlife Foods (Yoga Bar) | D14: BSE / ITC Ltd | E14: T1 | F14: 2023-01-17 | G14: 2026-10-10 | H14: pdf: sources/pdf/S013_itc_sproutlife_termsheet.pdf
A15: S014 | B15: https://www.bseindia.com/xml-data/corpfiling/AttachHis/b73174dc-3be1-4791-bb05-bce545ec7f84.pdf | C15: ITC Reg 30: transaction documents for 100% of Sproutlife Foods | D15: BSE / ITC Ltd | E15: T1 | F15: 2023-04-19 | G15: 2026-10-10 | H15: pdf: sources/pdf/S014_itc_sproutlife_docs.pdf
A16: S015 | B16: https://www.bseindia.com/xml-data/corpfiling/AttachHis/5f8b4f58-8459-4a20-968f-0ed992923469.pdf | C16: ITC Reg 30: acquisition of shares of Sproutlife Foods (tranche 1) | D16: BSE / ITC Ltd | E16: T1 | F16: 2023-05-05 | G16: 2026-10-10 | H16: pdf: sources/pdf/S015_itc_sproutlife_t1.pdf
A17: S016 | B17: https://www.bseindia.com/xml-data/corpfiling/AttachHis/6f9ac15e-3ac4-47a5-bc1b-f8043caf0b67.pdf | C17: ITC Reg 30: acquisition of shares of Sproutlife Foods (Mar 2024) | D17: BSE / ITC Ltd | E17: T1 | F17: 2024-03-11 | G17: 2026-10-10 | H17: pdf: sources/pdf/S016_itc_sproutlife_202403.pdf
A18: S017 | B18: https://www.bseindia.com/xml-data/corpfiling/AttachHis/da931624-7fe0-42e8-978a-173597ebe5be.pdf | C18: ITC Reg 30: acquisition of shares of Sproutlife Foods (Sep 2024) | D18: BSE / ITC Ltd | E18: T1 | F18: 2024-09-25 | G18: 2026-10-10 | H18: pdf: sources/pdf/S017_itc_sproutlife_202409.pdf
... A43: S042 | B43: https://www.bseindia.com/xml-data/corpfiling/AttachHis/734e383e-da03-4b94-ad73-36b9f9c10cc8.pdf | C43: TCPL: Scheme of amalgamation of NourishCo, Tata Smartfoodz and Tata Consumer Soulfull effective | D43: BSE / Tata Consumer Products Ltd | E43: T1 | F43: 2024-09-01 | G43: 2026-10-10 | H43: pdf: sources/pdf/S042_tcpl_soulfull_amalgamation.pdf
A44: S043 | B44: https://bwretailworld.com/fmcg/tata-consumer-products-raises-capital-foods-stake-to-80 | C44: Tata Consumer Deepens Capital Foods Bet, Raises Stake To 80% | D44: BW Retail World | E44: T3 | G44: 2026-10-10 | H44: html
A45: S044 | B45: https://tataconsumer.com/integrated-annual-report/explore-new-opportunities.html | C45: Tata Consumer integrated annual report: Explore new opportunities | D45: Tata Consumer Products Ltd | E45: T1 | G45: 2026-10-10 | H45: html
A46: S045 | B46: https://www.bseindia.com/xml-data/corpfiling/AttachHis/9bdee60f-06e1-4486-a933-6c890b79602a.pdf | C46: Marico Reg 30: acquisition of balance stake in Zed Lifestyle (Beardo) | D46: BSE / Marico Ltd | E46: T1 | F46: 2020-06-30 | G46: 2026-10-10 | H46: pdf: sources/pdf/S045_marico_beardo_2020.pdf
A47: S046 | B47: https://www.bseindia.com/xml-data/corpfiling/AttachHis/b14ca7a2-bf6b-4ee2-be75-9db8bae2c8f4.pdf | C47: Marico Reg 30: investment in Apcos Naturals (Just Herbs) | D47: BSE / Marico Ltd | E47: T1 | F47: 2021-07-14 | G47: 2026-10-10 | H47: pdf: sources/pdf/S046_marico_justherbs_2021.pdf
A48: S047 | B48: https://www.bseindia.com/xml-data/corpfiling/AttachHis/c8bac14c-bf1e-40ff-b341-f9189b080cd5.pdf | C48: Marico Reg 30: Just Herbs update (Jul 2022) | D48: BSE / Marico Ltd | E48: T1 | F48: 2022-07-04 | G48: 2026-10-10 | H48: pdf: sources/pdf/S047_marico_justherbs_202207.pdf
A49: S048 | B49: https://www.bseindia.com/xml-data/corpfiling/AttachHis/2554f0eb-32ae-4cf6-b15e-ade482dfd325.pdf | C49: Marico Reg 30: Just Herbs update (Nov 2022) | D49: BSE / Marico Ltd | E49: T1 | F49: 2022-11-12 | G49: 2026-10-10 | H49: pdf: sources/pdf/S048_marico_justherbs_202211.pdf
A50: S049 | B50: https://www.bseindia.com/xml-data/corpfiling/AttachHis/baa7cd35-b0c5-4f30-98c4-8cdadd609bfa.pdf | C50: Marico Reg 30: agreement to acquire balance 40% of Apcos Naturals | D50: BSE / Marico Ltd | E50: T1 | F50: 2024-09-06 | G50: 2026-10-10 | H50: pdf: sources/pdf/S049_marico_justherbs_202409.pdf
A51: S050 | B51: https://www.bseindia.com/xml-data/corpfiling/AttachHis/2dbf8f6b-cc7a-472b-8998-a772eaf85dfc.pdf | C51: Marico Reg 30: Just Herbs balance 40% completed | D51: BSE / Marico Ltd | E51: T1 | F51: 2024-09-17 | G51: 2026-10-10 | H51: pdf: sources/pdf/S050_marico_justherbs_100.pdf
A52: S051 | B52: https://www.bseindia.com/xml-data/corpfiling/AttachHis/27472172-f501-43b4-bfea-2d22eda5b637.pdf | C52: Marico Reg 30: investment in HW Wellness (True Elements) | D52: BSE / Marico Ltd | E52: T1 | F52: 2022-05-23 | G52: 2026-10-10 | H52: pdf: sources/pdf/S051_marico_trueelements_2022.pdf
A53: S052 | B53: https://www.bseindia.com/xml-data/corpfiling/AttachHis/a04fbe19-bb73-4ccc-83df-c1992aab64ad.pdf | C53: Marico Reg 30: agreement to acquire balance 46.02% of HW Wellness | D53: BSE / Marico Ltd | E53: T1 | F53: 2025-09-11 | G53: 2026-10-10 | H53: pdf: sources/pdf/S052_marico_trueelements_202509.pdf
A54: S053 | B54: https://www.bseindia.com/xml-data/corpfiling/AttachHis/a081acb0-7eaf-4037-b471-5921ae07d2d9.pdf | C54: Marico Reg 30: True Elements balance stake completed | D54: BSE / Marico Ltd | E54: T1 | F54: 2025-10-17 | G54: 2026-10-10 | H54: pdf: sources/pdf/S053_marico_trueelements_100.pdf
A55: S054 | B55: https://www.bseindia.com/xml-data/corpfiling/AttachHis/32224d77-4090-4b97-9c64-a9b3319a3b5e.pdf | C55: Marico Reg 30: agreement to acquire up to 58% of Satiya Nutraceuticals (Plix) | D55: BSE / Marico Ltd | E55: T1 | F55: 2023-07-26 | G55: 2026-10-10 | H55: pdf: sources/pdf/S054_marico_plix_2023.pdf
A56: S055 | B56: https://www.bseindia.com/xml-data/corpfiling/AttachHis/0d48ca42-672c-4f3e-8f93-15796bbabc48.pdf | C56: Marico Reg 30: Plix first tranche completed | D56: BSE / Marico Ltd | E56: T1 | F56: 2023-11-30 | G56: 2026-10-10 | H56: pdf: sources/pdf/S055_marico_plix_202311.pdf
A57: S056 | B57: https://www.bseindia.com/xml-data/corpfiling/AttachHis/fcae2276-5e43-4f45-a442-d3f227b724d1.pdf | C57: Marico Reg 30: Plix update (May 2025) | D57: BSE / Marico Ltd | E57: T1 | F57: 2025-05-31 | G57: 2026-10-10 | H57: pdf: sources/pdf/S056_marico_plix_202505.pdf
... A63: S062 | B63: https://www.bseindia.com/xml-data/corpfiling/AttachHis/8999b2a1-88be-4a37-a71c-c21ec50cac18.pdf | C63: Marico Reg 30: Zea Maize (4700BC) completion | D63: BSE / Marico Ltd | E63: T1 | F63: 2026-01-29 | G63: 2026-10-10 | H63: pdf: sources/pdf/S062_marico_4700bc_completion.pdf
A64: S063 | B64: https://www.storyboard18.com/brand-marketing/marico-integrates-rs-214-crore-beardo-business-into-parent-88319.htm | C64: Marico integrates Rs 214-crore Beardo business into parent | D64: Storyboard18 | E64: T3 | G64: 2026-10-10 | H64: html
A65: S064 | B65: https://www.bseindia.com/xml-data/corpfiling/AttachHis/6d4d60c0-4a9c-4431-a7f9-3667a8836d03.pdf | C65: Marico Reg 30 intimation 2026-01-27 (Zed Lifestyle/Beardo integration) | D65: BSE / Marico Ltd | E65: T1 | F65: 2026-01-27 | G65: 2026-10-10 | H65: pdf: sources/pdf/S064_marico_beardo_integration.pdf
A66: S065 | B66: https://www.bseindia.com/xml-data/corpfiling/AttachHis/479e8327-282f-4bb6-9a41-a7d3ffb13143.pdf | C66: Dabur Reg 30: proposed acquisition of 51% of Badshah Masala | D66: BSE / Dabur India Ltd | E66: T1 | F66: 2022-10-26 | G66: 2026-10-10 | H66: pdf: sources/pdf/S065_dabur_badshah_2022.pdf
A67: S066 | B67: https://www.bseindia.com/xml-data/corpfiling/AttachHis/76ef4351-9f81-4266-8677-4b4f3d375f5f.pdf | C67: Dabur Reg 30: completion of 51% of Badshah Masala | D67: BSE / Dabur India Ltd | E67: T1 | F67: 2023-01-02 | G67: 2026-10-10 | H67: pdf: sources/pdf/S066_dabur_badshah_completion.pdf
A68: S067 | B68: https://www.bseindia.com/xml-data/corpfiling/AttachHis/cadeef7a-138a-4e88-abf5-2285a34d9383.pdf | C68: Dabur Reg 30: implementation agreement with Sesa Care | D68: BSE / Dabur India Ltd | E68: T1 | F68: 2024-10-30 | G68: 2026-10-10 | H68: pdf: sources/pdf/S067_dabur_sesa_2024.pdf
A69: S068 | B69: https://www.bseindia.com/xml-data/corpfiling/AttachHis/09aaabc3-d276-44a4-b240-f217c79c7333.pdf | C69: GCPL Reg 30: acquisition of FMCG business of Raymond Consumer Care | D69: BSE / Godrej Consumer Products Ltd | E69: T1 | F69: 2023-04-27 | G69: 2026-10-10 | H69: pdf: sources/pdf/S068_gcpl_raymond_2023.pdf
A70: S069 | B70: https://www.bseindia.com/xml-data/corpfiling/AttachHis/7a1670e1-56f8-40f2-9abc-d3e4dc0d7af1.pdf | C70: GCPL Reg 30: completion of Raymond Consumer Care FMCG acquisition | D70: BSE / Godrej Consumer Products Ltd | E70: T1 | F70: 2023-05-08 | G70: 2026-10-10 | H70: pdf: sources/pdf/S069_gcpl_raymond_completion.pdf
A71: S070 | B71: https://www.bseindia.com/xml-data/corpfiling/AttachHis/76411a7d-0b48-4946-ab11-9d6a668ffbc6.pdf | C71: GCPL Reg 30 intimation 2025-09-19 | D71: BSE / Godrej Consumer Products Ltd | E71: T1 | F71: 2025-09-19 | G71: 2026-10-10 | H71: pdf: sources/pdf/S070_gcpl_20250919.pdf. NOT RELEVANT to Tab A: equity infusion into GCPL's Mauritius holding co
A72: S071 | B72: https://www.bseindia.com/xml-data/corpfiling/AttachHis/d84288eb-224d-4315-8ca8-0327ab543ee2.pdf | C72: GCPL Reg 30 intimation 2025-10-31 | D72: BSE / Godrej Consumer Products Ltd | E72: T1 | F72: 2025-10-31 | G72: 2026-10-10 | H72: pdf: sources/pdf/S071_gcpl_20251031.pdf
A73: S072 | B73: https://www.bseindia.com/xml-data/corpfiling/AttachHis/3ebf3b38-c013-4dba-a534-5d99fcf99841.pdf | C73: GCPL: completion of acquisition of FMCG business of Triology Solutions | D73: BSE / Godrej Consumer Products Ltd | E73: T1 | F73: 2025-11-10 | G73: 2026-10-10 | H73: pdf: sources/pdf/S072_gcpl_triology_completion.pdf
A74: S073 | B74: https://www.bseindia.com/xml-data/corpfiling/AttachHis/eafdff8f-cb1c-455f-9402-fff424b8ee37.pdf | C74: GCPL Reg 30 update 2026-07-22 | D74: BSE / Godrej Consumer Products Ltd | E74: T1 | F74: 2026-07-22 | G74: 2026-10-10 | H74: pdf: sources/pdf/S073_gcpl_20260722.pdf. NOT RELEVANT to Tab A: primary infusion into Godrej Pet Care (own subsidiary). TAB B LEAD: GCPL-built pet care; FY26 revenue Rs 222.1 lakh
A75: S074 | B75: https://www.bseindia.com/xml-data/corpfiling/AttachHis/9e4fa0ca-46f8-423c-9994-928347978912.pdf | C75: Dabur: Board approves scheme of amalgamation of Sesa Care | D75: BSE / Dabur India Ltd | E75: T1 | F75: 2025-05-26 | G75: 2026-10-10 | H75: pdf: sources/pdf/S074_dabur_sesa_scheme.pdf
A76: S075 | B76: https://www.bseindia.com/xml-data/corpfiling/AttachHis/48e68f82-81f8-4830-8909-261103c45d60.pdf | C76: Dabur: Sesa Care amalgamation NCLT sanction / effective update | D76: BSE / Dabur India Ltd | E76: T1 | F76: 2026-09-26 | G76: 2026-10-10 | H76: pdf: sources/pdf/S075_dabur_sesa_effective.pdf
A77: S076 | B77: https://www.outlookbusiness.com/corporate/dabur-q4fy26-cons-pat-rises-15-yoy-550-dividend-announced | C77: Dabur Q4FY26: Cons PAT Rises 15% YoY | D77: Outlook Business | E77: T3 | G77: 2026-10-10 | H77: html
A78: S077 | B78: https://www.bseindia.com/xml-data/corpfiling/AttachHis/b725c364-3c3d-43b0-b74d-533581aca349.pdf | C78: Nykaa board outcome 2022-04-22 (acquisition approval) | D78: BSE / FSN E-Commerce Ventures Ltd (Nykaa) | E78: T1 | F78: 2022-04-22 | G78: 2026-10-10 | H78: pdf: sources/pdf/S077_nykaa_board_20220422.pdf
A79: S078 | B79: https://www.bseindia.com/xml-data/corpfiling/AttachHis/7fe70c62-4b66-426f-ae2d-bfde5e8d40ef.pdf | C79: Nykaa Reg 30 disclosure 2022-07-29 | D79: BSE / FSN E-Commerce Ventures Ltd (Nykaa) | E79: T1 | F79: 2022-07-29 | G79: 2026-10-10 | H79: pdf: sources/pdf/S078_nykaa_20220729.pdf. NOT RELEVANT: Nykaa Foundation (Section 8 CSR company) incorporation
A80: S079 | B80: https://www.bseindia.com/xml-data/corpfiling/AttachHis/07eae3e3-fc2e-44b3-9709-da47560b4f0a.pdf | C80: Nykaa Reg 30: further acquisition in Dot & Key and Earth Rhythm (Aug 2024) | D80: BSE / FSN E-Commerce Ventures Ltd (Nykaa) | E80: T1 | F80: 2024-08-13 | G80: 2026-10-10 | H80: pdf: sources/pdf/S079_nykaa_dotkey_earthrhythm_202408.pdf
A81: S080 | B81: https://www.bseindia.com/xml-data/corpfiling/AttachHis/c81a6ea5-3ffc-41a4-97cb-f3e5d0efacdd.pdf | C81: Nykaa: completion of 39% of Dot & Key Wellness | D81: BSE / FSN E-Commerce Ventures Ltd (Nykaa) | E81: T1 | F81: 2024-09-21 | G81: 2026-10-10 | H81: pdf: sources/pdf/S080_nykaa_dotkey_39.pdf
A82: S081 | B82: https://www.bseindia.com/xml-data/corpfiling/AttachHis/c0d014e8-a963-408c-9c19-49ef45a09f93.pdf | C82: Nykaa: update on Earth Rhythm stake increase | D82: BSE / FSN E-Commerce Ventures Ltd (Nykaa) | E82: T1 | F82: 2024-11-26 | G82: 2026-10-10 | H82: pdf: sources/pdf/S081_nykaa_earthrhythm_202411.pdf
A83: S082 | B83: https://www.bseindia.com/xml-data/corpfiling/AttachHis/f50adba5-2df3-4371-b29f-fd0027a357b7.pdf | C83: Nykaa: completion of 2nd tranche into Earth Rhythm | D83: BSE / FSN E-Commerce Ventures Ltd (Nykaa) | E83: T1 | F83: 2025-06-09 | G83: 2026-10-10 | H83: pdf: sources/pdf/S082_nykaa_earthrhythm_202506.pdf
